Workbook

Sheet Resumen
A1: CONTROL OPERATIVO ORVANN | D1: Recordatorios | F1: Pendientes
A2: Última actualización | B2: 46067 | D2: Cuenta BC (empresarial o la de Julieta) - Celular y whatsapp para historias (Grupo de difusión) | F2: ITEM | G2: Valor | H2: NOTAS
D3: Mercado Pago y que más necesitamos para funcionar como pyme | F3: Tubo perchero | G3: 150000
A4: RESUMEN FINANCIERO | D4: Agregar proyección al por mayor y packs (Como se vende asi y como conversa con gran diferencia de precio) | F4: Ganchos | G4: 80000
A5: Inventario a costo: | B5: =Inventario!F2 -> 9858000 | D5: Proyección más clara de punto de equilibrio | F5: Espejo cuerpo completo | G5: 250000
A6: Inventario a precio venta: | B6: =Inventario!G2 -> 19460000 | D6: Como funciona shopify | F6: Estantería | H6: Viene en obra ?
A7: Ventas del mes: | B7: =SUMIF(Ventas!A:A,">="&DATE(YEAR(TODAY()),MONTH(TODAY()),1),Ventas!E:E) -> 320000 | D7: Automatizaciones de: Atención al cliente, pedidos, inventario, contabilidad y logística (Cómo la vamos a hacer) | F7: Sillas | G7: 50000
A8: Gastos del mes: | B8: =SUMIF(Gastos!A:A,">="&DATE(YEAR(TODAY()),MONTH(TODAY()),1),Gastos!C:C) -> 4791800 | D8: Enviar instagram a gente y compartir | F8: Luces LED | G8: 0
A9: Cuentas por pagar: | B9: =SUMIF('Pedidos Proveedores'!G:G,"Pendiente",'Pedidos Proveedores'!F:F) -> 9618000 | D9: Que es pixel y como se usa el inventario digital de meta (Inst y Facebook) | F9: Lamparas ? | G9: 0
A10: Utilidad bruta mes: | B10: =B7-SUMIF(Ventas!A:A,">="&DATE(YEAR(TODAY()),MONTH(TODAY()),1),Ventas!D:D)-B8 -> -4631800 | D10: Tema de tener solo uan persona trabajando (Inseguridad) | F10: Cámara seguridad | G10: 250000
D11: Quiero tener algo más dinámico de modelo financiero | F11: Alarma | G11: 120000
D12: Cerrar cuentas pendientes | F12: Candados | G12: 30000
A13: ALERTAS | F13: Registradora | G13: 120000
A14: Productos con stock bajo (<3): | B14: =COUNTIF(Inventario!G:G,"<3")-1 -> 79 | F14: Datafono | G14: 120000
A15: Pedidos pendientes de pago: | B15: =COUNTIF('Pedidos Proveedores'!G:G,"Pendiente") -> 10 | F15: Celular | G15: 300000
F16: Bafle / Parlante | G16: 350000
F17: Router | G17: 40000
A18: INDICADORES CLAVE DE DESEMPEÑO | F18: Ventilador | G18: 100000
D19: Otras referencias (Conocidas pero de nicho) | F19: Kit aseo | G19: 60000
A20: Ticket promedio: | B20: =IFERROR(SUMIF(Ventas!A:A,">="&DATE(YEAR(TODAY()),MONTH(TODAY()),1),Ventas!E:E)/COUNTIF(Ventas!A:A,">="&DATE(YEAR(TODAY()),MONTH(TODAY()),1)),0) -> 160000 | D20: Pulp Fiction (1994) | F20: Tapetes ? | G20: 100000
A21: Prendas vendidas (mes): | B21: =COUNTIF(Ventas!A:A,">="&DATE(YEAR(TODAY()),MONTH(TODAY()),1)) -> 2 | D21: Pedro navaja | F21: Toldo | G21: 500000
A22: Margen bruto %: | B22: =IFERROR((SUMIF(Ventas!A:A,">="&DATE(YEAR(TODAY()),MONTH(TODAY()),1),Ventas!E:E)-SUMIF(Ventas!A:A,">="&DATE(YEAR(TODAY()),MONTH(TODAY()),1),Ventas!D:D))/SUMIF(Ventas!A:A,">="&DATE(YEAR(TODAY()),MONTH(TODAY()),1),Ventas!E:E),0) -> 0.5 | D22: Léon: The Professional
A23: Rotación inventario: | B23: =IFERROR(COUNTIF(Ventas!A:A,">="&DATE(YEAR(TODAY()),MONTH(TODAY()),1))/Inventario!E2,0) -> 0.010869565 | C23: Mide cuántas veces se vende y se reemplaza el inventario en un período de un mes (al no haber ventas, es cero). | D23: Ciudad de Dios | F23: Basura | G23: 30000
A24: Días de inventario: | B24: =IFERROR(Inventario!E2/(COUNTIF(Ventas!A:A,">="&DATE(YEAR(TODAY()),MONTH(TODAY()),1))/30),0) -> 2760 | C24: Mide cuántos días tomaría vender el inventario actual (al no haber ventas, es cero). | D24: Charles Bukowski (Literatura Cruda) | F24: Letrero exterior | G24: 250000 | H24: Viene en obra ?
D25: Héctor Lavoe. Estilo "Vinyl Cover" | F25: Decoración (Cuadros, etc) | G25: 150000
D26: Gabo y Cien Años de Soledad | F26: Plantas | G26: 50000
A27: PUNTO DE EQUILIBRIO | D27: Blade Runner (1982). | F27: Señalización ? | G27: 50000
A28: Costos fijos mensuales: | B28: ='Costos Fijos'!B12 -> 1914900 | D28: Mercedes Sosa y LA FANIA. Volver a los 17 | F28: Extintor | G28: 30000
A29: Margen promedio por prenda: | B29: =IFERROR(AVERAGE(Inventario!E5:E212),0) -> 0.51927438 | D29: Taxi Driver | F29: Decoración y extras | G29: 150000
A30: Precio promedio venta: | B30: =IFERROR(AVERAGE(Inventario!D5:D212),0) -> 107806.12 | D30: Fight Club
A31: Prendas/mes para equilibrio: | B31: =IFERROR(ROUNDUP(B28/(B30*B29),0),0) -> 35 | D31: Scarface | F31: TOTAL | G31: =+SUM(G3:G29) -> 3330000
A32: Prendas/día para equilibrio: | B32: =ROUNDUP(B31/26,0) -> 2 | D32: Vendedora de Rosas
D33: Notorius BIG
A34: RESUMEN FINANCIERO | D34: Celia Cruz
A35: Total deudas | D35: Mike Tyson
A36: Total aportes socios | D36: Principe de Bel Air
D37: Jackass
A38: HORARIOS | D38: Friends
A39: Encargado | B39: Horas Semanales | C39: Días | D39: MTV
A40: JP | B40: =4.5*5 -> 22.5 | C40: L-V 2:30 a 7pm | D40: Play Station 1
A41: Kathe | B41: =B40 -> 22.5 | C41: L-V 10:00 a 2:30pm | D41: BackStreet Boys
A42: Andrés | B42: =9*2 -> 18 | C42: S y D 10:00 a 7:00pm | D42: Punk
D43: Eminem
D44: Tupac y BIG
D45: Cerati y Rock Español (Soda, cadillacs,caifanes)
D46: Mi pobre angelito
D47: manos de tijera
D48: Titanic
D49: Sexto sentido
D50: Marc Anthony
D51: Grupo niche
D52: Gran combo de las estrellas
D53: Rocky
D54: Canserbero (Raperos canon)
... D116: Andy Warhol

Sheet Inventario
A1: INVENTARIO | E1: Total Stock: | F1: Valor Costo: | G1: Valor Venta:
E2: =SUM(G5:G1012) -> 184 | F2: =SUMPRODUCT(C5:C1012,G5:G1012) -> 9858000 | G2: =SUMPRODUCT(D5:D1012,G5:G1012) -> 19460000
F3: =SUM(F5:F306) -> 184 | G3: =SUM(G5:G306) -> 184
A4: SKU | B4: Producto | C4: Costo | D4: Precio Venta | E4: Margen % | F4: Entradas | G4: Stock Actual | H4: Notas
A5: CAM-OVS-NEG-S | B5: Camisa Oversize Peruana S Negro | C5: 37000 | D5: 75000 | E5: =IF(D5>0,(D5-C5)/D5,0) -> 0.50666667 | F5: 0 | G5: 0 | H5: BASICO
A6: CAM-OVS-NEG-M | B6: Camisa Oversize Peruana M Negro | C6: 37000 | D6: 75000 | E6: =IF(D6>0,(D6-C6)/D6,0) -> 0.50666667 | F6: 0 | G6: 0 | H6: BASICO
A7: CAM-OVS-NEG-L | B7: Camisa Oversize Peruana L Negro | C7: 37000 | D7: 75000 | E7: =IF(D7>0,(D7-C7)/D7,0) -> 0.50666667 | F7: 0 | G7: 0 | H7: BASICO
A8: CAM-OVS-NEG-XL | B8: Camisa Oversize Peruana XL Negro | C8: 37000 | D8: 75000 | E8: =IF(D8>0,(D8-C8)/D8,0) -> 0.50666667 | F8: 0 | G8: 0 | H8: BASICO
A9: CAM-OVS-BLA-S | B9: Camisa Oversize Peruana S Blanco | C9: 37000 | D9: 75000 | E9: =IF(D9>0,(D9-C9)/D9,0) -> 0.50666667 | F9: 0 | G9: 0 | H9: BASICO
A10: CAM-OVS-BLA-M | B10: Camisa Oversize Peruana M Blanco | C10: 37000 | D10: 75000 | E10: =IF(D10>0,(D10-C10)/D10,0) -> 0.50666667 | F10: 0 | G10: 0 | H10: BASICO
A11: CAM-OVS-BLA-L | B11: Camisa Oversize Peruana L Blanco | C11: 37000 | D11: 75000 | E11: =IF(D11>0,(D11-C11)/D11,0) -> 0.50666667 | F11: 0 | G11: 0 | H11: BASICO
A12: CAM-OVS-BLA-XL | B12: Camisa Oversize Peruana XL Blanco | C12: 37000 | D12: 75000 | E12: =IF(D12>0,(D12-C12)/D12,0) -> 0.50666667 | F12: 0 | G12: 0 | H12: BASICO
A13: CAM-OVS-PER-S | B13: Camisa Oversize Peruana S Perla | C13: 37000 | D13: 75000 | E13: =IF(D13>0,(D13-C13)/D13,0) -> 0.50666667 | F13: 0 | G13: 0 | H13: BASICO
A14: CAM-OVS-PER-M | B14: Camisa Oversize Peruana M Perla | C14: 37000 | D14: 75000 | E14: =IF(D14>0,(D14-C14)/D14,0) -> 0.50666667 | F14: 0 | G14: 0 | H14: BASICO
A15: CAM-OVS-PER-L | B15: Camisa Oversize Peruana L Perla | C15: 37000 | D15: 75000 | E15: =IF(D15>0,(D15-C15)/D15,0) -> 0.50666667 | F15: 0 | G15: 0 | H15: BASICO
A16: CAM-OVS-PER-XL | B16: Camisa Oversize Peruana XL Perla | C16: 37000 | D16: 75000 | E16: =IF(D16>0,(D16-C16)/D16,0) -> 0.50666667 | F16: 0 | G16: 0 | H16: BASICO
... A38: HOOD-ACID-L | B38: Hoodie L Acid Wash Gris | C38: 120000 | D38: 200000 | E38: =IF(D38>0,(D38-C38)/D38,0) -> 0.4 | F38: 12 | G38: 12 | H38: BASICO
A39: CHOM-NEG-S | B39: Chompa Capucha S Negro | C39: ='Pedidos Proveedores'!$E$3 -> 90000 | D39: 200000 | E39: =IF(D39>0,(D39-C39)/D39,0) -> 0.55 | F39: 0 | G39: 0 | H39: BASICO
A40: CHOM-NEG-M | B40: Chompa Capucha M Negro | C40: ='Pedidos Proveedores'!$E$3 -> 90000 | D40: 200000 | E40: =IF(D40>0,(D40-C40)/D40,0) -> 0.55 | F40: 0 | G40: 0 | H40: BASICO
A41: CHOM-NEG-L | B41: Chompa Capucha L Negro | C41: ='Pedidos Proveedores'!$E$3 -> 90000 | D41: 200000 | E41: =IF(D41>0,(D41-C41)/D41,0) -> 0.55 | F41: 0 | G41: 0 | H41: BASICO
A42: CHOM-PER-S | B42: Chompa Capucha S Perla | C42: ='Pedidos Proveedores'!$E$3 -> 90000 | D42: 200000 | E42: =IF(D42>0,(D42-C42)/D42,0) -> 0.55 | F42: 0 | G42: 0 | H42: BASICO
A43: CHOM-PER-M | B43: Chompa Capucha M Perla | C43: ='Pedidos Proveedores'!$E$3 -> 90000 | D43: 200000 | E43: =IF(D43>0,(D43-C43)/D43,0) -> 0.55 | F43: 0 | G43: 0 | H43: BASICO
A44: CHOM-PER-L | B44: Chompa Capucha L Perla | C44: ='Pedidos Proveedores'!$E$3 -> 90000 | D44: 200000 | E44: =IF(D44>0,(D44-C44)/D44,0) -> 0.55 | F44: 4 | G44: 4 | H44: BASICO
A45: CHOM-VERD-S | B45: Chompa Capucha S Verde Botella | C45: ='Pedidos Proveedores'!$E$3 -> 90000 | D45: 200000 | E45: =IF(D45>0,(D45-C45)/D45,0) -> 0.55 | F45: 0 | G45: 0 | H45: BASICO
A46: CHOM-VERD-M | B46: Chompa Capucha M Verde Botella | C46: ='Pedidos Proveedores'!$E$3 -> 90000 | D46: 200000 | E46: =IF(D46>0,(D46-C46)/D46,0) -> 0.55 | F46: 0 | G46: 0 | H46: BASICO
A47: CHOM-VERD-L | B47: Chompa Capucha L Verde Botella | C47: ='Pedidos Proveedores'!$E$3 -> 90000 | D47: 200000 | E47: =IF(D47>0,(D47-C47)/D47,0) -> 0.55 | F47: 0 | G47: 0 | H47: BASICO
A48: CHOM-PLOM-S | B48: Chompa Capucha S Plomo Plata | C48: ='Pedidos Proveedores'!$E$3 -> 90000 | D48: 200000 | E48: =IF(D48>0,(D48-C48)/D48,0) -> 0.55 | F48: 0 | G48: 0 | H48: BASICO
A49: CHOM-PLOM-M | B49: Chompa Capucha M Plomo Plata | C49: ='Pedidos Proveedores'!$E$3 -> 90000 | D49: 200000 | E49: =IF(D49>0,(D49-C49)/D49,0) -> 0.55 | F49: 0 | G49: 0 | H49: BASICO
A50: CHOM-PLOM-L | B50: Chompa Capucha L Plomo Plata | C50: ='Pedidos Proveedores'!$E$3 -> 90000 | D50: 200000 | E50: =IF(D50>0,(D50-C50)/D50,0) -> 0.55 | F50: 0 | G50: 0 | H50: BASICO
A51: BUZ-OVS-NEG-M | B51: Buzo Cuello Redondo Oversized M Negro | C51: 55000 | D51: 120000 | E51: =IF(D51>0,(D51-C51)/D51,0) -> 0.54166667 | F51: 2 | G51: 2 | H51: BASICO
A52: BUZ-OVS-NEG-L | B52: Buzo Cuello Redondo Oversized L Negro | C52: 55000 | D52: 120000 | E52: =IF(D52>0,(D52-C52)/D52,0) -> 0.54166667 | F52: 4 | G52: 4 | H52: BASICO
A53: BUZ-OVS-NEG-XL | B53: Buzo Cuello Redondo Oversized XL Negro | C53: 55000 | D53: 120000 | E53: =IF(D53>0,(D53-C53)/D53,0) -> 0.54166667 | F53: 4 | G53: 4 | H53: BASICO
A54: BUZ-OVS-BEIG-M | B54: Buzo Cuello Redondo Oversized M Beige | C54: 55000 | D54: 120000 | E54: =IF(D54>0,(D54-C54)/D54,0) -> 0.54166667 | F54: 2 | G54: 2 | H54: BASICO
A55: BUZ-OVS-BEIG-L | B55: Buzo Cuello Redondo Oversized L Beige | C55: 55000 | D55: 120000 | E55: =IF(D55>0,(D55-C55)/D55,0) -> 0.54166667 | F55: 2 | G55: 2 | H55: BASICO
A56: BUZ-OVS-BEIG-XL | B56: Buzo Cuello Redondo Oversized XL Beige | C56: 55000 | D56: 120000 | E56: =IF(D56>0,(D56-C56)/D56,0) -> 0.54166667 | F56: 2 | G56: 2 | H56: BASICO
A57: BUZ-OVS-NEG-2XL | B57: Buzo Cuello Redondo Oversized 2XL Negro | C57: 55000 | D57: 120000 | E57: =IF(D57>0,(D57-C57)/D57,0) -> 0.54166667 | F57: 2 | G57: 2 | H57: BASICO
A58: BUZ-OVS-BEIG-2XL | B58: Buzo Cuello Redondo Oversized 2XL Beige | C58: 55000 | D58: 120000 | E58: =IF(D58>0,(D58-C58)/D58,0) -> 0.54166667 | F58: 2 | G58: 2 | H58: BASICO
A59: BUZ-OVS-CAF-L | B59: Buzo Cuello Redondo Oversized L Café | C59: 55000 | D59: 120000 | E59: =IF(D59>0,(D59-C59)/D59,0) -> 0.54166667 | F59: 2 | G59: 2 | H59: BASICO
A60: BUZ-OVS-CAF-XL | B60: Buzo Cuello Redondo Oversized XL Café | C60: 55000 | D60: 120000 | E60: =IF(D60>0,(D60-C60)/D60,0) -> 0.54166667 | F60: 2 | G60: 2 | H60: BASICO
A61: JOG-NEG-M | B61: Jogger Largo M Negro | C61: 55000 | D61: 100000 | E61: =IF(D61>0,(D61-C61)/D61,0) -> 0.45 | F61: 4 | G61: 4 | H61: BASICO
A62: JOG-NEG-L | B62: Jogger Largo L Negro | C62: 55000 | D62: 100000 | E62: =IF(D62>0,(D62-C62)/D62,0) -> 0.45 | F62: 4 | G62: 4 | H62: BASICO
... A69: JOG-CAF-XL | B69: Jogger Largo XL Café | C69: 55000 | D69: 100000 | E69: =IF(D69>0,(D69-C69)/D69,0) -> 0.45 | F69: 2 | G69: 2 | H69: BASICO
A70: CHA-NEG-M | B70: Chaqueta Cortavientos M Negro | C70: ='Pedidos Proveedores'!$E$8 -> 40000 | D70: 120000 | E70: =IF(D70>0,(D70-C70)/D70,0) -> 0.66666667 | F70: 4 | G70: 4 | H70: BASICO
A71: CHA-NEG-L | B71: Chaqueta Cortavientos L Negro | C71: ='Pedidos Proveedores'!$E$8 -> 40000 | D71: 120000 | E71: =IF(D71>0,(D71-C71)/D71,0) -> 0.66666667 | F71: 4 | G71: 4 | H71: BASICO
A72: CHA-NEG-XL | B72: Chaqueta Cortavientos XL Negro | C72: ='Pedidos Proveedores'!$E$8 -> 40000 | D72: 120000 | E72: =IF(D72>0,(D72-C72)/D72,0) -> 0.66666667 | F72: 4 | G72: 4 | H72: BASICO
A73: CHA-GRICLA-M | B73: Chaqueta Cortavientos M Gris Claro | C73: ='Pedidos Proveedores'!$E$8 -> 40000 | D73: 120000 | E73: =IF(D73>0,(D73-C73)/D73,0) -> 0.66666667 | F73: 2 | G73: 2 | H73: BASICO
A74: CHA-GRICLA-L | B74: Chaqueta Cortavientos L Gris Claro | C74: ='Pedidos Proveedores'!$E$8 -> 40000 | D74: 120000 | E74: =IF(D74>0,(D74-C74)/D74,0) -> 0.66666667 | F74: 2 | G74: 2 | H74: BASICO
A75: CHA-GRICLA-XL | B75: Chaqueta Cortavientos XL Gris Claro | C75: ='Pedidos Proveedores'!$E$8 -> 40000 | D75: 120000 | E75: =IF(D75>0,(D75-C75)/D75,0) -> 0.66666667 | F75: 2 | G75: 2 | H75: BASICO
A76: CHA-VERNEG-M | B76: Chaqueta Cortavientos M Verde Botella/Negro | C76: ='Pedidos Proveedores'!$E$8 -> 40000 | D76: 120000 | E76: =IF(D76>0,(D76-C76)/D76,0) -> 0.66666667 | F76: 2 | G76: 2 | H76: BASICO
A77: CHA-GRIOSC-M | B77: Chaqueta Cortavientos M Gris Oscuro | C77: ='Pedidos Proveedores'!$E$8 -> 40000 | D77: 120000 | E77: =IF(D77>0,(D77-C77)/D77,0) -> 0.66666667 | F77: 2 | G77: 2 | H77: BASICO
A78: CHA-GRIOSC-L | B78: Chaqueta Cortavientos L Gris Oscuro | C78: ='Pedidos Proveedores'!$E$8 -> 40000 | D78: 120000 | E78: =IF(D78>0,(D78-C78)/D78,0) -> 0.66666667 | F78: 2 | G78: 2 | H78: BASICO
A79: CHA-GRIOSC-XL | B79: Chaqueta Cortavientos XL Gris Oscuro | C79: ='Pedidos Proveedores'!$E$8 -> 40000 | D79: 120000 | E79: =IF(D79>0,(D79-C79)/D79,0) -> 0.66666667 | F79: 2 | G79: 2 | H79: BASICO
A80: CHA-MOSTNEG-L | B80: Chaqueta Cortavientos L Mostaza/Negro | C80: ='Pedidos Proveedores'!$E$8 -> 40000 | D80: 120000 | E80: =IF(D80>0,(D80-C80)/D80,0) -> 0.66666667 | F80: 2 | G80: 2 | H80: BASICO
A81: CHA-MOSTNEG-XL | B81: Chaqueta Cortavientos XL Mostaza/Negro | C81: ='Pedidos Proveedores'!$E$8 -> 40000 | D81: 120000 | E81: =IF(D81>0,(D81-C81)/D81,0) -> 0.66666667 | F81: 2 | G81: 2 | H81: BASICO
... A84: CHA-GRINEG-XL | B84: Chaqueta Cortavientos XL Gris Claro/Negro | C84: ='Pedidos Proveedores'!$E$8 -> 40000 | D84: 120000 | E84: =IF(D84>0,(D84-C84)/D84,0) -> 0.66666667 | F84: 2 | G84: 2 | H84: BASICO
A85: SUD-NEG-L | B85: Sudadera Bota Recta M Negro | C85: 55000 | D85: 90000 | E85: =IF(D85>0,(D85-C85)/D85,0) -> 0.38888889 | F85: 2 | G85: 2 | H85: BASICO
A86: SUD-NEG-L | B86: Sudadera Bota Recta L Negro | C86: 55000 | D86: 90000 | E86: =IF(D86>0,(D86-C86)/D86,0) -> 0.38888889 | F86: 2 | G86: 2 | H86: BASICO
A87: SUD-NEG-L | B87: Sudadera Bota Recta XL Negro | C87: 55000 | D87: 90000 | E87: =IF(D87>0,(D87-C87)/D87,0) -> 0.38888889 | F87: 2 | G87: 2 | H87: BASICO
A88: SUD-BEIG-M | B88: Sudadera Bota Recta M Beige | C88: 55000 | D88: 90000 | E88: =IF(D88>0,(D88-C88)/D88,0) -> 0.38888889 | F88: 1 | G88: 1 | H88: BASICO
A89: SUD-BEIG-XL | B89: Sudadera Bota Recta XL Beige | C89: 55000 | D89: 90000 | E89: =IF(D89>0,(D89-C89)/D89,0) -> 0.38888889 | F89: 2 | G89: 2 | H89: BASICO
A90: SUD-CAF-M | B90: Sudadera Bota Recta M Café | C90: 55000 | D90: 90000 | E90: =IF(D90>0,(D90-C90)/D90,0) -> 0.38888889 | F90: 1 | G90: 1 | H90: BASICO
A91: SUD-CAF-L | B91: Sudadera Bota Recta L Café | C91: 55000 | D91: 90000 | E91: =IF(D91>0,(D91-C91)/D91,0) -> 0.38888889 | F91: 2 | G91: 2 | H91: BASICO
A92: PANT-NEG-M | B92: Pantaloneta M Negro | C92: 45000 | D92: 90000 | E92: =IF(D92>0,(D92-C92)/D92,0) -> 0.5 | F92: 1 | G92: 1 | H92: BASICO
A93: PANT-NEG-L | B93: Pantaloneta L Negro | C93: 45000 | D93: 90000 | E93: =IF(D93>0,(D93-C93)/D93,0) -> 0.5 | F93: 1 | G93: 1 | H93: BASICO
A94: PANT-NEG-XL | B94: Pantaloneta XL Negro | C94: 45000 | D94: 90000 | E94: =IF(D94>0,(D94-C94)/D94,0) -> 0.5 | F94: 1 | G94: 1 | H94: BASICO
A95: PANT-BEIG-M | B95: Pantaloneta M Beige | C95: 45000 | D95: 90000 | E95: =IF(D95>0,(D95-C95)/D95,0) -> 0.5 | F95: 1 | G95: 1 | H95: BASICO
A96: PANT-BEIG-L | B96: Pantaloneta L Beige | C96: 45000 | D96: 90000 | E96: =IF(D96>0,(D96-C96)/D96,0) -> 0.5 | F96: 1 | G96: 1 | H96: BASICO
... A102: CAM-REP-1.1 | B102: Camisa Réplica 1.1 | C102: 54000 | D102: 75000 | E102: =IF(D102>0,(D102-C102)/D102,0) -> 0.28 | F102: 22 | G102: 22 | H102: REPLICA

Sheet Caja Diaria
A1: Fecha | B1: Efectivo Inicio | C1: Ventas Efectivo | D1: Ventas Datáfono | E1: Ventas Transf. | F1: Gastos Efectivo | G1: Efectivo Cierre | H1: Diferencia | I1: Notas
A2: 46067 | B2: 0 | C2: 0 | D2: 0 | E2: 120000 | F2: 0 | G2: =B2+C2-F2 -> 0 | H2: =G2-(B2+C2-F2) -> 0 | I2: Claudia Ramírez debe 200.000 de Hoodie Acid Wash M
G3: =B3+C3-F3 -> 0 | H3: =G3-(B3+C3-F3) -> 0
G4: =B4+C4-F4 -> 0 | H4: =G4-(B4+C4-F4) -> 0
G5: =B5+C5-F5 -> 0 | H5: =G5-(B5+C5-F5) -> 0
G6: =B6+C6-F6 -> 0 | H6: =G6-(B6+C6-F6) -> 0
G7: =B7+C7-F7 -> 0 | H7: =G7-(B7+C7-F7) -> 0
G8: =B8+C8-F8 -> 0 | H8: =G8-(B8+C8-F8) -> 0
G9: =B9+C9-F9 -> 0 | H9: =G9-(B9+C9-F9) -> 0
G10: =B10+C10-F10 -> 0 | H10: =G10-(B10+C10-F10) -> 0
G11: =B11+C11-F11 -> 0 | H11: =G11-(B11+C11-F11) -> 0
G12: =B12+C12-F12 -> 0 | H12: =G12-(B12+C12-F12) -> 0
G13: =B13+C13-F13 -> 0 | H13: =G13-(B13+C13-F13) -> 0
G14: =B14+C14-F14 -> 0 | H14: =G14-(B14+C14-F14) -> 0
... G61: =B61+C61-F61 -> 0 | H61: =G61-(B61+C61-F61) -> 0

Sheet Ventas
A1: Fecha | B1: SKU | C1: Producto | D1: Costo | E1: Precio Venta | F1: Método Pago | G1: Cliente | H1: Notas | K1: Efectivo
A2: 46067 | B2: =Inventario!A76 -> CHA-VERNEG-M | C2: =IFERROR(VLOOKUP(B2,Inventario!A:C,2,FALSE()),"") -> Chaqueta Cortavientos M Verde Botella/Negro | D2: =IFERROR(VLOOKUP(B2,Inventario!A:C,3,FALSE()),"") -> 40000 | E2: =IFERROR(VLOOKUP(B2,Inventario!A:D,4,FALSE()),"") -> 120000 | F2: Transferencia | G2: Edison | K2: Transferencia
A3: 46067 | B3: =Inventario!A38 -> HOOD-ACID-L | C3: =IFERROR(VLOOKUP(B3,Inventario!A:C,2,FALSE()),"") -> Hoodie L Acid Wash Gris | D3: =IFERROR(VLOOKUP(B3,Inventario!A:C,3,FALSE()),"") -> 120000 | E3: =IFERROR(VLOOKUP(B3,Inventario!A:D,4,FALSE()),"") -> 200000 | F3: Crédito | G3: Claudia Ramírez | H3: Se debe completo | K3: Datáfono
C4: =IFERROR(VLOOKUP(B4,Inventario!A:C,2,FALSE()),"") | D4: =IFERROR(VLOOKUP(B4,Inventario!A:C,3,FALSE()),"") | E4: =IFERROR(VLOOKUP(B4,Inventario!A:D,4,FALSE()),"") | K4: Crédito
C5: =IFERROR(VLOOKUP(B5,Inventario!A:C,2,FALSE()),"") | D5: =IFERROR(VLOOKUP(B5,Inventario!A:C,3,FALSE()),"") | E5: =IFERROR(VLOOKUP(B5,Inventario!A:D,4,FALSE()),"")
C6: =IFERROR(VLOOKUP(B6,Inventario!A:C,2,FALSE()),"") | D6: =IFERROR(VLOOKUP(B6,Inventario!A:C,3,FALSE()),"") | E6: =IFERROR(VLOOKUP(B6,Inventario!A:D,4,FALSE()),"")
C7: =IFERROR(VLOOKUP(B7,Inventario!A:C,2,FALSE()),"") | D7: =IFERROR(VLOOKUP(B7,Inventario!A:C,3,FALSE()),"") | E7: =IFERROR(VLOOKUP(B7,Inventario!A:D,4,FALSE()),"")
C8: =IFERROR(VLOOKUP(B8,Inventario!A:C,2,FALSE()),"") | D8: =IFERROR(VLOOKUP(B8,Inventario!A:C,3,FALSE()),"") | E8: =IFERROR(VLOOKUP(B8,Inventario!A:D,4,FALSE()),"")
C9: =IFERROR(VLOOKUP(B9,Inventario!A:C,2,FALSE()),"") | D9: =IFERROR(VLOOKUP(B9,Inventario!A:C,3,FALSE()),"") | E9: =IFERROR(VLOOKUP(B9,Inventario!A:D,4,FALSE()),"")
C10: =IFERROR(VLOOKUP(B10,Inventario!A:C,2,FALSE()),"") | D10: =IFERROR(VLOOKUP(B10,Inventario!A:C,3,FALSE()),"") | E10: =IFERROR(VLOOKUP(B10,Inventario!A:D,4,FALSE()),"")
C11: =IFERROR(VLOOKUP(B11,Inventario!A:C,2,FALSE()),"") | D11: =IFERROR(VLOOKUP(B11,Inventario!A:C,3,FALSE()),"") | E11: =IFERROR(VLOOKUP(B11,Inventario!A:D,4,FALSE()),"")
C12: =IFERROR(VLOOKUP(B12,Inventario!A:C,2,FALSE()),"") | D12: =IFERROR(VLOOKUP(B12,Inventario!A:C,3,FALSE()),"") | E12: =IFERROR(VLOOKUP(B12,Inventario!A:D,4,FALSE()),"")
C13: =IFERROR(VLOOKUP(B13,Inventario!A:C,2,FALSE()),"") | D13: =IFERROR(VLOOKUP(B13,Inventario!A:C,3,FALSE()),"") | E13: =IFERROR(VLOOKUP(B13,Inventario!A:D,4,FALSE()),"")
C14: =IFERROR(VLOOKUP(B14,Inventario!A:C,2,FALSE()),"") | D14: =IFERROR(VLOOKUP(B14,Inventario!A:C,3,FALSE()),"") | E14: =IFERROR(VLOOKUP(B14,Inventario!A:D,4,FALSE()),"")
C15: =IFERROR(VLOOKUP(B15,Inventario!A:C,2,FALSE()),"") | D15: =IFERROR(VLOOKUP(B15,Inventario!A:C,3,FALSE()),"") | E15: =IFERROR(VLOOKUP(B15,Inventario!A:D,4,FALSE()),"")
C16: =IFERROR(VLOOKUP(B16,Inventario!A:C,2,FALSE()),"") | D16: =IFERROR(VLOOKUP(B16,Inventario!A:C,3,FALSE()),"") | E16: =IFERROR(VLOOKUP(B16,Inventario!A:D,4,FALSE()),"")
... C51: =IFERROR(VLOOKUP(B51,Inventario!A:C,2,FALSE()),"") | D51: =IFERROR(VLOOKUP(B51,Inventario!A:C,3,FALSE()),"") | E51: =IFERROR(VLOOKUP(B51,Inventario!A:D,4,FALSE()),"")
A55: RESUMEN VENTAS
A56: Total ventas: | B56: =COUNTA(B2:B50) -> 2
A57: Ingresos: | B57: =SUM(E2:E50) -> 320000
A58: Costo mercancía: | B58: =SUM(D2:D50) -> 160000
A59: Margen bruto: | B59: =B57-B58 -> 160000

Sheet Costos Fijos
A1: COSTOS FIJOS MENSUALES
A3: CONCEPTO | B3: MONTO (COP) | C3: NOTAS
A4: Arriendo mensual | B4: 1210000
A5: Servicios públicos | B5: 250000 | C5: Estimado
A6: Internet | B6: 69000 | C6: Primeros dos meses $34.500
A7: Persona punto de venta | C7: Por ahora atienden socios (Una vez haya persona vale 3.000.000 mensual)
A8: Digitales | B8: =100000+53000 -> 153000 | C8: Marketing, IA (Shopify, AI Finder, ManyChat, Google Workspace, Hostinger, Freepik, Mockey) - esas 7 a futuro - Fijos hoy: Shopify, Google Workspace (Dominio)
A9: Seguros | B9: 80000
A10: Imprevistos | B10: =SUM(B4:B6)*0.1 -> 152900 | C10: 10% del total
A12: TOTAL | B12: =SUM(B4:B10) -> 1914900

Sheet Gastos
A1: Fecha | B1: Categoría | C1: Monto | D1: Descripción | E1: Método Pago | F1: Responsable | G1: Notas | I1: CATEGORÍAS DISPONIBLES: | L1: RESPONSABLES | M1: TOTAL | O1: Rubro | P1: Fecha Periódica
A2: 45992 | B2: Arriendo | C2: 404000 | D2: Pago arriendo Diciembre | E2: Transferencia | F2: KATHE | I2: Arriendo | J2: =SUMIF(B:B,I2,C:C) -> 3636000 | L2: ORVANN | M2: =SUMIF($F$2:$F$1006,L2,$C$2:$C$1006) -> 0 | O2: Pago Arriendo | P2: 1 de cada mes
A3: 45992 | B3: Arriendo | C3: 404000 | D3: Pago arriendo Diciembre | E3: Transferencia | F3: MILE | I3: Servicios (Agua, Luz, Gas) | J3: =SUMIF(B:B,I3,C:C) -> 0 | L3: KATHE | M3: =SUMIF($F$2:$F$1006,L3,$C$2:$C$1006) -> 5916090 | N3: =M3-890000 -> 5026090 | O3: Pago Servicios
A4: 45992 | B4: Arriendo | C4: 404000 | D4: Pago arriendo Diciembre | E4: Transferencia | F4: JP | I4: Internet | J4: =SUMIF(B:B,I4,C:C) -> 0 | L4: MILE | M4: =SUMIF($F$2:$F$1006,L4,$C$2:$C$1006) -> 5779090 | N4: =M4-890000 -> 4889090 | O4: Pago Internet
A5: 45998 | B5: Dotación local | C5: 2000000 | D5: Pago arreglo Local | E5: Transferencia | F5: KATHE | I5: Nómina/Vendedor | J5: =SUMIF(B:B,I5,C:C) -> 0 | L5: JP | M5: =SUMIF($F$2:$F$1006,L5,$C$2:$C$1006) -> 5751890 | N5: =M5-890000 -> 4861890 | O5: Pago Shopify
A6: 45998 | B6: Dotación local | C6: 2000000 | D6: Pago arreglo Local | E6: Transferencia | F6: MILE | I6: Contador | J6: =SUMIF(B:B,I6,C:C) -> 0 | O6: Pago Correo Corporativo | P6: 10 de cada mes
A7: 45998 | B7: Dotación local | C7: 2000000 | D7: Pago arreglo Local | E7: Transferencia | F7: JP | I7: Publicidad/Marketing | J7: =SUMIF(B:B,I7,C:C) -> 224746
A8: 46007 | B8: Dotación local | C8: 117000 | D8: Lavamanos | E8: Transferencia | F8: JP | I8: Empaque (Bolsas, Etiquetas) | J8: =SUMIF(B:B,I8,C:C) -> 0 | L8: Arreglo local | M8: 8160000
A9: 46007 | B9: Dotación local | C9: 117000 | D9: Lavamanos | E9: Transferencia | F9: MILE | I9: Aseo/Mantenimiento | J9: =SUMIF(B:B,I9,C:C) -> 157000 | L9: Faltantes | M9: 160000
A10: 46007 | B10: Dotación local | C10: 117000 | D10: Lavamanos | E10: Transferencia | F10: KATHE | I10: Transporte | J10: =SUMIF(B:B,I10,C:C) -> 67100
A11: 46008 | B11: Dotación local | C11: 18000 | D11: Percheros pequeños | E11: Transferencia | F11: JP | I11: Comisiones datáfono | J11: =SUMIF(B:B,I11,C:C) -> 0 | L11: Aporte por socio | M11: 2720000
A12: 46008 | B12: Dotación local | C12: 18000 | D12: Percheros pequeños | E12: Transferencia | F12: MILE | I12: Ilustraciones/Diseño | J12: =SUMIF(B:B,I12,C:C) -> 420000
A13: 46008 | B13: Dotación local | C13: 18000 | D13: Percheros pequeños | E13: Transferencia | F13: KATHE | I13: Dotación local | J13: =SUMIF(B:B,I13,C:C) -> 9376100
A14: 46018 | B14: Dotación local | C14: 500000 | D14: Pago arreglo Local | E14: Transferencia | F14: MILE | I14: Imprevistos | J14: =SUMIF(B:B,I14,C:C) -> 0
A15: 46018 | B15: Dotación local | C15: 100000 | D15: Pago arreglo Local | E15: Transferencia | F15: JP | I15: Mercancía | J15: =SUMIF(B:B,I15,C:C) -> 3566124
A16: 46023 | B16: Arriendo | C16: 404000 | D16: Pago arriendo Enero | E16: Transferencia | F16: KATHE | I16: Otro | J16: =SUMIF(B:B,I16,C:C) -> 0
A17: 46023 | B17: Arriendo | C17: 404000 | D17: Pago arriendo Enero | E17: Transferencia | F17: JP
A18: 46023 | B18: Arriendo | C18: 404000 | D18: Pago arriendo Enero | E18: Transferencia | F18: MILE
A19: 46024 | B19: Publicidad/Marketing | C19: 59682 | D19: Pago mensualidad Freepick y Mockey | E19: Transferencia | F19: JP
A20: 46024 | B20: Publicidad/Marketing | C20: 59682 | D20: Pago mensualidad Freepick y Mockey | E20: Transferencia | F20: KATHE
A21: 46024 | B21: Publicidad/Marketing | C21: 59682 | D21: Pago mensualidad Freepick y Mockey | E21: Transferencia | F21: MILE
A22: 46032 | B22: Dotación local | C22: 287000 | D22: Espejo, Toldo y Cámaras | E22: Transferencia | F22: JP
A23: 46032 | B23: Dotación local | C23: 287000 | D23: Espejo, Toldo y Cámaras | E23: Transferencia | F23: KATHE
A24: 46032 | B24: Dotación local | C24: 287000 | D24: Espejo, Toldo y Cámaras | E24: Transferencia | F24: MILE
A25: 46037 | B25: Dotación local | C25: 30000 | D25: Adicional espejo | E25: Transferencia | F25: MILE
A26: 46037 | B26: Dotación local | C26: 30000 | D26: Adicional espejo | E26: Transferencia | F26: JP
A27: 46037 | B27: Dotación local | C27: 30000 | D27: Adicional espejo | E27: Transferencia | F27: KATHE
A28: 45674 | B28: Dotación local | C28: 220000 | D28: Pago arreglo Local | E28: Transferencia | F28: MILE
... A40: 46059 | B40: Dotación local | C40: 400000 | D40: Pago arreglo Local | E40: Transferencia | F40: JP
A41: 46062 | B41: Mercancía | C41: =2670000/3 -> 890000 | D41: Mercancía Your Brand | E41: Datáfono | F41: MILE | G41: Pago con TC de JP (Pendiente pago)
A42: 46062 | B42: Mercancía | C42: =C41 -> 890000 | D42: Mercancía Your Brand | E42: Datáfono | F42: KATHE | G42: Pago con TC de JP (Pendiente pago)
A43: 46062 | B43: Mercancía | C43: =C42 -> 890000 | D43: Mercancía Your Brand | E43: Datáfono | F43: JP
A44: 46057 | B44: Mercancía | C44: 80000 | D44: Mercancía Your Brand | E44: Transferencia | F44: KATHE
A45: 46057 | B45: Mercancía | C45: 80000 | D45: Mercancía Your Brand | E45: Transferencia | F45: MILE
A46: 46057 | B46: Mercancía | C46: 80000 | D46: Mercancía Your Brand | E46: Transferencia | F46: JP
A47: 46062 | B47: Transporte | C47: 20000 | D47: Domicilio Mercancía Your Brand | E47: Transferencia | F47: KATHE
A48: 46063 | B48: Publicidad/Marketing | C48: 36700 | D48: Compra Dominio orvann.co | E48: Transferencia | F48: JP
A49: 46064 | B49: Publicidad/Marketing | C49: 9000 | D49: Compra Dominio orvann.co | E49: Transferencia | F49: KATHE
A50: 46067 | B50: Transporte | C50: 19100 | D50: Transporte mercancía Auren | E50: Transferencia | F50: JP
A51: 45693 | B51: Mercancía | C51: 218708 | D51: Marquillas y Etiquetas | E51: Transferencia | F51: KATHE
A52: 45693 | B52: Mercancía | C52: 218708 | D52: Marquillas y Etiquetas | E52: Transferencia | F52: JP
A53: 45693 | B53: Mercancía | C53: 218708 | D53: Marquillas y Etiquetas | E53: Transferencia | F53: MILE
A54: 46067 | B54: Aseo/Mantenimiento | C54: 77000 | D54: Implementos de aseo | E54: Transferencia | F54: JP
A55: 46067 | B55: Transporte | C55: 28000 | D55: Transporte mercancía a tienda | E55: Transferencia | F55: KATHE
A56: 46067 | B56: Aseo/Mantenimiento | C56: 80000 | D56: Aseo tienda para apertura | E56: Transferencia | F56: KATHE
A111: RESUMEN GASTOS
A112: Total gastos: | B112: =SUM(C2:C106) -> 17447070

Sheet Pedidos Proveedores
A1: Fecha Pedido | B1: Proveedor | C1: Descripción | D1: Unidades | E1: Costo Unit. | F1: Total | G1: Estado Pago | H1: Fecha Pago | I1: Notas | L1: Pendiente | M1: =SUMIF($G$2:$G$15,L1,$F$2:$F$15) -> 9618000 | Q1: Precios Proveedores
A2: 45692 | B2: YOUR BRAND | C2: Hoodie L | D2: 2 | E2: 120000 | F2: =D2*E2 -> 240000 | G2: Pagado | H2: 46057 | I2: 2 Acid Wash gris | L2: Pagado | M2: =SUMIF($G$2:$G$15,L2,$F$2:$F$15) -> 240000 | Q2: AUREN | R2: Precio
A3: 45692 | B3: YOUR BRAND | C3: Chompa 320gr Talla L | D3: 4 | E3: 90000 | F3: =D3*E3 -> 360000 | G3: Pendiente | I3: Crédito JP - 4 Perla | L3: Crédito | M3: =SUMIF($G$2:$G$15,L3,$F$2:$F$15) -> 0 | Q3: Regular | R3: 32000
A4: 46062 | B4: YOUR BRAND | C4: Hoodie L | D4: 10 | E4: 120000 | F4: =D4*E4 -> 1200000 | G4: Pendiente | I4: Crédito JP - 10 Acid Wash gris | Q4: Oversize | R4: 35000
A5: 46062 | B5: YOUR BRAND | C5: Camiseta Boxy Fit 320gr | D5: 30 | E5: 37000 | F5: =D5*E5 -> 1110000 | G5: Pendiente | I5: Crédito JP - 10 negras, 10 blancas, 10 plomo plata | Q5: Buso regular | R5: 50000
A6: 46056 | B6: BRACOR | C6: Camiseta Réplica Y/Out 1.1 | D6: 8 | E6: 60000 | F6: =D6*E6 -> 480000 | G6: Pendiente | Q6: Buso oversize | R6: 55000
A7: 46056 | B7: BRACOR | C7: Camiseta Réplica 1.1 | D7: 22 | E7: 54000 | F7: =D7*E7 -> 1188000 | G7: Pendiente | Q7: Pantaloneta | R7: 45000
A8: 46067 | B8: AUREN | C8: Chaqueta Cortavientos | D8: 36 | E8: 40000 | F8: =D8*E8 -> 1440000 | G8: Pendiente | I8: 24 Chaquetas 1 Color y 12 Chaquetas Bicolor | Q8: Jogger | R8: 55000
A9: 46067 | B9: AUREN | C9: Pantalonetas | D9: 12 | E9: 45000 | F9: =D9*E9 -> 540000 | G9: Pendiente | I9: 12 Pantalonetas (Negras, Beige y Café) | Q9: Sudadera bota recta | R9: 55000
A10: 46067 | B10: AUREN | C10: Sudadera Bota Recta | D10: 12 | E10: 55000 | F10: =D10*E10 -> 660000 | G10: Pendiente | I10: 12 Sudaderas (Negras, Beige y Café) | Q10: Chompa | R10: 75000
A11: 46067 | B11: AUREN | C11: Jogger | D11: 24 | E11: 55000 | F11: =D11*E11 -> 1320000 | G11: Pendiente | I11: 12 Jogger (Negras, Beige y Café) | Q11: Chaquetas cortavientos | R11: 40000
A12: 46067 | B12: AUREN | C12: Buso Oversized | D12: 24 | E12: 55000 | F12: =D12*E12 -> 1320000 | G12: Pendiente | I12: 24 Busos Oversized (Negro, Beige y Café) | Q12: Sudadera cortavientos | R12: 32000
F13: =D13*E13 -> 0 | Q13: Chaqueta reflectiva | R13: 50000
F14: =D14*E14 -> 0
Q15: ETIQUETAS / MARQUILLAS / EMPAQUES
A16: TOTAL PEDIDOS | D16: =SUM(D2:D14) -> 184 | F16: =SUM(F2:F14) -> 9858000 | Q16: Bolsas buenas | R16: 600
Q17: bolsa sencilla | R17: 150

Sheet Análisis Precios
A1: ANÁLISIS DE COSTO REAL POR TIPO DE PRENDA
A2: Incluye: Prenda + Estampado + Etiquetas + Empaque
A4: COSTOS ADICIONALES (EDITAR EN AZUL) | F4: Siempre precio llevando los diseños listos
A5: Concepto | B5: 1-10 uds | C5: 11-50 uds | D5: 51-100 uds | E5: Más de 100 | F5: Notas
A6: Estampado DTF pequeño (pecho) | B6: =25000/8 -> 3125 | C6: =25000/10 -> 2500 | D6: =25000/10 -> 2500 | E6: =25000/12 -> 2083.3333 | F6: Se vende por metro. El metro vale aproximadamente 25.000. Salen tamaño (Aprox 57 cm de ancho): punto corazon (Logo pequeño), media carta (Logo estandar tipo clemont), carta (Figura tamaño carta), oficio y tabloide (Casi estampado completo). Salen unos 100 punto corazón, unas 15 media carta, unas 8 carta, unas 6 oficio y 2 tabloides.
A7: Estampado DTF grande (espalda) | B7: =25000/2 -> 12500 | C7: =25000/3 -> 8333.3333 | D7: =25000/3 -> 8333.3333 | E7: =25000/4 -> 6250 | F7: Llenar después de cotizar
A8: Estampado Serigrafía (1 color) | B8: $8,000 | C8: $5,000 | D8: $3,500 | E8: $2,500 | F8: El metro de vinilo de alta densidad vale aprox 105.000 (sumando el estampado (72.000) plotteado y descolillado (33.000), si se averigua seguro es más barato) - Solo negro, blanco y rojo normalmente / El metro de vinilo vale aprox 80.000 (sumando el estampado (45.000) plotteado y descolillado (35.000), si se averigua seguro es más barato) - Solo negro, blanco y rojo normalmente. Vinilo sale en un solo color, DTF varios. Vinilo queda con un poco de relieve. DTG no se encontró (Proveedor Santiago)
A9: Etiqueta cuello tejida | B9: 1500 | C9: 1000 | D9: 800 | E9: 600 | F9: Mínimo típico: 100 uds
A10: Hang tag (etiqueta colgante) | B10: 1200 | C10: $800 | D10: $600 | E10: $400 | F10: Con diseño e hilo
A11: Bolsa papel con logo | B11: 1500 | C11: 1000 | D11: 800 | E11: 800
A12: Bolsa premium | B12: 3000 | C12: 3000 | D12: 2500 | E12: 2000 | F12: Bolsa Premium
A13: Sticker logo | B13: 500 | C13: 300 | D13: 200 | E13: 150 | F13: Para sellar bolsa y dejar adentro
A16: COSTO REAL POR TIPO DE PRODUCTO
A17: Tipo Prenda | B17: Costo Base AUREN | C17: Estampado | D17: Etiquetas | E17: Empaque | F17: COSTO TOTAL | G17: Precio Venta Sugerido | H17: Margen %
A18: Camisa Básica (sin estampar) | B18: 37000 | C18: 0 | D18: =$B$9+$B$10 -> 2700 | E18: =$B$11+$B$12+$B$13 -> 5000 | F18: =SUM(B18:E18) -> 44700 | G18: 80000 | H18: =IF(G18>0,(G18-F18)/G18,0) -> 0.44125
A19: Camisa Estampada Pecho | B19: 37000 | C19: =B6 -> 3125 | D19: =$B$9+$B$10 -> 2700 | E19: =$B$11+$B$12+$B$13 -> 5000 | F19: =SUM(B19:E19) -> 47825 | G19: 80000 | H19: =IF(G19>0,(G19-F19)/G19,0) -> 0.4021875
A20: Camisa Estampada Espalda | B20: 37000 | C20: =B7 -> 12500 | D20: =$B$9+$B$10 -> 2700 | E20: =$B$11+$B$12+$B$13 -> 5000 | F20: =SUM(B20:E20) -> 57200 | G20: 80000 | H20: =IF(G20>0,(G20-F20)/G20,0) -> 0.285
A21: Camisa Estampada Full (pecho+espalda) | B21: 37000 | C21: =C19+C20 -> 15625 | D21: =$B$9+$B$10 -> 2700 | E21: =$B$11+$B$12+$B$13 -> 5000 | F21: =SUM(B21:E21) -> 60325 | G21: 80000 | H21: =IF(G21>0,(G21-F21)/G21,0) -> 0.2459375
A22: Chompa Capucha Básica | B22: 76000 | C22: $0 | D22: =$B$9+$B$10 -> 2700 | E22: =$B$11+$B$12+$B$13 -> 5000 | F22: =SUM(B22:E22) -> 83700 | G22: 120000 | H22: =IF(G22>0,(G22-F22)/G22,0) -> 0.3025
A23: Chompa Capucha Estampada | B23: 76000 | C23: =C21 -> 15625 | D23: =$B$9+$B$10 -> 2700 | E23: =$B$11+$B$12+$B$13 -> 5000 | F23: =SUM(B23:E23) -> 99325 | G23: 130000 | H23: =IF(G23>0,(G23-F23)/G23,0) -> 0.23596154
A24: Buzo Cuello Redondo Básico | B24: 56000 | C24: $0 | D24: =$B$9+$B$10 -> 2700 | E24: =$B$11+$B$12+$B$13 -> 5000 | F24: =SUM(B24:E24) -> 63700 | G24: 100000 | H24: =IF(G24>0,(G24-F24)/G24,0) -> 0.363
A25: Buzo Estampado | B25: 56000 | C25: =C23 -> 15625 | D25: =$B$9+$B$10 -> 2700 | E25: =$B$11+$B$12+$B$13 -> 5000 | F25: =SUM(B25:E25) -> 79325 | G25: 120000 | H25: =IF(G25>0,(G25-F25)/G25,0) -> 0.33895833
A26: Jogger Básico | B26: 62000 | C26: $0 | D26: =$B$9+$B$10 -> 2700 | E26: =$B$11+$B$12+$B$13 -> 5000 | F26: =SUM(B26:E26) -> 69700 | G26: 100000 | H26: =IF(G26>0,(G26-F26)/G26,0) -> 0.303
A27: Sudadera Bota Recta Básica | B27: 62000 | C27: $0 | D27: =$B$9+$B$10 -> 2700 | E27: =$B$11+$B$12+$B$13 -> 5000 | F27: =SUM(B27:E27) -> 69700 | G27: 100000 | H27: =IF(G27>0,(G27-F27)/G27,0) -> 0.303
A28: Pantaloneta Básica | B28: 49000 | C28: $0 | D28: =$B$9+$B$10 -> 2700 | E28: =$B$11+$B$12+$B$13 -> 5000 | F28: =SUM(B28:E28) -> 56700 | G28: 80000 | H28: =IF(G28>0,(G28-F28)/G28,0) -> 0.29125
A29: Chaqueta Cortavientos Básica | B29: 45000 | C29: $0 | D29: =$B$9+$B$10 -> 2700 | E29: =$B$11+$B$12+$B$13 -> 5000 | F29: =SUM(B29:E29) -> 52700 | G29: 80000 | H29: =IF(G29>0,(G29-F29)/G29,0) -> 0.34125
A30: Chaqueta Cortavientos Estampada | B30: 45000 | C30: =C25 -> 15625 | D30: =$B$9+$B$10 -> 2700 | E30: =$B$11+$B$12+$B$13 -> 5000 | F30: =SUM(B30:E30) -> 68325 | G30: 100000 | H30: =IF(G30>0,(G30-F30)/G30,0) -> 0.31675
A34: ESCENARIOS DE PRECIO DE VENTA - CAMISA ESTAMPADA
A35: Escenario | B35: Costo Total | C35: Precio Venta | D35: Margen $ | E35: Margen % | F35: Comentario
A36: Económico (réplica) | B36: =F21 -> 60325 | C36: 80000 | D36: =C36-B36 -> 19675 | E36: =IF(C36>0,(C36-B36)/C36,0) -> 0.2459375 | F36: Competir con réplicas baratas
A37: Estándar | B37: =F21 -> 60325 | C37: 90000 | D37: =C37-B37 -> 29675 | E37: =IF(C37>0,(C37-B37)/C37,0) -> 0.32972222 | F37: Precio medio del mercado
A38: Premium ORVANN | B38: =F21 -> 60325 | C38: 110000 | D38: =C38-B38 -> 49675 | E38: =IF(C38>0,(C38-B38)/C38,0) -> 0.45159091 | F38: Marca propia, diseño exclusivo
A39: Ultra Premium (edición limitada) | B39: =F21*1.1 -> 66357.5 | C39: 140000 | D39: =C39-B39 -> 73642.5 | E39: =IF(C39>0,(C39-B39)/C39,0) -> 0.52601786 | F39: Colección especial, empaque VHS/Vinilo
A42: NOTAS IMPORTANTES:
A43: Los precios en AZUL son inputs
A44: Para réplicas (Clemont, etc): menor margen pero mayor volumen
A45: Para colecciones ORVANN: mayor margen, menor volumen, más exclusividad

Sheet Cotizador Compras
A1: COTIZADOR DE COMPRAS - ORVANN
A3: CATÁLOGO DE PRODUCTOS (Referencia de Costos) | O3: LISTAS DE OPCIONES (Ocultar esta columna)
A4: Tipo Producto | B4: Proveedor | C4: Costo Base | D4: Estampado Pecho | E4: Estampado Espalda | F4: Etiquetas | G4: Empaque | H4: Precio Venta Basica | I4: Precio Venta Estampado Full | J4: Precio Venta Estampado Pecho | O4: Productos | P4: Tallas | Q4: Colores | R4: Estampado
A5: Camisa Oversize | B5: AUREN | C5: 35000 | D5: 3500 | E5: 11000 | F5: 1700 | G5: 1000 | H5: 75000 | I5: 130000 | J5: 100000 | O5: Camisa Oversize | P5: S | Q5: Negro | R5: Sin estampar
A6: Camisa Oversize Peruana | B6: YOUR BRAND | C6: 37000 | D6: 3500 | E6: 11000 | F6: 1700 | G6: 1000 | H6: 75000 | I6: 130000 | J6: 100000 | O6: Camisa Oversize Peruana | P6: M | Q6: Blanco | R6: Pecho
A7: Camisa Regular | B7: YOUR BRAND | C7: 37000 | D7: 3500 | E7: 11000 | F7: 1700 | G7: 1000 | H7: 75000 | I7: 130000 | J7: 100000 | O7: Camisa Regular | P7: L | Q7: Plomo Plata | R7: Espalda
A8: Camisa Boxy fit | B8: YOUR BRAND | C8: 37000 | D8: 3500 | E8: 11000 | F8: 1700 | G8: 1000 | H8: 75000 | I8: 130000 | J8: 100000 | O8: Camisa Boxy fit | P8: XL | Q8: Beige | R8: Full (Pecho+Espalda)
A9: Chompa Capucha | B9: YOUR BRAND | C9: 90000 | D9: 3500 | E9: 11000 | F9: 1700 | G9: 1000 | H9: 200000 | I9: 260000 | J9: 230000 | O9: Chompa Capucha | P9: 2XL | Q9: Perla | R9: Especial
A10: Hoodie | B10: YOUR BRAND | C10: 120000 | D10: 3500 | E10: 11000 | F10: 1700 | G10: 1000 | H10: 200000 | I10: 260000 | J10: 230000 | O10: Hoodie | P10: Unica | Q10: Acid Wash Gris
A11: Buzo Cuello Redondo Regular | B11: AUREN | C11: 50000 | D11: 3500 | E11: 11000 | F11: 1700 | G11: 1000 | H11: 120000 | I11: 140000 | J11: 140000 | O11: Buzo Cuello Redondo Regular | Q11: Verde Botella
A12: Buzo Cuello Redondo Oversized | B12: AUREN | C12: 55000 | D12: 3500 | E12: 11000 | F12: 1700 | G12: 1000 | H12: 120000 | I12: 140000 | J12: 140000 | O12: Buzo Cuello Redondo Oversized | Q12: Café
A13: Jogger Largo | B13: AUREN | C13: 55000 | D13: 3500 | E13: 11000 | F13: 1700 | G13: 1000 | H13: 100000 | I13: 100000 | J13: 100000 | O13: Jogger Largo
A14: Sudadera Bota Recta | B14: AUREN | C14: 55000 | D14: 3500 | E14: 11000 | F14: 1700 | G14: 1000 | H14: 90000 | I14: 100000 | J14: 100000 | O14: Sudadera Bota Recta
A15: Pantaloneta | B15: AUREN | C15: 45000 | D15: 3500 | E15: 11000 | F15: 1700 | G15: 1000 | H15: 90000 | I15: 90000 | J15: 90000 | O15: Pantaloneta
A16: Chaqueta Cortavientos | B16: AUREN | C16: 40000 | D16: 3500 | E16: 11000 | F16: 1700 | G16: 1000 | H16: 120000 | I16: 120000 | J16: 120000 | O16: Chaqueta Cortavientos
A17: Sudadera Cortavientos | B17: AUREN | C17: 32000 | D17: 3500 | E17: 11000 | F17: 1700 | G17: 1000 | H17: 65000 | I17: 65000 | J17: 65000 | O17: Sudadera Cortavientos
A18: Gorra | C18: 25000 | D18: 5000 | F18: 1700 | G18: 1000 | H18: 50000 | I18: 65000 | J18: 65000 | O18: Gorra
A19: Camisa Réplica Y/Out | B19: BRACOR | C19: 60000 | G19: 1000 | H19: 75000 | I19: =+'Cotizador Compras'!$H19 -> 75000 | J19: =+'Cotizador Compras'!$H19 -> 75000 | O19: Camisa Réplica White Out
A20: Camisa Réplica 1.1 | B20: BRACOR | C20: 54000 | G20: 1000 | H20: 75000 | I20: =+'Cotizador Compras'!$H20 -> 75000 | J20: =+'Cotizador Compras'!$H20 -> 75000 | O20: Camisa Réplica 1.1
A22: PLANIFICADOR DE COMPRA
A25: Tipo Producto | B25: Talla | C25: Color | D25: Estampado | E25: Cantidad | F25: Provedor | G25: Costo Prenda | H25: Costo Estampado | I25: Costo Etiquetas | J25: Costo Empaque | K25: COSTO TOTAL | L25: Precio Venta Unit. | M25: VENTA TOTAL | N25: Costo Unitario | O25: Margen | P25: Nombre | Q25: Productos | R25: Cantidad | T25: Costo Prendas | W25: Precio unitario x3 | X25: Precio x3 | Y25: Margen x3 | Z25: Precio unitario x6 | AA25: Precio x6 | AB25: Margen x6 | AC25: Precio Unit x12 | AD25: Precio x12 + | AE25: Margen x12
A26: Camisa Oversize Peruana | B26: S | C26: Negro | D26: Sin estampar | E26: 1 | F26: =IF(A26="","",VLOOKUP(A26,'Cotizador Compras'!$A$5:$J$21,2,FALSE)) -> YOUR BRAND | G26: =IF(A26="","",VLOOKUP(A26,'Cotizador Compras'!$A$5:$J$21,3,FALSE)) -> 37000 | H26: =IF(OR(A26="",D26=""),"",IF(D26="Sin estampar",0,IF(D26="Pecho",VLOOKUP(A26,'Cotizador Compras'!$A$5:$J$21,4,FALSE),IF(D26="Espalda",VLOOKUP(A26,'Cotizador Compras'!$A$5:$J$21,5,FALSE),VLOOKUP(A26,'Cotizador Compras'!$A$5:$J$21,4,FALSE)+VLOOKUP(A26,'Cotizador Compras'!$A$5:$J$21,5,FALSE))))) -> 0 | I26: =IF(A26="","",VLOOKUP(A26,'Cotizador Compras'!$A$5:$J$21,6,FALSE)) -> 1700 | J26: =IF(A26="","",VLOOKUP(A26,'Cotizador Compras'!$A$5:$J$21,7,FALSE)) -> 1000 | K26: =IF(OR(A26="",E26=""),"",(G26+H26+I26+J26)*E26) -> 39700 | L26: =IF(A26="","",IF(D26="Sin estampar",VLOOKUP(A26,'Cotizador Compras'!$A$5:$J$21,8,FALSE),IF(D26="Pecho",VLOOKUP(A26,'Cotizador Compras'!$A$5:$J$21,10,FALSE),VLOOKUP(A26,'Cotizador Compras'!$A$5:$J$21,9,FALSE)))) -> 75000 | M26: =IF(OR(A26="",E26=""),"",L26*E26) -> 75000 | N26: =+G26+H26+I26+J26 -> 39700 | O26: =IF(L26>0,(L26-N26)/L26,0) -> 0.47066667 | P26: =CONCATENATE(A26," ",B26," ",C26) -> Camisa Oversize Peruana S Negro | Q26: {=+UNIQUE(P26:P163)} -> Camisa Oversize Peruana S Negro | R26: =SUMIF($P$26:$P$159,Q26,$E$26:$E$159) -> 2 | T26: =E26*G26 -> 37000 | X26: =ROUNDUP(L26*0.95,-3)*3 -> 216000 | Y26: =IF(X26>0,(X26-N26*3)/X26,0) -> 0.44861111 | AA26: =+ROUNDUP(L26*0.925,-3)*6 -> 420000 | AB26: =IF(AA26>0,(AA26-N26*6)/AA26,0) -> 0.43285714 | AC26: =+E26*AD26/12 -> 68000 | AD26: =+ROUNDUP(L26*0.9,-3)*12 -> 816000 | AE26: =IF(AD26>0,(AD26-N26*12)/AD26,0) -> 0.41617647
A27: Camisa Oversize Peruana | B27: M | C27: Negro | D27: Sin estampar | E27: 4 | F27: =IF(A27="","",VLOOKUP(A27,'Cotizador Compras'!$A$5:$J$21,2,FALSE)) -> YOUR BRAND | G27: =IF(A27="","",VLOOKUP(A27,'Cotizador Compras'!$A$5:$J$21,3,FALSE)) -> 37000 | H27: =IF(OR(A27="",D27=""),"",IF(D27="Sin estampar",0,IF(D27="Pecho",VLOOKUP(A27,'Cotizador Compras'!$A$5:$J$21,4,FALSE),IF(D27="Espalda",VLOOKUP(A27,'Cotizador Compras'!$A$5:$J$21,5,FALSE),VLOOKUP(A27,'Cotizador Compras'!$A$5:$J$21,4,FALSE)+VLOOKUP(A27,'Cotizador Compras'!$A$5:$J$21,5,FALSE))))) -> 0 | I27: =IF(A27="","",VLOOKUP(A27,'Cotizador Compras'!$A$5:$J$21,6,FALSE)) -> 1700 | J27: =IF(A27="","",VLOOKUP(A27,'Cotizador Compras'!$A$5:$J$21,7,FALSE)) -> 1000 | K27: =IF(OR(A27="",E27=""),"",(G27+H27+I27+J27)*E27) -> 158800 | L27: =IF(A27="","",IF(D27="Sin estampar",VLOOKUP(A27,'Cotizador Compras'!$A$5:$J$21,8,FALSE),IF(D27="Pecho",VLOOKUP(A27,'Cotizador Compras'!$A$5:$J$21,10,FALSE),VLOOKUP(A27,'Cotizador Compras'!$A$5:$J$21,9,FALSE)))) -> 75000 | M27: =IF(OR(A27="",E27=""),"",L27*E27) -> 300000 | N27: =+G27+H27+I27+J27 -> 39700 | O27: =IF(L27>0,(L27-N27)/L27,0) -> 0.47066667 | P27: =CONCATENATE(A27," ",B27," ",C27) -> Camisa Oversize Peruana M Negro | Q27: Camisa Oversize Peruana M Negro | R27: =SUMIF($P$26:$P$159,Q27,$E$26:$E$159) -> 6 | T27: =E27*G27 -> 148000 | X27: =ROUNDUP(L27*0.95,-3)*3 -> 216000 | Y27: =IF(X27>0,(X27-N27*3)/X27,0) -> 0.44861111 | AA27: =+ROUNDUP(L27*0.925,-3)*6 -> 420000 | AB27: =IF(AA27>0,(AA27-N27*6)/AA27,0) -> 0.43285714 | AC27: =+E27*AD27/12 -> 272000 | AD27: =+ROUNDUP(L27*0.9,-3)*12 -> 816000 | AE27: =IF(AD27>0,(AD27-N27*12)/AD27,0) -> 0.41617647
A28: Camisa Oversize Peruana | B28: L | C28: Negro | D28: Sin estampar | E28: 4 | F28: =IF(A28="","",VLOOKUP(A28,'Cotizador Compras'!$A$5:$J$21,2,FALSE)) -> YOUR BRAND | G28: =IF(A28="","",VLOOKUP(A28,'Cotizador Compras'!$A$5:$J$21,3,FALSE)) -> 37000 | H28: =IF(OR(A28="",D28=""),"",IF(D28="Sin estampar",0,IF(D28="Pecho",VLOOKUP(A28,'Cotizador Compras'!$A$5:$J$21,4,FALSE),IF(D28="Espalda",VLOOKUP(A28,'Cotizador Compras'!$A$5:$J$21,5,FALSE),VLOOKUP(A28,'Cotizador Compras'!$A$5:$J$21,4,FALSE)+VLOOKUP(A28,'Cotizador Compras'!$A$5:$J$21,5,FALSE))))) -> 0 | I28: =IF(A28="","",VLOOKUP(A28,'Cotizador Compras'!$A$5:$J$21,6,FALSE)) -> 1700 | J28: =IF(A28="","",VLOOKUP(A28,'Cotizador Compras'!$A$5:$J$21,7,FALSE)) -> 1000 | K28: =IF(OR(A28="",E28=""),"",(G28+H28+I28+J28)*E28) -> 158800 | L28: =IF(A28="","",IF(D28="Sin estampar",VLOOKUP(A28,'Cotizador Compras'!$A$5:$J$21,8,FALSE),IF(D28="Pecho",VLOOKUP(A28,'Cotizador Compras'!$A$5:$J$21,10,FALSE),VLOOKUP(A28,'Cotizador Compras'!$A$5:$J$21,9,FALSE)))) -> 75000 | M28: =IF(OR(A28="",E28=""),"",L28*E28) -> 300000 | N28: =+G28+H28+I28+J28 -> 39700 | O28: =IF(L28>0,(L28-N28)/L28,0) -> 0.47066667 | P28: =CONCATENATE(A28," ",B28," ",C28) -> Camisa Oversize Peruana L Negro | Q28: Camisa Oversize Peruana L Negro | R28: =SUMIF($P$26:$P$159,Q28,$E$26:$E$159) -> 6 | T28: =E28*G28 -> 148000 | X28: =ROUNDUP(L28*0.95,-3)*3 -> 216000 | Y28: =IF(X28>0,(X28-N28*3)/X28,0) -> 0.44861111 | AA28: =+ROUNDUP(L28*0.925,-3)*6 -> 420000 | AB28: =IF(AA28>0,(AA28-N28*6)/AA28,0) -> 0.43285714 | AC28: =+E28*AD28/12 -> 272000 | AD28: =+ROUNDUP(L28*0.9,-3)*12 -> 816000 | AE28: =IF(AD28>0,(AD28-N28*12)/AD28,0) -> 0.41617647
A29: Camisa Oversize Peruana | B29: XL | C29: Negro | D29: Sin estampar | E29: 4 | F29: =IF(A29="","",VLOOKUP(A29,'Cotizador Compras'!$A$5:$J$21,2,FALSE)) -> YOUR BRAND | G29: =IF(A29="","",VLOOKUP(A29,'Cotizador Compras'!$A$5:$J$21,3,FALSE)) -> 37000 | H29: =IF(OR(A29="",D29=""),"",IF(D29="Sin estampar",0,IF(D29="Pecho",VLOOKUP(A29,'Cotizador Compras'!$A$5:$J$21,4,FALSE),IF(D29="Espalda",VLOOKUP(A29,'Cotizador Compras'!$A$5:$J$21,5,FALSE),VLOOKUP(A29,'Cotizador Compras'!$A$5:$J$21,4,FALSE)+VLOOKUP(A29,'Cotizador Compras'!$A$5:$J$21,5,FALSE))))) -> 0 | I29: =IF(A29="","",VLOOKUP(A29,'Cotizador Compras'!$A$5:$J$21,6,FALSE)) -> 1700 | J29: =IF(A29="","",VLOOKUP(A29,'Cotizador Compras'!$A$5:$J$21,7,FALSE)) -> 1000 | K29: =IF(OR(A29="",E29=""),"",(G29+H29+I29+J29)*E29) -> 158800 | L29: =IF(A29="","",IF(D29="Sin estampar",VLOOKUP(A29,'Cotizador Compras'!$A$5:$J$21,8,FALSE),IF(D29="Pecho",VLOOKUP(A29,'Cotizador Compras'!$A$5:$J$21,10,FALSE),VLOOKUP(A29,'Cotizador Compras'!$A$5:$J$21,9,FALSE)))) -> 75000 | M29: =IF(OR(A29="",E29=""),"",L29*E29) -> 300000 | N29: =+G29+H29+I29+J29 -> 39700 | O29: =IF(L29>0,(L29-N29)/L29,0) -> 0.47066667 | P29: =CONCATENATE(A29," ",B29," ",C29) -> Camisa Oversize Peruana XL Negro | Q29: Camisa Oversize Peruana XL Negro | R29: =SUMIF($P$26:$P$159,Q29,$E$26:$E$159) -> 6 | T29: =E29*G29 -> 148000 | X29: =ROUNDUP(L29*0.95,-3)*3 -> 216000 | Y29: =IF(X29>0,(X29-N29*3)/X29,0) -> 0.44861111 | AA29: =+ROUNDUP(L29*0.925,-3)*6 -> 420000 | AB29: =IF(AA29>0,(AA29-N29*6)/AA29,0) -> 0.43285714 | AC29: =+E29*AD29/12 -> 272000 | AD29: =+ROUNDUP(L29*0.9,-3)*12 -> 816000 | AE29: =IF(AD29>0,(AD29-N29*12)/AD29,0) -> 0.41617647
A30: Camisa Oversize Peruana | B30: S | C30: Blanco | D30: Sin estampar | E30: 1 | F30: =IF(A30="","",VLOOKUP(A30,'Cotizador Compras'!$A$5:$J$21,2,FALSE)) -> YOUR BRAND | G30: =IF(A30="","",VLOOKUP(A30,'Cotizador Compras'!$A$5:$J$21,3,FALSE)) -> 37000 | H30: =IF(OR(A30="",D30=""),"",IF(D30="Sin estampar",0,IF(D30="Pecho",VLOOKUP(A30,'Cotizador Compras'!$A$5:$J$21,4,FALSE),IF(D30="Espalda",VLOOKUP(A30,'Cotizador Compras'!$A$5:$J$21,5,FALSE),VLOOKUP(A30,'Cotizador Compras'!$A$5:$J$21,4,FALSE)+VLOOKUP(A30,'Cotizador Compras'!$A$5:$J$21,5,FALSE))))) -> 0 | I30: =IF(A30="","",VLOOKUP(A30,'Cotizador Compras'!$A$5:$J$21,6,FALSE)) -> 1700 | J30: =IF(A30="","",VLOOKUP(A30,'Cotizador Compras'!$A$5:$J$21,7,FALSE)) -> 1000 | K30: =IF(OR(A30="",E30=""),"",(G30+H30+I30+J30)*E30) -> 39700 | L30: =IF(A30="","",IF(D30="Sin estampar",VLOOKUP(A30,'Cotizador Compras'!$A$5:$J$21,8,FALSE),IF(D30="Pecho",VLOOKUP(A30,'Cotizador Compras'!$A$5:$J$21,10,FALSE),VLOOKUP(A30,'Cotizador Compras'!$A$5:$J$21,9,FALSE)))) -> 75000 | M30: =IF(OR(A30="",E30=""),"",L30*E30) -> 75000 | N30: =+G30+H30+I30+J30 -> 39700 | O30: =IF(L30>0,(L30-N30)/L30,0) -> 0.47066667 | P30: =CONCATENATE(A30," ",B30," ",C30) -> Camisa Oversize Peruana S Blanco | Q30: Camisa Oversize Peruana S Blanco | R30: =SUMIF($P$26:$P$159,Q30,$E$26:$E$159) -> 2 | T30: =E30*G30 -> 37000 | X30: =ROUNDUP(L30*0.95,-3)*3 -> 216000 | Y30: =IF(X30>0,(X30-N30*3)/X30,0) -> 0.44861111 | AA30: =+ROUNDUP(L30*0.925,-3)*6 -> 420000 | AB30: =IF(AA30>0,(AA30-N30*6)/AA30,0) -> 0.43285714 | AC30: =+E30*AD30/12 -> 68000 | AD30: =+ROUNDUP(L30*0.9,-3)*12 -> 816000 | AE30: =IF(AD30>0,(AD30-N30*12)/AD30,0) -> 0.41617647
A31: Camisa Oversize Peruana | B31: M | C31: Blanco | D31: Sin estampar | E31: 4 | F31: =IF(A31="","",VLOOKUP(A31,'Cotizador Compras'!$A$5:$J$21,2,FALSE)) -> YOUR BRAND | G31: =IF(A31="","",VLOOKUP(A31,'Cotizador Compras'!$A$5:$J$21,3,FALSE)) -> 37000 | H31: =IF(OR(A31="",D31=""),"",IF(D31="Sin estampar",0,IF(D31="Pecho",VLOOKUP(A31,'Cotizador Compras'!$A$5:$J$21,4,FALSE),IF(D31="Espalda",VLOOKUP(A31,'Cotizador Compras'!$A$5:$J$21,5,FALSE),VLOOKUP(A31,'Cotizador Compras'!$A$5:$J$21,4,FALSE)+VLOOKUP(A31,'Cotizador Compras'!$A$5:$J$21,5,FALSE))))) -> 0 | I31: =IF(A31="","",VLOOKUP(A31,'Cotizador Compras'!$A$5:$J$21,6,FALSE)) -> 1700 | J31: =IF(A31="","",VLOOKUP(A31,'Cotizador Compras'!$A$5:$J$21,7,FALSE)) -> 1000 | K31: =IF(OR(A31="",E31=""),"",(G31+H31+I31+J31)*E31) -> 158800 | L31: =IF(A31="","",IF(D31="Sin estampar",VLOOKUP(A31,'Cotizador Compras'!$A$5:$J$21,8,FALSE),IF(D31="Pecho",VLOOKUP(A31,'Cotizador Compras'!$A$5:$J$21,10,FALSE),VLOOKUP(A31,'Cotizador Compras'!$A$5:$J$21,9,FALSE)))) -> 75000 | M31: =IF(OR(A31="",E31=""),"",L31*E31) -> 300000 | N31: =+G31+H31+I31+J31 -> 39700 | O31: =IF(L31>0,(L31-N31)/L31,0) -> 0.47066667 | P31: =CONCATENATE(A31," ",B31," ",C31) -> Camisa Oversize Peruana M Blanco | Q31: Camisa Oversize Peruana M Blanco | R31: =SUMIF($P$26:$P$159,Q31,$E$26:$E$159) -> 6 | T31: =E31*G31 -> 148000 | X31: =ROUNDUP(L31*0.95,-3)*3 -> 216000 | Y31: =IF(X31>0,(X31-N31*3)/X31,0) -> 0.44861111 | AA31: =+ROUNDUP(L31*0.925,-3)*6 -> 420000 | AB31: =IF(AA31>0,(AA31-N31*6)/AA31,0) -> 0.43285714 | AC31: =+E31*AD31/12 -> 272000 | AD31: =+ROUNDUP(L31*0.9,-3)*12 -> 816000 | AE31: =IF(AD31>0,(AD31-N31*12)/AD31,0) -> 0.41617647
A32: Camisa Oversize Peruana | B32: L | C32: Blanco | D32: Sin estampar | E32: 4 | F32: =IF(A32="","",VLOOKUP(A32,'Cotizador Compras'!$A$5:$J$21,2,FALSE)) -> YOUR BRAND | G32: =IF(A32="","",VLOOKUP(A32,'Cotizador Compras'!$A$5:$J$21,3,FALSE)) -> 37000 | H32: =IF(OR(A32="",D32=""),"",IF(D32="Sin estampar",0,IF(D32="Pecho",VLOOKUP(A32,'Cotizador Compras'!$A$5:$J$21,4,FALSE),IF(D32="Espalda",VLOOKUP(A32,'Cotizador Compras'!$A$5:$J$21,5,FALSE),VLOOKUP(A32,'Cotizador Compras'!$A$5:$J$21,4,FALSE)+VLOOKUP(A32,'Cotizador Compras'!$A$5:$J$21,5,FALSE))))) -> 0 | I32: =IF(A32="","",VLOOKUP(A32,'Cotizador Compras'!$A$5:$J$21,6,FALSE)) -> 1700 | J32: =IF(A32="","",VLOOKUP(A32,'Cotizador Compras'!$A$5:$J$21,7,FALSE)) -> 1000 | K32: =IF(OR(A32="",E32=""),"",(G32+H32+I32+J32)*E32) -> 158800 | L32: =IF(A32="","",IF(D32="Sin estampar",VLOOKUP(A32,'Cotizador Compras'!$A$5:$J$21,8,FALSE),IF(D32="Pecho",VLOOKUP(A32,'Cotizador Compras'!$A$5:$J$21,10,FALSE),VLOOKUP(A32,'Cotizador Compras'!$A$5:$J$21,9,FALSE)))) -> 75000 | M32: =IF(OR(A32="",E32=""),"",L32*E32) -> 300000 | N32: =+G32+H32+I32+J32 -> 39700 | O32: =IF(L32>0,(L32-N32)/L32,0) -> 0.47066667 | P32: =CONCATENATE(A32," ",B32," ",C32) -> Camisa Oversize Peruana L Blanco | Q32: Camisa Oversize Peruana L Blanco | R32: =SUMIF($P$26:$P$159,Q32,$E$26:$E$159) -> 6 | T32: =E32*G32 -> 148000 | X32: =ROUNDUP(L32*0.95,-3)*3 -> 216000 | Y32: =IF(X32>0,(X32-N32*3)/X32,0) -> 0.44861111 | AA32: =+ROUNDUP(L32*0.925,-3)*6 -> 420000 | AB32: =IF(AA32>0,(AA32-N32*6)/AA32,0) -> 0.43285714 | AC32: =+E32*AD32/12 -> 272000 | AD32: =+ROUNDUP(L32*0.9,-3)*12 -> 816000 | AE32: =IF(AD32>0,(AD32-N32*12)/AD32,0) -> 0.41617647
A33: Camisa Oversize Peruana | B33: XL | C33: Blanco | D33: Sin estampar | E33: 4 | F33: =IF(A33="","",VLOOKUP(A33,'Cotizador Compras'!$A$5:$J$21,2,FALSE)) -> YOUR BRAND | G33: =IF(A33="","",VLOOKUP(A33,'Cotizador Compras'!$A$5:$J$21,3,FALSE)) -> 37000 | H33: =IF(OR(A33="",D33=""),"",IF(D33="Sin estampar",0,IF(D33="Pecho",VLOOKUP(A33,'Cotizador Compras'!$A$5:$J$21,4,FALSE),IF(D33="Espalda",VLOOKUP(A33,'Cotizador Compras'!$A$5:$J$21,5,FALSE),VLOOKUP(A33,'Cotizador Compras'!$A$5:$J$21,4,FALSE)+VLOOKUP(A33,'Cotizador Compras'!$A$5:$J$21,5,FALSE))))) -> 0 | I33: =IF(A33="","",VLOOKUP(A33,'Cotizador Compras'!$A$5:$J$21,6,FALSE)) -> 1700 | J33: =IF(A33="","",VLOOKUP(A33,'Cotizador Compras'!$A$5:$J$21,7,FALSE)) -> 1000 | K33: =IF(OR(A33="",E33=""),"",(G33+H33+I33+J33)*E33) -> 158800 | L33: =IF(A33="","",IF(D33="Sin estampar",VLOOKUP(A33,'Cotizador Compras'!$A$5:$J$21,8,FALSE),IF(D33="Pecho",VLOOKUP(A33,'Cotizador Compras'!$A$5:$J$21,10,FALSE),VLOOKUP(A33,'Cotizador Compras'!$A$5:$J$21,9,FALSE)))) -> 75000 | M33: =IF(OR(A33="",E33=""),"",L33*E33) -> 300000 | N33: =+G33+H33+I33+J33 -> 39700 | O33: =IF(L33>0,(L33-N33)/L33,0) -> 0.47066667 | P33: =CONCATENATE(A33," ",B33," ",C33) -> Camisa Oversize Peruana XL Blanco | Q33: Camisa Oversize Peruana XL Blanco | R33: =SUMIF($P$26:$P$159,Q33,$E$26:$E$159) -> 6 | T33: =E33*G33 -> 148000 | X33: =ROUNDUP(L33*0.95,-3)*3 -> 216000 | Y33: =IF(X33>0,(X33-N33*3)/X33,0) -> 0.44861111 | AA33: =+ROUNDUP(L33*0.925,-3)*6 -> 420000 | AB33: =IF(AA33>0,(AA33-N33*6)/AA33,0) -> 0.43285714 | AC33: =+E33*AD33/12 -> 272000 | AD33: =+ROUNDUP(L33*0.9,-3)*12 -> 816000 | AE33: =IF(AD33>0,(AD33-N33*12)/AD33,0) -> 0.41617647
A34: Camisa Oversize Peruana | B34: S | C34: Perla | D34: Sin estampar | E34: 1 | F34: =IF(A34="","",VLOOKUP(A34,'Cotizador Compras'!$A$5:$J$21,2,FALSE)) -> YOUR BRAND | G34: =IF(A34="","",VLOOKUP(A34,'Cotizador Compras'!$A$5:$J$21,3,FALSE)) -> 37000 | H34: =IF(OR(A34="",D34=""),"",IF(D34="Sin estampar",0,IF(D34="Pecho",VLOOKUP(A34,'Cotizador Compras'!$A$5:$J$21,4,FALSE),IF(D34="Espalda",VLOOKUP(A34,'Cotizador Compras'!$A$5:$J$21,5,FALSE),VLOOKUP(A34,'Cotizador Compras'!$A$5:$J$21,4,FALSE)+VLOOKUP(A34,'Cotizador Compras'!$A$5:$J$21,5,FALSE))))) -> 0 | I34: =IF(A34="","",VLOOKUP(A34,'Cotizador Compras'!$A$5:$J$21,6,FALSE)) -> 1700 | J34: =IF(A34="","",VLOOKUP(A34,'Cotizador Compras'!$A$5:$J$21,7,FALSE)) -> 1000 | K34: =IF(OR(A34="",E34=""),"",(G34+H34+I34+J34)*E34) -> 39700 | L34: =IF(A34="","",IF(D34="Sin estampar",VLOOKUP(A34,'Cotizador Compras'!$A$5:$J$21,8,FALSE),IF(D34="Pecho",VLOOKUP(A34,'Cotizador Compras'!$A$5:$J$21,10,FALSE),VLOOKUP(A34,'Cotizador Compras'!$A$5:$J$21,9,FALSE)))) -> 75000 | M34: =IF(OR(A34="",E34=""),"",L34*E34) -> 75000 | N34: =+G34+H34+I34+J34 -> 39700 | O34: =IF(L34>0,(L34-N34)/L34,0) -> 0.47066667 | P34: =CONCATENATE(A34," ",B34," ",C34) -> Camisa Oversize Peruana S Perla | Q34: Camisa Oversize Peruana S Perla | R34: =SUMIF($P$26:$P$159,Q34,$E$26:$E$159) -> 2 | T34: =E34*G34 -> 37000 | X34: =ROUNDUP(L34*0.95,-3)*3 -> 216000 | Y34: =IF(X34>0,(X34-N34*3)/X34,0) -> 0.44861111 | AA34: =+ROUNDUP(L34*0.925,-3)*6 -> 420000 | AB34: =IF(AA34>0,(AA34-N34*6)/AA34,0) -> 0.43285714 | AC34: =+E34*AD34/12 -> 68000 | AD34: =+ROUNDUP(L34*0.9,-3)*12 -> 816000 | AE34: =IF(AD34>0,(AD34-N34*12)/AD34,0) -> 0.41617647
A35: Camisa Oversize Peruana | B35: M | C35: Perla | D35: Sin estampar | E35: 4 | F35: =IF(A35="","",VLOOKUP(A35,'Cotizador Compras'!$A$5:$J$21,2,FALSE)) -> YOUR BRAND | G35: =IF(A35="","",VLOOKUP(A35,'Cotizador Compras'!$A$5:$J$21,3,FALSE)) -> 37000 | H35: =IF(OR(A35="",D35=""),"",IF(D35="Sin estampar",0,IF(D35="Pecho",VLOOKUP(A35,'Cotizador Compras'!$A$5:$J$21,4,FALSE),IF(D35="Espalda",VLOOKUP(A35,'Cotizador Compras'!$A$5:$J$21,5,FALSE),VLOOKUP(A35,'Cotizador Compras'!$A$5:$J$21,4,FALSE)+VLOOKUP(A35,'Cotizador Compras'!$A$5:$J$21,5,FALSE))))) -> 0 | I35: =IF(A35="","",VLOOKUP(A35,'Cotizador Compras'!$A$5:$J$21,6,FALSE)) -> 1700 | J35: =IF(A35="","",VLOOKUP(A35,'Cotizador Compras'!$A$5:$J$21,7,FALSE)) -> 1000 | K35: =IF(OR(A35="",E35=""),"",(G35+H35+I35+J35)*E35) -> 158800 | L35: =IF(A35="","",IF(D35="Sin estampar",VLOOKUP(A35,'Cotizador Compras'!$A$5:$J$21,8,FALSE),IF(D35="Pecho",VLOOKUP(A35,'Cotizador Compras'!$A$5:$J$21,10,FALSE),VLOOKUP(A35,'Cotizador Compras'!$A$5:$J$21,9,FALSE)))) -> 75000 | M35: =IF(OR(A35="",E35=""),"",L35*E35) -> 300000 | N35: =+G35+H35+I35+J35 -> 39700 | O35: =IF(L35>0,(L35-N35)/L35,0) -> 0.47066667 | P35: =CONCATENATE(A35," ",B35," ",C35) -> Camisa Oversize Peruana M Perla | Q35: Camisa Oversize Peruana M Perla | R35: =SUMIF($P$26:$P$159,Q35,$E$26:$E$159) -> 6 | T35: =E35*G35 -> 148000 | X35: =ROUNDUP(L35*0.95,-3)*3 -> 216000 | Y35: =IF(X35>0,(X35-N35*3)/X35,0) -> 0.44861111 | AA35: =+ROUNDUP(L35*0.925,-3)*6 -> 420000 | AB35: =IF(AA35>0,(AA35-N35*6)/AA35,0) -> 0.43285714 | AC35: =+E35*AD35/12 -> 272000 | AD35: =+ROUNDUP(L35*0.9,-3)*12 -> 816000 | AE35: =IF(AD35>0,(AD35-N35*12)/AD35,0) -> 0.41617647
A36: Camisa Oversize Peruana | B36: L | C36: Perla | D36: Sin estampar | E36: 4 | F36: =IF(A36="","",VLOOKUP(A36,'Cotizador Compras'!$A$5:$J$21,2,FALSE)) -> YOUR BRAND | G36: =IF(A36="","",VLOOKUP(A36,'Cotizador Compras'!$A$5:$J$21,3,FALSE)) -> 37000 | H36: =IF(OR(A36="",D36=""),"",IF(D36="Sin estampar",0,IF(D36="Pecho",VLOOKUP(A36,'Cotizador Compras'!$A$5:$J$21,4,FALSE),IF(D36="Espalda",VLOOKUP(A36,'Cotizador Compras'!$A$5:$J$21,5,FALSE),VLOOKUP(A36,'Cotizador Compras'!$A$5:$J$21,4,FALSE)+VLOOKUP(A36,'Cotizador Compras'!$A$5:$J$21,5,FALSE))))) -> 0 | I36: =IF(A36="","",VLOOKUP(A36,'Cotizador Compras'!$A$5:$J$21,6,FALSE)) -> 1700 | J36: =IF(A36="","",VLOOKUP(A36,'Cotizador Compras'!$A$5:$J$21,7,FALSE)) -> 1000 | K36: =IF(OR(A36="",E36=""),"",(G36+H36+I36+J36)*E36) -> 158800 | L36: =IF(A36="","",IF(D36="Sin estampar",VLOOKUP(A36,'Cotizador Compras'!$A$5:$J$21,8,FALSE),IF(D36="Pecho",VLOOKUP(A36,'Cotizador Compras'!$A$5:$J$21,10,FALSE),VLOOKUP(A36,'Cotizador Compras'!$A$5:$J$21,9,FALSE)))) -> 75000 | M36: =IF(OR(A36="",E36=""),"",L36*E36) -> 300000 | N36: =+G36+H36+I36+J36 -> 39700 | O36: =IF(L36>0,(L36-N36)/L36,0) -> 0.47066667 | P36: =CONCATENATE(A36," ",B36," ",C36) -> Camisa Oversize Peruana L Perla | Q36: Camisa Oversize Peruana L Perla | R36: =SUMIF($P$26:$P$159,Q36,$E$26:$E$159) -> 6 | T36: =E36*G36 -> 148000 | X36: =ROUNDUP(L36*0.95,-3)*3 -> 216000 | Y36: =IF(X36>0,(X36-N36*3)/X36,0) -> 0.44861111 | AA36: =+ROUNDUP(L36*0.925,-3)*6 -> 420000 | AB36: =IF(AA36>0,(AA36-N36*6)/AA36,0) -> 0.43285714 | AC36: =+E36*AD36/12 -> 272000 | AD36: =+ROUNDUP(L36*0.9,-3)*12 -> 816000 | AE36: =IF(AD36>0,(AD36-N36*12)/AD36,0) -> 0.41617647
A37: Camisa Oversize Peruana | B37: XL | C37: Perla | D37: Sin estampar | E37: 4 | F37: =IF(A37="","",VLOOKUP(A37,'Cotizador Compras'!$A$5:$J$21,2,FALSE)) -> YOUR BRAND | G37: =IF(A37="","",VLOOKUP(A37,'Cotizador Compras'!$A$5:$J$21,3,FALSE)) -> 37000 | H37: =IF(OR(A37="",D37=""),"",IF(D37="Sin estampar",0,IF(D37="Pecho",VLOOKUP(A37,'Cotizador Compras'!$A$5:$J$21,4,FALSE),IF(D37="Espalda",VLOOKUP(A37,'Cotizador Compras'!$A$5:$J$21,5,FALSE),VLOOKUP(A37,'Cotizador Compras'!$A$5:$J$21,4,FALSE)+VLOOKUP(A37,'Cotizador Compras'!$A$5:$J$21,5,FALSE))))) -> 0 | I37: =IF(A37="","",VLOOKUP(A37,'Cotizador Compras'!$A$5:$J$21,6,FALSE)) -> 1700 | J37: =IF(A37="","",VLOOKUP(A37,'Cotizador Compras'!$A$5:$J$21,7,FALSE)) -> 1000 | K37: =IF(OR(A37="",E37=""),"",(G37+H37+I37+J37)*E37) -> 158800 | L37: =IF(A37="","",IF(D37="Sin estampar",VLOOKUP(A37,'Cotizador Compras'!$A$5:$J$21,8,FALSE),IF(D37="Pecho",VLOOKUP(A37,'Cotizador Compras'!$A$5:$J$21,10,FALSE),VLOOKUP(A37,'Cotizador Compras'!$A$5:$J$21,9,FALSE)))) -> 75000 | M37: =IF(OR(A37="",E37=""),"",L37*E37) -> 300000 | N37: =+G37+H37+I37+J37 -> 39700 | O37: =IF(L37>0,(L37-N37)/L37,0) -> 0.47066667 | P37: =CONCATENATE(A37," ",B37," ",C37) -> Camisa Oversize Peruana XL Perla | Q37: Camisa Oversize Peruana XL Perla | R37: =SUMIF($P$26:$P$159,Q37,$E$26:$E$159) -> 6 | T37: =E37*G37 -> 148000 | X37: =ROUNDUP(L37*0.95,-3)*3 -> 216000 | Y37: =IF(X37>0,(X37-N37*3)/X37,0) -> 0.44861111 | AA37: =+ROUNDUP(L37*0.925,-3)*6 -> 420000 | AB37: =IF(AA37>0,(AA37-N37*6)/AA37,0) -> 0.43285714 | AC37: =+E37*AD37/12 -> 272000 | AD37: =+ROUNDUP(L37*0.9,-3)*12 -> 816000 | AE37: =IF(AD37>0,(AD37-N37*12)/AD37,0) -> 0.41617647
A38: Camisa Oversize Peruana | B38: S | C38: Beige | D38: Sin estampar | E38: 1 | F38: =IF(A38="","",VLOOKUP(A38,'Cotizador Compras'!$A$5:$J$21,2,FALSE)) -> YOUR BRAND | G38: =IF(A38="","",VLOOKUP(A38,'Cotizador Compras'!$A$5:$J$21,3,FALSE)) -> 37000 | H38: =IF(OR(A38="",D38=""),"",IF(D38="Sin estampar",0,IF(D38="Pecho",VLOOKUP(A38,'Cotizador Compras'!$A$5:$J$21,4,FALSE),IF(D38="Espalda",VLOOKUP(A38,'Cotizador Compras'!$A$5:$J$21,5,FALSE),VLOOKUP(A38,'Cotizador Compras'!$A$5:$J$21,4,FALSE)+VLOOKUP(A38,'Cotizador Compras'!$A$5:$J$21,5,FALSE))))) -> 0 | I38: =IF(A38="","",VLOOKUP(A38,'Cotizador Compras'!$A$5:$J$21,6,FALSE)) -> 1700 | J38: =IF(A38="","",VLOOKUP(A38,'Cotizador Compras'!$A$5:$J$21,7,FALSE)) -> 1000 | K38: =IF(OR(A38="",E38=""),"",(G38+H38+I38+J38)*E38) -> 39700 | L38: =IF(A38="","",IF(D38="Sin estampar",VLOOKUP(A38,'Cotizador Compras'!$A$5:$J$21,8,FALSE),IF(D38="Pecho",VLOOKUP(A38,'Cotizador Compras'!$A$5:$J$21,10,FALSE),VLOOKUP(A38,'Cotizador Compras'!$A$5:$J$21,9,FALSE)))) -> 75000 | M38: =IF(OR(A38="",E38=""),"",L38*E38) -> 75000 | N38: =+G38+H38+I38+J38 -> 39700 | O38: =IF(L38>0,(L38-N38)/L38,0) -> 0.47066667 | P38: =CONCATENATE(A38," ",B38," ",C38) -> Camisa Oversize Peruana S Beige | Q38: Camisa Oversize Peruana S Beige | R38: =SUMIF($P$26:$P$159,Q38,$E$26:$E$159) -> 2 | T38: =E38*G38 -> 37000 | X38: =ROUNDUP(L38*0.95,-3)*3 -> 216000 | Y38: =IF(X38>0,(X38-N38*3)/X38,0) -> 0.44861111 | AA38: =+ROUNDUP(L38*0.925,-3)*6 -> 420000 | AB38: =IF(AA38>0,(AA38-N38*6)/AA38,0) -> 0.43285714 | AC38: =+E38*AD38/12 -> 68000 | AD38: =+ROUNDUP(L38*0.9,-3)*12 -> 816000 | AE38: =IF(AD38>0,(AD38-N38*12)/AD38,0) -> 0.41617647
... A73: Camisa Oversize Peruana | B73: XL | C73: Negro | D73: Full (Pecho+Espalda) | E73: 2 | F73: =IF(A73="","",VLOOKUP(A73,'Cotizador Compras'!$A$5:$J$21,2,FALSE)) -> YOUR BRAND | G73: =IF(A73="","",VLOOKUP(A73,'Cotizador Compras'!$A$5:$J$21,3,FALSE)) -> 37000 | H73: =IF(OR(A73="",D73=""),"",IF(D73="Sin estampar",0,IF(D73="Pecho",VLOOKUP(A73,'Cotizador Compras'!$A$5:$J$21,4,FALSE),IF(D73="Espalda",VLOOKUP(A73,'Cotizador Compras'!$A$5:$J$21,5,FALSE),VLOOKUP(A73,'Cotizador Compras'!$A$5:$J$21,4,FALSE)+VLOOKUP(A73,'Cotizador Compras'!$A$5:$J$21,5,FALSE))))) -> 14500 | I73: =IF(A73="","",VLOOKUP(A73,'Cotizador Compras'!$A$5:$J$21,6,FALSE)) -> 1700 | J73: =IF(A73="","",VLOOKUP(A73,'Cotizador Compras'!$A$5:$J$21,7,FALSE)) -> 1000 | K73: =IF(OR(A73="",E73=""),"",(G73+H73+I73+J73)*E73) -> 108400 | L73: =IF(A73="","",IF(D73="Sin estampar",VLOOKUP(A73,'Cotizador Compras'!$A$5:$J$21,8,FALSE),IF(D73="Pecho",VLOOKUP(A73,'Cotizador Compras'!$A$5:$J$21,10,FALSE),VLOOKUP(A73,'Cotizador Compras'!$A$5:$J$21,9,FALSE)))) -> 130000 | M73: =IF(OR(A73="",E73=""),"",L73*E73) -> 260000 | N73: =+G73+H73+I73+J73 -> 54200 | O73: =IF(L73>0,(L73-N73)/L73,0) -> 0.58307692 | P73: =CONCATENATE(A73," ",B73," ",C73) -> Camisa Oversize Peruana XL Negro | Q73: Buzo Cuello Redondo Oversized L Negro | R73: =SUMIF($P$26:$P$159,Q73,$E$26:$E$159) -> 4 | T73: =E73*G73 -> 74000 | X73: =ROUNDUP(L73*0.95,-3)*3 -> 372000 | Y73: =IF(X73>0,(X73-N73*3)/X73,0) -> 0.56290323 | AA73: =+ROUNDUP(L73*0.925,-3)*6 -> 726000 | AB73: =IF(AA73>0,(AA73-N73*6)/AA73,0) -> 0.55206612 | AC73: =+E73*AD73/12 -> 234000 | AD73: =+ROUNDUP(L73*0.9,-3)*12 -> 1404000 | AE73: =IF(AD73>0,(AD73-N73*12)/AD73,0) -> 0.53675214
A74: Camisa Boxy fit | B74: S | C74: Negro | D74: Sin estampar | E74: 1 | F74: YOUR BRAND | G74: =IF(A74="","",VLOOKUP(A74,'Cotizador Compras'!$A$5:$J$21,3,FALSE)) -> 37000 | H74: =IF(OR(A74="",D74=""),"",IF(D74="Sin estampar",0,IF(D74="Pecho",VLOOKUP(A74,'Cotizador Compras'!$A$5:$J$21,4,FALSE),IF(D74="Espalda",VLOOKUP(A74,'Cotizador Compras'!$A$5:$J$21,5,FALSE),VLOOKUP(A74,'Cotizador Compras'!$A$5:$J$21,4,FALSE)+VLOOKUP(A74,'Cotizador Compras'!$A$5:$J$21,5,FALSE))))) -> 0 | I74: =IF(A74="","",VLOOKUP(A74,'Cotizador Compras'!$A$5:$J$21,6,FALSE)) -> 1700 | J74: =IF(A74="","",VLOOKUP(A74,'Cotizador Compras'!$A$5:$J$21,7,FALSE)) -> 1000 | K74: =IF(OR(A74="",E74=""),"",(G74+H74+I74+J74)*E74) -> 39700 | L74: =IF(A74="","",IF(D74="Sin estampar",VLOOKUP(A74,'Cotizador Compras'!$A$5:$J$21,8,FALSE),IF(D74="Pecho",VLOOKUP(A74,'Cotizador Compras'!$A$5:$J$21,10,FALSE),VLOOKUP(A74,'Cotizador Compras'!$A$5:$J$21,9,FALSE)))) -> 75000 | M74: =IF(OR(A74="",E74=""),"",L74*E74) -> 75000 | N74: =+G74+H74+I74+J74 -> 39700 | O74: =IF(L74>0,(L74-N74)/L74,0) -> 0.47066667 | P74: =CONCATENATE(A74," ",B74," ",C74) -> Camisa Boxy fit S Negro | Q74: Buzo Cuello Redondo Oversized XL Negro | R74: =SUMIF($P$26:$P$159,Q74,$E$26:$E$159) -> 4 | T74: =E74*G74 -> 37000 | X74: =ROUNDUP(L74*0.95,-3)*3 -> 216000 | Y74: =IF(X74>0,(X74-N74*3)/X74,0) -> 0.44861111 | AA74: =+ROUNDUP(L74*0.925,-3)*6 -> 420000 | AB74: =IF(AA74>0,(AA74-N74*6)/AA74,0) -> 0.43285714 | AC74: =+E74*AD74/12 -> 68000 | AD74: =+ROUNDUP(L74*0.9,-3)*12 -> 816000 | AE74: =IF(AD74>0,(AD74-N74*12)/AD74,0) -> 0.41617647
A75: Camisa Boxy fit | B75: M | C75: Negro | D75: Sin estampar | E75: 2 | F75: YOUR BRAND | G75: =IF(A75="","",VLOOKUP(A75,'Cotizador Compras'!$A$5:$J$21,3,FALSE)) -> 37000 | H75: =IF(OR(A75="",D75=""),"",IF(D75="Sin estampar",0,IF(D75="Pecho",VLOOKUP(A75,'Cotizador Compras'!$A$5:$J$21,4,FALSE),IF(D75="Espalda",VLOOKUP(A75,'Cotizador Compras'!$A$5:$J$21,5,FALSE),VLOOKUP(A75,'Cotizador Compras'!$A$5:$J$21,4,FALSE)+VLOOKUP(A75,'Cotizador Compras'!$A$5:$J$21,5,FALSE))))) -> 0 | I75: =IF(A75="","",VLOOKUP(A75,'Cotizador Compras'!$A$5:$J$21,6,FALSE)) -> 1700 | J75: =IF(A75="","",VLOOKUP(A75,'Cotizador Compras'!$A$5:$J$21,7,FALSE)) -> 1000 | K75: =IF(OR(A75="",E75=""),"",(G75+H75+I75+J75)*E75) -> 79400 | L75: =IF(A75="","",IF(D75="Sin estampar",VLOOKUP(A75,'Cotizador Compras'!$A$5:$J$21,8,FALSE),IF(D75="Pecho",VLOOKUP(A75,'Cotizador Compras'!$A$5:$J$21,10,FALSE),VLOOKUP(A75,'Cotizador Compras'!$A$5:$J$21,9,FALSE)))) -> 75000 | M75: =IF(OR(A75="",E75=""),"",L75*E75) -> 150000 | N75: =+G75+H75+I75+J75 -> 39700 | O75: =IF(L75>0,(L75-N75)/L75,0) -> 0.47066667 | P75: =CONCATENATE(A75," ",B75," ",C75) -> Camisa Boxy fit M Negro | Q75: Buzo Cuello Redondo Oversized M Beige | R75: =SUMIF($P$26:$P$159,Q75,$E$26:$E$159) -> 2 | T75: =E75*G75 -> 74000 | X75: =ROUNDUP(L75*0.95,-3)*3 -> 216000 | Y75: =IF(X75>0,(X75-N75*3)/X75,0) -> 0.44861111 | AA75: =+ROUNDUP(L75*0.925,-3)*6 -> 420000 | AB75: =IF(AA75>0,(AA75-N75*6)/AA75,0) -> 0.43285714 | AC75: =+E75*AD75/12 -> 136000 | AD75: =+ROUNDUP(L75*0.9,-3)*12 -> 816000 | AE75: =IF(AD75>0,(AD75-N75*12)/AD75,0) -> 0.41617647
A76: Camisa Boxy fit | B76: L | C76: Negro | D76: Sin estampar | E76: 2 | F76: YOUR BRAND | G76: =IF(A76="","",VLOOKUP(A76,'Cotizador Compras'!$A$5:$J$21,3,FALSE)) -> 37000 | H76: =IF(OR(A76="",D76=""),"",IF(D76="Sin estampar",0,IF(D76="Pecho",VLOOKUP(A76,'Cotizador Compras'!$A$5:$J$21,4,FALSE),IF(D76="Espalda",VLOOKUP(A76,'Cotizador Compras'!$A$5:$J$21,5,FALSE),VLOOKUP(A76,'Cotizador Compras'!$A$5:$J$21,4,FALSE)+VLOOKUP(A76,'Cotizador Compras'!$A$5:$J$21,5,FALSE))))) -> 0 | I76: =IF(A76="","",VLOOKUP(A76,'Cotizador Compras'!$A$5:$J$21,6,FALSE)) -> 1700 | J76: =IF(A76="","",VLOOKUP(A76,'Cotizador Compras'!$A$5:$J$21,7,FALSE)) -> 1000 | K76: =IF(OR(A76="",E76=""),"",(G76+H76+I76+J76)*E76) -> 79400 | L76: =IF(A76="","",IF(D76="Sin estampar",VLOOKUP(A76,'Cotizador Compras'!$A$5:$J$21,8,FALSE),IF(D76="Pecho",VLOOKUP(A76,'Cotizador Compras'!$A$5:$J$21,10,FALSE),VLOOKUP(A76,'Cotizador Compras'!$A$5:$J$21,9,FALSE)))) -> 75000 | M76: =IF(OR(A76="",E76=""),"",L76*E76) -> 150000 | N76: =+G76+H76+I76+J76 -> 39700 | O76: =IF(L76>0,(L76-N76)/L76,0) -> 0.47066667 | P76: =CONCATENATE(A76," ",B76," ",C76) -> Camisa Boxy fit L Negro | Q76: Buzo Cuello Redondo Oversized L Beige | R76: =SUMIF($P$26:$P$159,Q76,$E$26:$E$159) -> 4 | T76: =E76*G76 -> 74000 | X76: =ROUNDUP(L76*0.95,-3)*3 -> 216000 | Y76: =IF(X76>0,(X76-N76*3)/X76,0) -> 0.44861111 | AA76: =+ROUNDUP(L76*0.925,-3)*6 -> 420000 | AB76: =IF(AA76>0,(AA76-N76*6)/AA76,0) -> 0.43285714 | AC76: =+E76*AD76/12 -> 136000 | AD76: =+ROUNDUP(L76*0.9,-3)*12 -> 816000 | AE76: =IF(AD76>0,(AD76-N76*12)/AD76,0) -> 0.41617647
A77: Camisa Boxy fit | B77: S | C77: Blanco | D77: Sin estampar | E77: 1 | F77: YOUR BRAND | G77: =IF(A77="","",VLOOKUP(A77,'Cotizador Compras'!$A$5:$J$21,3,FALSE)) -> 37000 | H77: =IF(OR(A77="",D77=""),"",IF(D77="Sin estampar",0,IF(D77="Pecho",VLOOKUP(A77,'Cotizador Compras'!$A$5:$J$21,4,FALSE),IF(D77="Espalda",VLOOKUP(A77,'Cotizador Compras'!$A$5:$J$21,5,FALSE),VLOOKUP(A77,'Cotizador Compras'!$A$5:$J$21,4,FALSE)+VLOOKUP(A77,'Cotizador Compras'!$A$5:$J$21,5,FALSE))))) -> 0 | I77: =IF(A77="","",VLOOKUP(A77,'Cotizador Compras'!$A$5:$J$21,6,FALSE)) -> 1700 | J77: =IF(A77="","",VLOOKUP(A77,'Cotizador Compras'!$A$5:$J$21,7,FALSE)) -> 1000 | K77: =IF(OR(A77="",E77=""),"",(G77+H77+I77+J77)*E77) -> 39700 | L77: =IF(A77="","",IF(D77="Sin estampar",VLOOKUP(A77,'Cotizador Compras'!$A$5:$J$21,8,FALSE),IF(D77="Pecho",VLOOKUP(A77,'Cotizador Compras'!$A$5:$J$21,10,FALSE),VLOOKUP(A77,'Cotizador Compras'!$A$5:$J$21,9,FALSE)))) -> 75000 | M77: =IF(OR(A77="",E77=""),"",L77*E77) -> 75000 | N77: =+G77+H77+I77+J77 -> 39700 | O77: =IF(L77>0,(L77-N77)/L77,0) -> 0.47066667 | P77: =CONCATENATE(A77," ",B77," ",C77) -> Camisa Boxy fit S Blanco | Q77: Buzo Cuello Redondo Oversized XL Beige | R77: =SUMIF($P$26:$P$159,Q77,$E$26:$E$159) -> 4 | T77: =E77*G77 -> 37000 | X77: =ROUNDUP(L77*0.95,-3)*3 -> 216000 | Y77: =IF(X77>0,(X77-N77*3)/X77,0) -> 0.44861111 | AA77: =+ROUNDUP(L77*0.925,-3)*6 -> 420000 | AB77: =IF(AA77>0,(AA77-N77*6)/AA77,0) -> 0.43285714 | AC77: =+E77*AD77/12 -> 68000 | AD77: =+ROUNDUP(L77*0.9,-3)*12 -> 816000 | AE77: =IF(AD77>0,(AD77-N77*12)/AD77,0) -> 0.41617647
A78: Camisa Boxy fit | B78: M | C78: Blanco | D78: Sin estampar | E78: 2 | F78: YOUR BRAND | G78: =IF(A78="","",VLOOKUP(A78,'Cotizador Compras'!$A$5:$J$21,3,FALSE)) -> 37000 | H78: =IF(OR(A78="",D78=""),"",IF(D78="Sin estampar",0,IF(D78="Pecho",VLOOKUP(A78,'Cotizador Compras'!$A$5:$J$21,4,FALSE),IF(D78="Espalda",VLOOKUP(A78,'Cotizador Compras'!$A$5:$J$21,5,FALSE),VLOOKUP(A78,'Cotizador Compras'!$A$5:$J$21,4,FALSE)+VLOOKUP(A78,'Cotizador Compras'!$A$5:$J$21,5,FALSE))))) -> 0 | I78: =IF(A78="","",VLOOKUP(A78,'Cotizador Compras'!$A$5:$J$21,6,FALSE)) -> 1700 | J78: =IF(A78="","",VLOOKUP(A78,'Cotizador Compras'!$A$5:$J$21,7,FALSE)) -> 1000 | K78: =IF(OR(A78="",E78=""),"",(G78+H78+I78+J78)*E78) -> 79400 | L78: =IF(A78="","",IF(D78="Sin estampar",VLOOKUP(A78,'Cotizador Compras'!$A$5:$J$21,8,FALSE),IF(D78="Pecho",VLOOKUP(A78,'Cotizador Compras'!$A$5:$J$21,10,FALSE),VLOOKUP(A78,'Cotizador Compras'!$A$5:$J$21,9,FALSE)))) -> 75000 | M78: =IF(OR(A78="",E78=""),"",L78*E78) -> 150000 | N78: =+G78+H78+I78+J78 -> 39700 | O78: =IF(L78>0,(L78-N78)/L78,0) -> 0.47066667 | P78: =CONCATENATE(A78," ",B78," ",C78) -> Camisa Boxy fit M Blanco | Q78: Buzo Cuello Redondo Oversized 2XL Negro | R78: =SUMIF($P$26:$P$159,Q78,$E$26:$E$159) -> 2 | T78: =E78*G78 -> 74000 | X78: =ROUNDUP(L78*0.95,-3)*3 -> 216000 | Y78: =IF(X78>0,(X78-N78*3)/X78,0) -> 0.44861111 | AA78: =+ROUNDUP(L78*0.925,-3)*6 -> 420000 | AB78: =IF(AA78>0,(AA78-N78*6)/AA78,0) -> 0.43285714 | AC78: =+E78*AD78/12 -> 136000 | AD78: =+ROUNDUP(L78*0.9,-3)*12 -> 816000 | AE78: =IF(AD78>0,(AD78-N78*12)/AD78,0) -> 0.41617647
A79: Camisa Boxy fit | B79: L | C79: Blanco | D79: Sin estampar | E79: 2 | F79: YOUR BRAND | G79: =IF(A79="","",VLOOKUP(A79,'Cotizador Compras'!$A$5:$J$21,3,FALSE)) -> 37000 | H79: =IF(OR(A79="",D79=""),"",IF(D79="Sin estampar",0,IF(D79="Pecho",VLOOKUP(A79,'Cotizador Compras'!$A$5:$J$21,4,FALSE),IF(D79="Espalda",VLOOKUP(A79,'Cotizador Compras'!$A$5:$J$21,5,FALSE),VLOOKUP(A79,'Cotizador Compras'!$A$5:$J$21,4,FALSE)+VLOOKUP(A79,'Cotizador Compras'!$A$5:$J$21,5,FALSE))))) -> 0 | I79: =IF(A79="","",VLOOKUP(A79,'Cotizador Compras'!$A$5:$J$21,6,FALSE)) -> 1700 | J79: =IF(A79="","",VLOOKUP(A79,'Cotizador Compras'!$A$5:$J$21,7,FALSE)) -> 1000 | K79: =IF(OR(A79="",E79=""),"",(G79+H79+I79+J79)*E79) -> 79400 | L79: =IF(A79="","",IF(D79="Sin estampar",VLOOKUP(A79,'Cotizador Compras'!$A$5:$J$21,8,FALSE),IF(D79="Pecho",VLOOKUP(A79,'Cotizador Compras'!$A$5:$J$21,10,FALSE),VLOOKUP(A79,'Cotizador Compras'!$A$5:$J$21,9,FALSE)))) -> 75000 | M79: =IF(OR(A79="",E79=""),"",L79*E79) -> 150000 | N79: =+G79+H79+I79+J79 -> 39700 | O79: =IF(L79>0,(L79-N79)/L79,0) -> 0.47066667 | P79: =CONCATENATE(A79," ",B79," ",C79) -> Camisa Boxy fit L Blanco | Q79: Buzo Cuello Redondo Oversized 2XL Beige | R79: =SUMIF($P$26:$P$159,Q79,$E$26:$E$159) -> 2 | T79: =E79*G79 -> 74000 | X79: =ROUNDUP(L79*0.95,-3)*3 -> 216000 | Y79: =IF(X79>0,(X79-N79*3)/X79,0) -> 0.44861111 | AA79: =+ROUNDUP(L79*0.925,-3)*6 -> 420000 | AB79: =IF(AA79>0,(AA79-N79*6)/AA79,0) -> 0.43285714 | AC79: =+E79*AD79/12 -> 136000 | AD79: =+ROUNDUP(L79*0.9,-3)*12 -> 816000 | AE79: =IF(AD79>0,(AD79-N79*12)/AD79,0) -> 0.41617647
A80: Camisa Boxy fit | B80: S | C80: Plomo Plata | D80: Sin estampar | E80: 1 | F80: YOUR BRAND | G80: =IF(A80="","",VLOOKUP(A80,'Cotizador Compras'!$A$5:$J$21,3,FALSE)) -> 37000 | H80: =IF(OR(A80="",D80=""),"",IF(D80="Sin estampar",0,IF(D80="Pecho",VLOOKUP(A80,'Cotizador Compras'!$A$5:$J$21,4,FALSE),IF(D80="Espalda",VLOOKUP(A80,'Cotizador Compras'!$A$5:$J$21,5,FALSE),VLOOKUP(A80,'Cotizador Compras'!$A$5:$J$21,4,FALSE)+VLOOKUP(A80,'Cotizador Compras'!$A$5:$J$21,5,FALSE))))) -> 0 | I80: =IF(A80="","",VLOOKUP(A80,'Cotizador Compras'!$A$5:$J$21,6,FALSE)) -> 1700 | J80: =IF(A80="","",VLOOKUP(A80,'Cotizador Compras'!$A$5:$J$21,7,FALSE)) -> 1000 | K80: =IF(OR(A80="",E80=""),"",(G80+H80+I80+J80)*E80) -> 39700 | L80: =IF(A80="","",IF(D80="Sin estampar",VLOOKUP(A80,'Cotizador Compras'!$A$5:$J$21,8,FALSE),IF(D80="Pecho",VLOOKUP(A80,'Cotizador Compras'!$A$5:$J$21,10,FALSE),VLOOKUP(A80,'Cotizador Compras'!$A$5:$J$21,9,FALSE)))) -> 75000 | M80: =IF(OR(A80="",E80=""),"",L80*E80) -> 75000 | N80: =+G80+H80+I80+J80 -> 39700 | O80: =IF(L80>0,(L80-N80)/L80,0) -> 0.47066667 | P80: =CONCATENATE(A80," ",B80," ",C80) -> Camisa Boxy fit S Plomo Plata | Q80: Jogger Largo M Negro | R80: =SUMIF($P$26:$P$159,Q80,$E$26:$E$159) -> 4 | T80: =E80*G80 -> 37000 | X80: =ROUNDUP(L80*0.95,-3)*3 -> 216000 | Y80: =IF(X80>0,(X80-N80*3)/X80,0) -> 0.44861111 | AA80: =+ROUNDUP(L80*0.925,-3)*6 -> 420000 | AB80: =IF(AA80>0,(AA80-N80*6)/AA80,0) -> 0.43285714 | AC80: =+E80*AD80/12 -> 68000 | AD80: =+ROUNDUP(L80*0.9,-3)*12 -> 816000 | AE80: =IF(AD80>0,(AD80-N80*12)/AD80,0) -> 0.41617647
A81: Camisa Boxy fit | B81: M | C81: Plomo Plata | D81: Sin estampar | E81: 2 | F81: YOUR BRAND | G81: =IF(A81="","",VLOOKUP(A81,'Cotizador Compras'!$A$5:$J$21,3,FALSE)) -> 37000 | H81: =IF(OR(A81="",D81=""),"",IF(D81="Sin estampar",0,IF(D81="Pecho",VLOOKUP(A81,'Cotizador Compras'!$A$5:$J$21,4,FALSE),IF(D81="Espalda",VLOOKUP(A81,'Cotizador Compras'!$A$5:$J$21,5,FALSE),VLOOKUP(A81,'Cotizador Compras'!$A$5:$J$21,4,FALSE)+VLOOKUP(A81,'Cotizador Compras'!$A$5:$J$21,5,FALSE))))) -> 0 | I81: =IF(A81="","",VLOOKUP(A81,'Cotizador Compras'!$A$5:$J$21,6,FALSE)) -> 1700 | J81: =IF(A81="","",VLOOKUP(A81,'Cotizador Compras'!$A$5:$J$21,7,FALSE)) -> 1000 | K81: =IF(OR(A81="",E81=""),"",(G81+H81+I81+J81)*E81) -> 79400 | L81: =IF(A81="","",IF(D81="Sin estampar",VLOOKUP(A81,'Cotizador Compras'!$A$5:$J$21,8,FALSE),IF(D81="Pecho",VLOOKUP(A81,'Cotizador Compras'!$A$5:$J$21,10,FALSE),VLOOKUP(A81,'Cotizador Compras'!$A$5:$J$21,9,FALSE)))) -> 75000 | M81: =IF(OR(A81="",E81=""),"",L81*E81) -> 150000 | N81: =+G81+H81+I81+J81 -> 39700 | O81: =IF(L81>0,(L81-N81)/L81,0) -> 0.47066667 | P81: =CONCATENATE(A81," ",B81," ",C81) -> Camisa Boxy fit M Plomo Plata | Q81: Jogger Largo L Negro | R81: =SUMIF($P$26:$P$159,Q81,$E$26:$E$159) -> 4 | T81: =E81*G81 -> 74000 | X81: =ROUNDUP(L81*0.95,-3)*3 -> 216000 | Y81: =IF(X81>0,(X81-N81*3)/X81,0) -> 0.44861111 | AA81: =+ROUNDUP(L81*0.925,-3)*6 -> 420000 | AB81: =IF(AA81>0,(AA81-N81*6)/AA81,0) -> 0.43285714 | AC81: =+E81*AD81/12 -> 136000 | AD81: =+ROUNDUP(L81*0.9,-3)*12 -> 816000 | AE81: =IF(AD81>0,(AD81-N81*12)/AD81,0) -> 0.41617647
A82: Camisa Boxy fit | B82: L | C82: Plomo Plata | D82: Sin estampar | E82: 2 | F82: YOUR BRAND | G82: =IF(A82="","",VLOOKUP(A82,'Cotizador Compras'!$A$5:$J$21,3,FALSE)) -> 37000 | H82: =IF(OR(A82="",D82=""),"",IF(D82="Sin estampar",0,IF(D82="Pecho",VLOOKUP(A82,'Cotizador Compras'!$A$5:$J$21,4,FALSE),IF(D82="Espalda",VLOOKUP(A82,'Cotizador Compras'!$A$5:$J$21,5,FALSE),VLOOKUP(A82,'Cotizador Compras'!$A$5:$J$21,4,FALSE)+VLOOKUP(A82,'Cotizador Compras'!$A$5:$J$21,5,FALSE))))) -> 0 | I82: =IF(A82="","",VLOOKUP(A82,'Cotizador Compras'!$A$5:$J$21,6,FALSE)) -> 1700 | J82: =IF(A82="","",VLOOKUP(A82,'Cotizador Compras'!$A$5:$J$21,7,FALSE)) -> 1000 | K82: =IF(OR(A82="",E82=""),"",(G82+H82+I82+J82)*E82) -> 79400 | L82: =IF(A82="","",IF(D82="Sin estampar",VLOOKUP(A82,'Cotizador Compras'!$A$5:$J$21,8,FALSE),IF(D82="Pecho",VLOOKUP(A82,'Cotizador Compras'!$A$5:$J$21,10,FALSE),VLOOKUP(A82,'Cotizador Compras'!$A$5:$J$21,9,FALSE)))) -> 75000 | M82: =IF(OR(A82="",E82=""),"",L82*E82) -> 150000 | N82: =+G82+H82+I82+J82 -> 39700 | O82: =IF(L82>0,(L82-N82)/L82,0) -> 0.47066667 | P82: =CONCATENATE(A82," ",B82," ",C82) -> Camisa Boxy fit L Plomo Plata | Q82: Jogger Largo XL Negro | R82: =SUMIF($P$26:$P$159,Q82,$E$26:$E$159) -> 4 | T82: =E82*G82 -> 74000 | X82: =ROUNDUP(L82*0.95,-3)*3 -> 216000 | Y82: =IF(X82>0,(X82-N82*3)/X82,0) -> 0.44861111 | AA82: =+ROUNDUP(L82*0.925,-3)*6 -> 420000 | AB82: =IF(AA82>0,(AA82-N82*6)/AA82,0) -> 0.43285714 | AC82: =+E82*AD82/12 -> 136000 | AD82: =+ROUNDUP(L82*0.9,-3)*12 -> 816000 | AE82: =IF(AD82>0,(AD82-N82*12)/AD82,0) -> 0.41617647
A83: Camisa Boxy fit | B83: S | C83: Negro | D83: Pecho | E83: 1 | F83: YOUR BRAND | G83: =IF(A83="","",VLOOKUP(A83,'Cotizador Compras'!$A$5:$J$21,3,FALSE)) -> 37000 | H83: =IF(OR(A83="",D83=""),"",IF(D83="Sin estampar",0,IF(D83="Pecho",VLOOKUP(A83,'Cotizador Compras'!$A$5:$J$21,4,FALSE),IF(D83="Espalda",VLOOKUP(A83,'Cotizador Compras'!$A$5:$J$21,5,FALSE),VLOOKUP(A83,'Cotizador Compras'!$A$5:$J$21,4,FALSE)+VLOOKUP(A83,'Cotizador Compras'!$A$5:$J$21,5,FALSE))))) -> 3500 | I83: =IF(A83="","",VLOOKUP(A83,'Cotizador Compras'!$A$5:$J$21,6,FALSE)) -> 1700 | J83: =IF(A83="","",VLOOKUP(A83,'Cotizador Compras'!$A$5:$J$21,7,FALSE)) -> 1000 | K83: =IF(OR(A83="",E83=""),"",(G83+H83+I83+J83)*E83) -> 43200 | L83: =IF(A83="","",IF(D83="Sin estampar",VLOOKUP(A83,'Cotizador Compras'!$A$5:$J$21,8,FALSE),IF(D83="Pecho",VLOOKUP(A83,'Cotizador Compras'!$A$5:$J$21,10,FALSE),VLOOKUP(A83,'Cotizador Compras'!$A$5:$J$21,9,FALSE)))) -> 100000 | M83: =IF(OR(A83="",E83=""),"",L83*E83) -> 100000 | N83: =+G83+H83+I83+J83 -> 43200 | O83: =IF(L83>0,(L83-N83)/L83,0) -> 0.568 | P83: =CONCATENATE(A83," ",B83," ",C83) -> Camisa Boxy fit S Negro | Q83: Jogger Largo M Beige | R83: =SUMIF($P$26:$P$159,Q83,$E$26:$E$159) -> 4 | T83: =E83*G83 -> 37000 | X83: =ROUNDUP(L83*0.95,-3)*3 -> 285000 | Y83: =IF(X83>0,(X83-N83*3)/X83,0) -> 0.54526316 | AA83: =+ROUNDUP(L83*0.925,-3)*6 -> 558000 | AB83: =IF(AA83>0,(AA83-N83*6)/AA83,0) -> 0.53548387 | AC83: =+E83*AD83/12 -> 90000 | AD83: =+ROUNDUP(L83*0.9,-3)*12 -> 1080000 | AE83: =IF(AD83>0,(AD83-N83*12)/AD83,0) -> 0.52
A84: Camisa Boxy fit | B84: M | C84: Negro | D84: Pecho | E84: 2 | F84: YOUR BRAND | G84: =IF(A84="","",VLOOKUP(A84,'Cotizador Compras'!$A$5:$J$21,3,FALSE)) -> 37000 | H84: =IF(OR(A84="",D84=""),"",IF(D84="Sin estampar",0,IF(D84="Pecho",VLOOKUP(A84,'Cotizador Compras'!$A$5:$J$21,4,FALSE),IF(D84="Espalda",VLOOKUP(A84,'Cotizador Compras'!$A$5:$J$21,5,FALSE),VLOOKUP(A84,'Cotizador Compras'!$A$5:$J$21,4,FALSE)+VLOOKUP(A84,'Cotizador Compras'!$A$5:$J$21,5,FALSE))))) -> 3500 | I84: =IF(A84="","",VLOOKUP(A84,'Cotizador Compras'!$A$5:$J$21,6,FALSE)) -> 1700 | J84: =IF(A84="","",VLOOKUP(A84,'Cotizador Compras'!$A$5:$J$21,7,FALSE)) -> 1000 | K84: =IF(OR(A84="",E84=""),"",(G84+H84+I84+J84)*E84) -> 86400 | L84: =IF(A84="","",IF(D84="Sin estampar",VLOOKUP(A84,'Cotizador Compras'!$A$5:$J$21,8,FALSE),IF(D84="Pecho",VLOOKUP(A84,'Cotizador Compras'!$A$5:$J$21,10,FALSE),VLOOKUP(A84,'Cotizador Compras'!$A$5:$J$21,9,FALSE)))) -> 100000 | M84: =IF(OR(A84="",E84=""),"",L84*E84) -> 200000 | N84: =+G84+H84+I84+J84 -> 43200 | O84: =IF(L84>0,(L84-N84)/L84,0) -> 0.568 | P84: =CONCATENATE(A84," ",B84," ",C84) -> Camisa Boxy fit M Negro | Q84: Jogger Largo L Beige | R84: =SUMIF($P$26:$P$159,Q84,$E$26:$E$159) -> 4 | T84: =E84*G84 -> 74000 | X84: =ROUNDUP(L84*0.95,-3)*3 -> 285000 | Y84: =IF(X84>0,(X84-N84*3)/X84,0) -> 0.54526316 | AA84: =+ROUNDUP(L84*0.925,-3)*6 -> 558000 | AB84: =IF(AA84>0,(AA84-N84*6)/AA84,0) -> 0.53548387 | AC84: =+E84*AD84/12 -> 180000 | AD84: =+ROUNDUP(L84*0.9,-3)*12 -> 1080000 | AE84: =IF(AD84>0,(AD84-N84*12)/AD84,0) -> 0.52
A85: Camisa Boxy fit | B85: L | C85: Negro | D85: Pecho | E85: 2 | F85: YOUR BRAND | G85: =IF(A85="","",VLOOKUP(A85,'Cotizador Compras'!$A$5:$J$21,3,FALSE)) -> 37000 | H85: =IF(OR(A85="",D85=""),"",IF(D85="Sin estampar",0,IF(D85="Pecho",VLOOKUP(A85,'Cotizador Compras'!$A$5:$J$21,4,FALSE),IF(D85="Espalda",VLOOKUP(A85,'Cotizador Compras'!$A$5:$J$21,5,FALSE),VLOOKUP(A85,'Cotizador Compras'!$A$5:$J$21,4,FALSE)+VLOOKUP(A85,'Cotizador Compras'!$A$5:$J$21,5,FALSE))))) -> 3500 | I85: =IF(A85="","",VLOOKUP(A85,'Cotizador Compras'!$A$5:$J$21,6,FALSE)) -> 1700 | J85: =IF(A85="","",VLOOKUP(A85,'Cotizador Compras'!$A$5:$J$21,7,FALSE)) -> 1000 | K85: =IF(OR(A85="",E85=""),"",(G85+H85+I85+J85)*E85) -> 86400 | L85: =IF(A85="","",IF(D85="Sin estampar",VLOOKUP(A85,'Cotizador Compras'!$A$5:$J$21,8,FALSE),IF(D85="Pecho",VLOOKUP(A85,'Cotizador Compras'!$A$5:$J$21,10,FALSE),VLOOKUP(A85,'Cotizador Compras'!$A$5:$J$21,9,FALSE)))) -> 100000 | M85: =IF(OR(A85="",E85=""),"",L85*E85) -> 200000 | N85: =+G85+H85+I85+J85 -> 43200 | O85: =IF(L85>0,(L85-N85)/L85,0) -> 0.568 | P85: =CONCATENATE(A85," ",B85," ",C85) -> Camisa Boxy fit L Negro | Q85: Jogger Largo XL Beige | R85: =SUMIF($P$26:$P$159,Q85,$E$26:$E$159) -> 4 | T85: =E85*G85 -> 74000 | X85: =ROUNDUP(L85*0.95,-3)*3 -> 285000 | Y85: =IF(X85>0,(X85-N85*3)/X85,0) -> 0.54526316 | AA85: =+ROUNDUP(L85*0.925,-3)*6 -> 558000 | AB85: =IF(AA85>0,(AA85-N85*6)/AA85,0) -> 0.53548387 | AC85: =+E85*AD85/12 -> 180000 | AD85: =+ROUNDUP(L85*0.9,-3)*12 -> 1080000 | AE85: =IF(AD85>0,(AD85-N85*12)/AD85,0) -> 0.52
... A93: Hoodie | B93: L | C93: Acid Wash Gris | D93: Pecho | E93: 6 | F93: YOUR BRAND | G93: =IF(A93="","",VLOOKUP(A93,'Cotizador Compras'!$A$5:$J$21,3,FALSE)) -> 120000 | H93: =IF(OR(A93="",D93=""),"",IF(D93="Sin estampar",0,IF(D93="Pecho",VLOOKUP(A93,'Cotizador Compras'!$A$5:$J$21,4,FALSE),IF(D93="Espalda",VLOOKUP(A93,'Cotizador Compras'!$A$5:$J$21,5,FALSE),VLOOKUP(A93,'Cotizador Compras'!$A$5:$J$21,4,FALSE)+VLOOKUP(A93,'Cotizador Compras'!$A$5:$J$21,5,FALSE))))) -> 3500 | I93: =IF(A93="","",VLOOKUP(A93,'Cotizador Compras'!$A$5:$J$21,6,FALSE)) -> 1700 | J93: =IF(A93="","",VLOOKUP(A93,'Cotizador Compras'!$A$5:$J$21,7,FALSE)) -> 1000 | K93: =IF(OR(A93="",E93=""),"",(G93+H93+I93+J93)*E93) -> 757200 | L93: =IF(A93="","",IF(D93="Sin estampar",VLOOKUP(A93,'Cotizador Compras'!$A$5:$J$21,8,FALSE),IF(D93="Pecho",VLOOKUP(A93,'Cotizador Compras'!$A$5:$J$21,10,FALSE),VLOOKUP(A93,'Cotizador Compras'!$A$5:$J$21,9,FALSE)))) -> 230000 | M93: =IF(OR(A93="",E93=""),"",L93*E93) -> 1380000 | N93: =+G93+H93+I93+J93 -> 126200 | O93: =IF(L93>0,(L93-N93)/L93,0) -> 0.45130435 | P93: =CONCATENATE(A93," ",B93," ",C93) -> Hoodie L Acid Wash Gris | Q93: Chaqueta Cortavientos L Verde Botella | R93: =SUMIF($P$26:$P$159,Q93,$E$26:$E$159) -> 4 | T93: =E93*G93 -> 720000 | X93: =ROUNDUP(L93*0.95,-3)*3 -> 657000 | Y93: =IF(X93>0,(X93-N93*3)/X93,0) -> 0.42374429 | AA93: =+ROUNDUP(L93*0.925,-3)*6 -> 1278000 | AB93: =IF(AA93>0,(AA93-N93*6)/AA93,0) -> 0.40751174 | AC93: =+E93*AD93/12 -> 1242000 | AD93: =+ROUNDUP(L93*0.9,-3)*12 -> 2484000 | AE93: =IF(AD93>0,(AD93-N93*12)/AD93,0) -> 0.39033816
A94: Chompa Capucha | B94: S | C94: Negro | D94: Sin estampar | E94: 1 | F94: =IF(A94="","",VLOOKUP(A94,'Cotizador Compras'!$A$5:$J$21,2,FALSE)) -> YOUR BRAND | G94: =IF(A94="","",VLOOKUP(A94,'Cotizador Compras'!$A$5:$J$21,3,FALSE)) -> 90000 | H94: =IF(OR(A94="",D94=""),"",IF(D94="Sin estampar",0,IF(D94="Pecho",VLOOKUP(A94,'Cotizador Compras'!$A$5:$J$21,4,FALSE),IF(D94="Espalda",VLOOKUP(A94,'Cotizador Compras'!$A$5:$J$21,5,FALSE),VLOOKUP(A94,'Cotizador Compras'!$A$5:$J$21,4,FALSE)+VLOOKUP(A94,'Cotizador Compras'!$A$5:$J$21,5,FALSE))))) -> 0 | I94: =IF(A94="","",VLOOKUP(A94,'Cotizador Compras'!$A$5:$J$21,6,FALSE)) -> 1700 | J94: =IF(A94="","",VLOOKUP(A94,'Cotizador Compras'!$A$5:$J$21,7,FALSE)) -> 1000 | K94: =IF(OR(A94="",E94=""),"",(G94+H94+I94+J94)*E94) -> 92700 | L94: =IF(A94="","",IF(D94="Sin estampar",VLOOKUP(A94,'Cotizador Compras'!$A$5:$J$21,8,FALSE),IF(D94="Pecho",VLOOKUP(A94,'Cotizador Compras'!$A$5:$J$21,10,FALSE),VLOOKUP(A94,'Cotizador Compras'!$A$5:$J$21,9,FALSE)))) -> 200000 | M94: =IF(OR(A94="",E94=""),"",L94*E94) -> 200000 | N94: =+G94+H94+I94+J94 -> 92700 | O94: =IF(L94>0,(L94-N94)/L94,0) -> 0.5365 | P94: =CONCATENATE(A94," ",B94," ",C94) -> Chompa Capucha S Negro | Q94: Chaqueta Cortavientos XL Verde Botella | R94: =SUMIF($P$26:$P$159,Q94,$E$26:$E$159) -> 4 | T94: =E94*G94 -> 90000 | X94: =ROUNDUP(L94*0.95,-3)*3 -> 570000 | Y94: =IF(X94>0,(X94-N94*3)/X94,0) -> 0.51210526 | AA94: =+ROUNDUP(L94*0.925,-3)*6 -> 1110000 | AB94: =IF(AA94>0,(AA94-N94*6)/AA94,0) -> 0.49891892 | AC94: =+E94*AD94/12 -> 180000 | AD94: =+ROUNDUP(L94*0.9,-3)*12 -> 2160000 | AE94: =IF(AD94>0,(AD94-N94*12)/AD94,0) -> 0.485
A95: Chompa Capucha | B95: M | C95: Negro | D95: Sin estampar | E95: 6 | F95: =IF(A95="","",VLOOKUP(A95,'Cotizador Compras'!$A$5:$J$21,2,FALSE)) -> YOUR BRAND | G95: =IF(A95="","",VLOOKUP(A95,'Cotizador Compras'!$A$5:$J$21,3,FALSE)) -> 90000 | H95: =IF(OR(A95="",D95=""),"",IF(D95="Sin estampar",0,IF(D95="Pecho",VLOOKUP(A95,'Cotizador Compras'!$A$5:$J$21,4,FALSE),IF(D95="Espalda",VLOOKUP(A95,'Cotizador Compras'!$A$5:$J$21,5,FALSE),VLOOKUP(A95,'Cotizador Compras'!$A$5:$J$21,4,FALSE)+VLOOKUP(A95,'Cotizador Compras'!$A$5:$J$21,5,FALSE))))) -> 0 | I95: =IF(A95="","",VLOOKUP(A95,'Cotizador Compras'!$A$5:$J$21,6,FALSE)) -> 1700 | J95: =IF(A95="","",VLOOKUP(A95,'Cotizador Compras'!$A$5:$J$21,7,FALSE)) -> 1000 | K95: =IF(OR(A95="",E95=""),"",(G95+H95+I95+J95)*E95) -> 556200 | L95: =IF(A95="","",IF(D95="Sin estampar",VLOOKUP(A95,'Cotizador Compras'!$A$5:$J$21,8,FALSE),IF(D95="Pecho",VLOOKUP(A95,'Cotizador Compras'!$A$5:$J$21,10,FALSE),VLOOKUP(A95,'Cotizador Compras'!$A$5:$J$21,9,FALSE)))) -> 200000 | M95: =IF(OR(A95="",E95=""),"",L95*E95) -> 1200000 | N95: =+G95+H95+I95+J95 -> 92700 | O95: =IF(L95>0,(L95-N95)/L95,0) -> 0.5365 | P95: =CONCATENATE(A95," ",B95," ",C95) -> Chompa Capucha M Negro | Q95: Sudadera Bota Recta M Negro | R95: =SUMIF($P$26:$P$159,Q95,$E$26:$E$159) -> 2 | T95: =E95*G95 -> 540000 | X95: =ROUNDUP(L95*0.95,-3)*3 -> 570000 | Y95: =IF(X95>0,(X95-N95*3)/X95,0) -> 0.51210526 | AA95: =+ROUNDUP(L95*0.925,-3)*6 -> 1110000 | AB95: =IF(AA95>0,(AA95-N95*6)/AA95,0) -> 0.49891892 | AC95: =+E95*AD95/12 -> 1080000 | AD95: =+ROUNDUP(L95*0.9,-3)*12 -> 2160000 | AE95: =IF(AD95>0,(AD95-N95*12)/AD95,0) -> 0.485
A96: Chompa Capucha | B96: L | C96: Negro | D96: Sin estampar | E96: 6 | F96: =IF(A96="","",VLOOKUP(A96,'Cotizador Compras'!$A$5:$J$21,2,FALSE)) -> YOUR BRAND | G96: =IF(A96="","",VLOOKUP(A96,'Cotizador Compras'!$A$5:$J$21,3,FALSE)) -> 90000 | H96: =IF(OR(A96="",D96=""),"",IF(D96="Sin estampar",0,IF(D96="Pecho",VLOOKUP(A96,'Cotizador Compras'!$A$5:$J$21,4,FALSE),IF(D96="Espalda",VLOOKUP(A96,'Cotizador Compras'!$A$5:$J$21,5,FALSE),VLOOKUP(A96,'Cotizador Compras'!$A$5:$J$21,4,FALSE)+VLOOKUP(A96,'Cotizador Compras'!$A$5:$J$21,5,FALSE))))) -> 0 | I96: =IF(A96="","",VLOOKUP(A96,'Cotizador Compras'!$A$5:$J$21,6,FALSE)) -> 1700 | J96: =IF(A96="","",VLOOKUP(A96,'Cotizador Compras'!$A$5:$J$21,7,FALSE)) -> 1000 | K96: =IF(OR(A96="",E96=""),"",(G96+H96+I96+J96)*E96) -> 556200 | L96: =IF(A96="","",IF(D96="Sin estampar",VLOOKUP(A96,'Cotizador Compras'!$A$5:$J$21,8,FALSE),IF(D96="Pecho",VLOOKUP(A96,'Cotizador Compras'!$A$5:$J$21,10,FALSE),VLOOKUP(A96,'Cotizador Compras'!$A$5:$J$21,9,FALSE)))) -> 200000 | M96: =IF(OR(A96="",E96=""),"",L96*E96) -> 1200000 | N96: =+G96+H96+I96+J96 -> 92700 | O96: =IF(L96>0,(L96-N96)/L96,0) -> 0.5365 | P96: =CONCATENATE(A96," ",B96," ",C96) -> Chompa Capucha L Negro | Q96: Sudadera Bota Recta L Negro | R96: =SUMIF($P$26:$P$159,Q96,$E$26:$E$159) -> 2 | T96: =E96*G96 -> 540000 | X96: =ROUNDUP(L96*0.95,-3)*3 -> 570000 | Y96: =IF(X96>0,(X96-N96*3)/X96,0) -> 0.51210526 | AA96: =+ROUNDUP(L96*0.925,-3)*6 -> 1110000 | AB96: =IF(AA96>0,(AA96-N96*6)/AA96,0) -> 0.49891892 | AC96: =+E96*AD96/12 -> 1080000 | AD96: =+ROUNDUP(L96*0.9,-3)*12 -> 2160000 | AE96: =IF(AD96>0,(AD96-N96*12)/AD96,0) -> 0.485
A97: Chompa Capucha | B97: S | C97: Perla | D97: Sin estampar | E97: 1 | F97: =IF(A97="","",VLOOKUP(A97,'Cotizador Compras'!$A$5:$J$21,2,FALSE)) -> YOUR BRAND | G97: =IF(A97="","",VLOOKUP(A97,'Cotizador Compras'!$A$5:$J$21,3,FALSE)) -> 90000 | H97: =IF(OR(A97="",D97=""),"",IF(D97="Sin estampar",0,IF(D97="Pecho",VLOOKUP(A97,'Cotizador Compras'!$A$5:$J$21,4,FALSE),IF(D97="Espalda",VLOOKUP(A97,'Cotizador Compras'!$A$5:$J$21,5,FALSE),VLOOKUP(A97,'Cotizador Compras'!$A$5:$J$21,4,FALSE)+VLOOKUP(A97,'Cotizador Compras'!$A$5:$J$21,5,FALSE))))) -> 0 | I97: =IF(A97="","",VLOOKUP(A97,'Cotizador Compras'!$A$5:$J$21,6,FALSE)) -> 1700 | J97: =IF(A97="","",VLOOKUP(A97,'Cotizador Compras'!$A$5:$J$21,7,FALSE)) -> 1000 | K97: =IF(OR(A97="",E97=""),"",(G97+H97+I97+J97)*E97) -> 92700 | L97: =IF(A97="","",IF(D97="Sin estampar",VLOOKUP(A97,'Cotizador Compras'!$A$5:$J$21,8,FALSE),IF(D97="Pecho",VLOOKUP(A97,'Cotizador Compras'!$A$5:$J$21,10,FALSE),VLOOKUP(A97,'Cotizador Compras'!$A$5:$J$21,9,FALSE)))) -> 200000 | M97: =IF(OR(A97="",E97=""),"",L97*E97) -> 200000 | N97: =+G97+H97+I97+J97 -> 92700 | O97: =IF(L97>0,(L97-N97)/L97,0) -> 0.5365 | P97: =CONCATENATE(A97," ",B97," ",C97) -> Chompa Capucha S Perla | Q97: Sudadera Bota Recta XL Negro | R97: =SUMIF($P$26:$P$159,Q97,$E$26:$E$159) -> 2 | T97: =E97*G97 -> 90000 | X97: =ROUNDUP(L97*0.95,-3)*3 -> 570000 | Y97: =IF(X97>0,(X97-N97*3)/X97,0) -> 0.51210526 | AA97: =+ROUNDUP(L97*0.925,-3)*6 -> 1110000 | AB97: =IF(AA97>0,(AA97-N97*6)/AA97,0) -> 0.49891892 | AC97: =+E97*AD97/12 -> 180000 | AD97: =+ROUNDUP(L97*0.9,-3)*12 -> 2160000 | AE97: =IF(AD97>0,(AD97-N97*12)/AD97,0) -> 0.485
A98: Chompa Capucha | B98: M | C98: Perla | D98: Sin estampar | E98: 2 | F98: =IF(A98="","",VLOOKUP(A98,'Cotizador Compras'!$A$5:$J$21,2,FALSE)) -> YOUR BRAND | G98: =IF(A98="","",VLOOKUP(A98,'Cotizador Compras'!$A$5:$J$21,3,FALSE)) -> 90000 | H98: =IF(OR(A98="",D98=""),"",IF(D98="Sin estampar",0,IF(D98="Pecho",VLOOKUP(A98,'Cotizador Compras'!$A$5:$J$21,4,FALSE),IF(D98="Espalda",VLOOKUP(A98,'Cotizador Compras'!$A$5:$J$21,5,FALSE),VLOOKUP(A98,'Cotizador Compras'!$A$5:$J$21,4,FALSE)+VLOOKUP(A98,'Cotizador Compras'!$A$5:$J$21,5,FALSE))))) -> 0 | I98: =IF(A98="","",VLOOKUP(A98,'Cotizador Compras'!$A$5:$J$21,6,FALSE)) -> 1700 | J98: =IF(A98="","",VLOOKUP(A98,'Cotizador Compras'!$A$5:$J$21,7,FALSE)) -> 1000 | K98: =IF(OR(A98="",E98=""),"",(G98+H98+I98+J98)*E98) -> 185400 | L98: =IF(A98="","",IF(D98="Sin estampar",VLOOKUP(A98,'Cotizador Compras'!$A$5:$J$21,8,FALSE),IF(D98="Pecho",VLOOKUP(A98,'Cotizador Compras'!$A$5:$J$21,10,FALSE),VLOOKUP(A98,'Cotizador Compras'!$A$5:$J$21,9,FALSE)))) -> 200000 | M98: =IF(OR(A98="",E98=""),"",L98*E98) -> 400000 | N98: =+G98+H98+I98+J98 -> 92700 | O98: =IF(L98>0,(L98-N98)/L98,0) -> 0.5365 | P98: =CONCATENATE(A98," ",B98," ",C98) -> Chompa Capucha M Perla | Q98: Sudadera Bota Recta M Beige | R98: =SUMIF($P$26:$P$159,Q98,$E$26:$E$159) -> 2 | T98: =E98*G98 -> 180000 | X98: =ROUNDUP(L98*0.95,-3)*3 -> 570000 | Y98: =IF(X98>0,(X98-N98*3)/X98,0) -> 0.51210526 | AA98: =+ROUNDUP(L98*0.925,-3)*6 -> 1110000 | AB98: =IF(AA98>0,(AA98-N98*6)/AA98,0) -> 0.49891892 | AC98: =+E98*AD98/12 -> 360000 | AD98: =+ROUNDUP(L98*0.9,-3)*12 -> 2160000 | AE98: =IF(AD98>0,(AD98-N98*12)/AD98,0) -> 0.485
A99: Chompa Capucha | B99: L | C99: Perla | D99: Sin estampar | E99: 2 | F99: =IF(A99="","",VLOOKUP(A99,'Cotizador Compras'!$A$5:$J$21,2,FALSE)) -> YOUR BRAND | G99: =IF(A99="","",VLOOKUP(A99,'Cotizador Compras'!$A$5:$J$21,3,FALSE)) -> 90000 | H99: =IF(OR(A99="",D99=""),"",IF(D99="Sin estampar",0,IF(D99="Pecho",VLOOKUP(A99,'Cotizador Compras'!$A$5:$J$21,4,FALSE),IF(D99="Espalda",VLOOKUP(A99,'Cotizador Compras'!$A$5:$J$21,5,FALSE),VLOOKUP(A99,'Cotizador Compras'!$A$5:$J$21,4,FALSE)+VLOOKUP(A99,'Cotizador Compras'!$A$5:$J$21,5,FALSE))))) -> 0 | I99: =IF(A99="","",VLOOKUP(A99,'Cotizador Compras'!$A$5:$J$21,6,FALSE)) -> 1700 | J99: =IF(A99="","",VLOOKUP(A99,'Cotizador Compras'!$A$5:$J$21,7,FALSE)) -> 1000 | K99: =IF(OR(A99="",E99=""),"",(G99+H99+I99+J99)*E99) -> 185400 | L99: =IF(A99="","",IF(D99="Sin estampar",VLOOKUP(A99,'Cotizador Compras'!$A$5:$J$21,8,FALSE),IF(D99="Pecho",VLOOKUP(A99,'Cotizador Compras'!$A$5:$J$21,10,FALSE),VLOOKUP(A99,'Cotizador Compras'!$A$5:$J$21,9,FALSE)))) -> 200000 | M99: =IF(OR(A99="",E99=""),"",L99*E99) -> 400000 | N99: =+G99+H99+I99+J99 -> 92700 | O99: =IF(L99>0,(L99-N99)/L99,0) -> 0.5365 | P99: =CONCATENATE(A99," ",B99," ",C99) -> Chompa Capucha L Perla | Q99: Sudadera Bota Recta L Beige | R99: =SUMIF($P$26:$P$159,Q99,$E$26:$E$159) -> 2 | T99: =E99*G99 -> 180000 | X99: =ROUNDUP(L99*0.95,-3)*3 -> 570000 | Y99: =IF(X99>0,(X99-N99*3)/X99,0) -> 0.51210526 | AA99: =+ROUNDUP(L99*0.925,-3)*6 -> 1110000 | AB99: =IF(AA99>0,(AA99-N99*6)/AA99,0) -> 0.49891892 | AC99: =+E99*AD99/12 -> 360000 | AD99: =+ROUNDUP(L99*0.9,-3)*12 -> 2160000 | AE99: =IF(AD99>0,(AD99-N99*12)/AD99,0) -> 0.485
A100: Chompa Capucha | B100: S | C100: Verde Botella | D100: Sin estampar | E100: 1 | F100: =IF(A100="","",VLOOKUP(A100,'Cotizador Compras'!$A$5:$J$21,2,FALSE)) -> YOUR BRAND | G100: =IF(A100="","",VLOOKUP(A100,'Cotizador Compras'!$A$5:$J$21,3,FALSE)) -> 90000 | H100: =IF(OR(A100="",D100=""),"",IF(D100="Sin estampar",0,IF(D100="Pecho",VLOOKUP(A100,'Cotizador Compras'!$A$5:$J$21,4,FALSE),IF(D100="Espalda",VLOOKUP(A100,'Cotizador Compras'!$A$5:$J$21,5,FALSE),VLOOKUP(A100,'Cotizador Compras'!$A$5:$J$21,4,FALSE)+VLOOKUP(A100,'Cotizador Compras'!$A$5:$J$21,5,FALSE))))) -> 0 | I100: =IF(A100="","",VLOOKUP(A100,'Cotizador Compras'!$A$5:$J$21,6,FALSE)) -> 1700 | J100: =IF(A100="","",VLOOKUP(A100,'Cotizador Compras'!$A$5:$J$21,7,FALSE)) -> 1000 | K100: =IF(OR(A100="",E100=""),"",(G100+H100+I100+J100)*E100) -> 92700 | L100: =IF(A100="","",IF(D100="Sin estampar",VLOOKUP(A100,'Cotizador Compras'!$A$5:$J$21,8,FALSE),IF(D100="Pecho",VLOOKUP(A100,'Cotizador Compras'!$A$5:$J$21,10,FALSE),VLOOKUP(A100,'Cotizador Compras'!$A$5:$J$21,9,FALSE)))) -> 200000 | M100: =IF(OR(A100="",E100=""),"",L100*E100) -> 200000 | N100: =+G100+H100+I100+J100 -> 92700 | O100: =IF(L100>0,(L100-N100)/L100,0) -> 0.5365 | P100: =CONCATENATE(A100," ",B100," ",C100) -> Chompa Capucha S Verde Botella | Q100: Sudadera Bota Recta XL Beige | R100: =SUMIF($P$26:$P$159,Q100,$E$26:$E$159) -> 2 | T100: =E100*G100 -> 90000 | X100: =ROUNDUP(L100*0.95,-3)*3 -> 570000 | Y100: =IF(X100>0,(X100-N100*3)/X100,0) -> 0.51210526 | AA100: =+ROUNDUP(L100*0.925,-3)*6 -> 1110000 | AB100: =IF(AA100>0,(AA100-N100*6)/AA100,0) -> 0.49891892 | AC100: =+E100*AD100/12 -> 180000 | AD100: =+ROUNDUP(L100*0.9,-3)*12 -> 2160000 | AE100: =IF(AD100>0,(AD100-N100*12)/AD100,0) -> 0.485
A101: Chompa Capucha | B101: M | C101: Verde Botella | D101: Sin estampar | E101: 2 | F101: =IF(A101="","",VLOOKUP(A101,'Cotizador Compras'!$A$5:$J$21,2,FALSE)) -> YOUR BRAND | G101: =IF(A101="","",VLOOKUP(A101,'Cotizador Compras'!$A$5:$J$21,3,FALSE)) -> 90000 | H101: =IF(OR(A101="",D101=""),"",IF(D101="Sin estampar",0,IF(D101="Pecho",VLOOKUP(A101,'Cotizador Compras'!$A$5:$J$21,4,FALSE),IF(D101="Espalda",VLOOKUP(A101,'Cotizador Compras'!$A$5:$J$21,5,FALSE),VLOOKUP(A101,'Cotizador Compras'!$A$5:$J$21,4,FALSE)+VLOOKUP(A101,'Cotizador Compras'!$A$5:$J$21,5,FALSE))))) -> 0 | I101: =IF(A101="","",VLOOKUP(A101,'Cotizador Compras'!$A$5:$J$21,6,FALSE)) -> 1700 | J101: =IF(A101="","",VLOOKUP(A101,'Cotizador Compras'!$A$5:$J$21,7,FALSE)) -> 1000 | K101: =IF(OR(A101="",E101=""),"",(G101+H101+I101+J101)*E101) -> 185400 | L101: =IF(A101="","",IF(D101="Sin estampar",VLOOKUP(A101,'Cotizador Compras'!$A$5:$J$21,8,FALSE),IF(D101="Pecho",VLOOKUP(A101,'Cotizador Compras'!$A$5:$J$21,10,FALSE),VLOOKUP(A101,'Cotizador Compras'!$A$5:$J$21,9,FALSE)))) -> 200000 | M101: =IF(OR(A101="",E101=""),"",L101*E101) -> 400000 | N101: =+G101+H101+I101+J101 -> 92700 | O101: =IF(L101>0,(L101-N101)/L101,0) -> 0.5365 | P101: =CONCATENATE(A101," ",B101," ",C101) -> Chompa Capucha M Verde Botella | Q101: Pantaloneta M Beige | R101: =SUMIF($P$26:$P$159,Q101,$E$26:$E$159) -> 8 | T101: =E101*G101 -> 180000 | X101: =ROUNDUP(L101*0.95,-3)*3 -> 570000 | Y101: =IF(X101>0,(X101-N101*3)/X101,0) -> 0.51210526 | AA101: =+ROUNDUP(L101*0.925,-3)*6 -> 1110000 | AB101: =IF(AA101>0,(AA101-N101*6)/AA101,0) -> 0.49891892 | AC101: =+E101*AD101/12 -> 360000 | AD101: =+ROUNDUP(L101*0.9,-3)*12 -> 2160000 | AE101: =IF(AD101>0,(AD101-N101*12)/AD101,0) -> 0.485
A102: Chompa Capucha | B102: L | C102: Verde Botella | D102: Sin estampar | E102: 2 | F102: =IF(A102="","",VLOOKUP(A102,'Cotizador Compras'!$A$5:$J$21,2,FALSE)) -> YOUR BRAND | G102: =IF(A102="","",VLOOKUP(A102,'Cotizador Compras'!$A$5:$J$21,3,FALSE)) -> 90000 | H102: =IF(OR(A102="",D102=""),"",IF(D102="Sin estampar",0,IF(D102="Pecho",VLOOKUP(A102,'Cotizador Compras'!$A$5:$J$21,4,FALSE),IF(D102="Espalda",VLOOKUP(A102,'Cotizador Compras'!$A$5:$J$21,5,FALSE),VLOOKUP(A102,'Cotizador Compras'!$A$5:$J$21,4,FALSE)+VLOOKUP(A102,'Cotizador Compras'!$A$5:$J$21,5,FALSE))))) -> 0 | I102: =IF(A102="","",VLOOKUP(A102,'Cotizador Compras'!$A$5:$J$21,6,FALSE)) -> 1700 | J102: =IF(A102="","",VLOOKUP(A102,'Cotizador Compras'!$A$5:$J$21,7,FALSE)) -> 1000 | K102: =IF(OR(A102="",E102=""),"",(G102+H102+I102+J102)*E102) -> 185400 | L102: =IF(A102="","",IF(D102="Sin estampar",VLOOKUP(A102,'Cotizador Compras'!$A$5:$J$21,8,FALSE),IF(D102="Pecho",VLOOKUP(A102,'Cotizador Compras'!$A$5:$J$21,10,FALSE),VLOOKUP(A102,'Cotizador Compras'!$A$5:$J$21,9,FALSE)))) -> 200000 | M102: =IF(OR(A102="",E102=""),"",L102*E102) -> 400000 | N102: =+G102+H102+I102+J102 -> 92700 | O102: =IF(L102>0,(L102-N102)/L102,0) -> 0.5365 | P102: =CONCATENATE(A102," ",B102," ",C102) -> Chompa Capucha L Verde Botella | Q102: Pantaloneta L Beige | R102: =SUMIF($P$26:$P$159,Q102,$E$26:$E$159) -> 8 | T102: =E102*G102 -> 180000 | X102: =ROUNDUP(L102*0.95,-3)*3 -> 570000 | Y102: =IF(X102>0,(X102-N102*3)/X102,0) -> 0.51210526 | AA102: =+ROUNDUP(L102*0.925,-3)*6 -> 1110000 | AB102: =IF(AA102>0,(AA102-N102*6)/AA102,0) -> 0.49891892 | AC102: =+E102*AD102/12 -> 360000 | AD102: =+ROUNDUP(L102*0.9,-3)*12 -> 2160000 | AE102: =IF(AD102>0,(AD102-N102*12)/AD102,0) -> 0.485
A103: Chompa Capucha | B103: S | C103: Plomo Plata | D103: Sin estampar | E103: 1 | F103: =IF(A103="","",VLOOKUP(A103,'Cotizador Compras'!$A$5:$J$21,2,FALSE)) -> YOUR BRAND | G103: =IF(A103="","",VLOOKUP(A103,'Cotizador Compras'!$A$5:$J$21,3,FALSE)) -> 90000 | H103: =IF(OR(A103="",D103=""),"",IF(D103="Sin estampar",0,IF(D103="Pecho",VLOOKUP(A103,'Cotizador Compras'!$A$5:$J$21,4,FALSE),IF(D103="Espalda",VLOOKUP(A103,'Cotizador Compras'!$A$5:$J$21,5,FALSE),VLOOKUP(A103,'Cotizador Compras'!$A$5:$J$21,4,FALSE)+VLOOKUP(A103,'Cotizador Compras'!$A$5:$J$21,5,FALSE))))) -> 0 | I103: =IF(A103="","",VLOOKUP(A103,'Cotizador Compras'!$A$5:$J$21,6,FALSE)) -> 1700 | J103: =IF(A103="","",VLOOKUP(A103,'Cotizador Compras'!$A$5:$J$21,7,FALSE)) -> 1000 | K103: =IF(OR(A103="",E103=""),"",(G103+H103+I103+J103)*E103) -> 92700 | L103: =IF(A103="","",IF(D103="Sin estampar",VLOOKUP(A103,'Cotizador Compras'!$A$5:$J$21,8,FALSE),IF(D103="Pecho",VLOOKUP(A103,'Cotizador Compras'!$A$5:$J$21,10,FALSE),VLOOKUP(A103,'Cotizador Compras'!$A$5:$J$21,9,FALSE)))) -> 200000 | M103: =IF(OR(A103="",E103=""),"",L103*E103) -> 200000 | N103: =+G103+H103+I103+J103 -> 92700 | O103: =IF(L103>0,(L103-N103)/L103,0) -> 0.5365 | P103: =CONCATENATE(A103," ",B103," ",C103) -> Chompa Capucha S Plomo Plata | Q103: Pantaloneta XL Beige | R103: =SUMIF($P$26:$P$159,Q103,$E$26:$E$159) -> 8 | T103: =E103*G103 -> 90000 | X103: =ROUNDUP(L103*0.95,-3)*3 -> 570000 | Y103: =IF(X103>0,(X103-N103*3)/X103,0) -> 0.51210526 | AA103: =+ROUNDUP(L103*0.925,-3)*6 -> 1110000 | AB103: =IF(AA103>0,(AA103-N103*6)/AA103,0) -> 0.49891892 | AC103: =+E103*AD103/12 -> 180000 | AD103: =+ROUNDUP(L103*0.9,-3)*12 -> 2160000 | AE103: =IF(AD103>0,(AD103-N103*12)/AD103,0) -> 0.485
A104: Chompa Capucha | B104: M | C104: Plomo Plata | D104: Sin estampar | E104: 2 | F104: =IF(A104="","",VLOOKUP(A104,'Cotizador Compras'!$A$5:$J$21,2,FALSE)) -> YOUR BRAND | G104: =IF(A104="","",VLOOKUP(A104,'Cotizador Compras'!$A$5:$J$21,3,FALSE)) -> 90000 | H104: =IF(OR(A104="",D104=""),"",IF(D104="Sin estampar",0,IF(D104="Pecho",VLOOKUP(A104,'Cotizador Compras'!$A$5:$J$21,4,FALSE),IF(D104="Espalda",VLOOKUP(A104,'Cotizador Compras'!$A$5:$J$21,5,FALSE),VLOOKUP(A104,'Cotizador Compras'!$A$5:$J$21,4,FALSE)+VLOOKUP(A104,'Cotizador Compras'!$A$5:$J$21,5,FALSE))))) -> 0 | I104: =IF(A104="","",VLOOKUP(A104,'Cotizador Compras'!$A$5:$J$21,6,FALSE)) -> 1700 | J104: =IF(A104="","",VLOOKUP(A104,'Cotizador Compras'!$A$5:$J$21,7,FALSE)) -> 1000 | K104: =IF(OR(A104="",E104=""),"",(G104+H104+I104+J104)*E104) -> 185400 | L104: =IF(A104="","",IF(D104="Sin estampar",VLOOKUP(A104,'Cotizador Compras'!$A$5:$J$21,8,FALSE),IF(D104="Pecho",VLOOKUP(A104,'Cotizador Compras'!$A$5:$J$21,10,FALSE),VLOOKUP(A104,'Cotizador Compras'!$A$5:$J$21,9,FALSE)))) -> 200000 | M104: =IF(OR(A104="",E104=""),"",L104*E104) -> 400000 | N104: =+G104+H104+I104+J104 -> 92700 | O104: =IF(L104>0,(L104-N104)/L104,0) -> 0.5365 | P104: =CONCATENATE(A104," ",B104," ",C104) -> Chompa Capucha M Plomo Plata | Q104: Camisa Réplica Y/Out M | R104: =SUMIF($P$26:$P$159,Q104,$E$26:$E$159) -> 3 | T104: =E104*G104 -> 180000 | X104: =ROUNDUP(L104*0.95,-3)*3 -> 570000 | Y104: =IF(X104>0,(X104-N104*3)/X104,0) -> 0.51210526 | AA104: =+ROUNDUP(L104*0.925,-3)*6 -> 1110000 | AB104: =IF(AA104>0,(AA104-N104*6)/AA104,0) -> 0.49891892 | AC104: =+E104*AD104/12 -> 360000 | AD104: =+ROUNDUP(L104*0.9,-3)*12 -> 2160000 | AE104: =IF(AD104>0,(AD104-N104*12)/AD104,0) -> 0.485
A105: Chompa Capucha | B105: L | C105: Plomo Plata | D105: Sin estampar | E105: 2 | F105: =IF(A105="","",VLOOKUP(A105,'Cotizador Compras'!$A$5:$J$21,2,FALSE)) -> YOUR BRAND | G105: =IF(A105="","",VLOOKUP(A105,'Cotizador Compras'!$A$5:$J$21,3,FALSE)) -> 90000 | H105: =IF(OR(A105="",D105=""),"",IF(D105="Sin estampar",0,IF(D105="Pecho",VLOOKUP(A105,'Cotizador Compras'!$A$5:$J$21,4,FALSE),IF(D105="Espalda",VLOOKUP(A105,'Cotizador Compras'!$A$5:$J$21,5,FALSE),VLOOKUP(A105,'Cotizador Compras'!$A$5:$J$21,4,FALSE)+VLOOKUP(A105,'Cotizador Compras'!$A$5:$J$21,5,FALSE))))) -> 0 | I105: =IF(A105="","",VLOOKUP(A105,'Cotizador Compras'!$A$5:$J$21,6,FALSE)) -> 1700 | J105: =IF(A105="","",VLOOKUP(A105,'Cotizador Compras'!$A$5:$J$21,7,FALSE)) -> 1000 | K105: =IF(OR(A105="",E105=""),"",(G105+H105+I105+J105)*E105) -> 185400 | L105: =IF(A105="","",IF(D105="Sin estampar",VLOOKUP(A105,'Cotizador Compras'!$A$5:$J$21,8,FALSE),IF(D105="Pecho",VLOOKUP(A105,'Cotizador Compras'!$A$5:$J$21,10,FALSE),VLOOKUP(A105,'Cotizador Compras'!$A$5:$J$21,9,FALSE)))) -> 200000 | M105: =IF(OR(A105="",E105=""),"",L105*E105) -> 400000 | N105: =+G105+H105+I105+J105 -> 92700 | O105: =IF(L105>0,(L105-N105)/L105,0) -> 0.5365 | P105: =CONCATENATE(A105," ",B105," ",C105) -> Chompa Capucha L Plomo Plata | R105: =SUMIF($P$26:$P$159,Q105,$E$26:$E$159) -> 0 | T105: =E105*G105 -> 180000 | X105: =ROUNDUP(L105*0.95,-3)*3 -> 570000 | Y105: =IF(X105>0,(X105-N105*3)/X105,0) -> 0.51210526 | AA105: =+ROUNDUP(L105*0.925,-3)*6 -> 1110000 | AB105: =IF(AA105>0,(AA105-N105*6)/AA105,0) -> 0.49891892 | AC105: =+E105*AD105/12 -> 360000 | AD105: =+ROUNDUP(L105*0.9,-3)*12 -> 2160000 | AE105: =IF(AD105>0,(AD105-N105*12)/AD105,0) -> 0.485
A106: Chompa Capucha | B106: S | C106: Negro | D106: Pecho | E106: 1 | F106: =IF(A106="","",VLOOKUP(A106,'Cotizador Compras'!$A$5:$J$21,2,FALSE)) -> YOUR BRAND | G106: =IF(A106="","",VLOOKUP(A106,'Cotizador Compras'!$A$5:$J$21,3,FALSE)) -> 90000 | H106: =IF(OR(A106="",D106=""),"",IF(D106="Sin estampar",0,IF(D106="Pecho",VLOOKUP(A106,'Cotizador Compras'!$A$5:$J$21,4,FALSE),IF(D106="Espalda",VLOOKUP(A106,'Cotizador Compras'!$A$5:$J$21,5,FALSE),VLOOKUP(A106,'Cotizador Compras'!$A$5:$J$21,4,FALSE)+VLOOKUP(A106,'Cotizador Compras'!$A$5:$J$21,5,FALSE))))) -> 3500 | I106: =IF(A106="","",VLOOKUP(A106,'Cotizador Compras'!$A$5:$J$21,6,FALSE)) -> 1700 | J106: =IF(A106="","",VLOOKUP(A106,'Cotizador Compras'!$A$5:$J$21,7,FALSE)) -> 1000 | K106: =IF(OR(A106="",E106=""),"",(G106+H106+I106+J106)*E106) -> 96200 | L106: =IF(A106="","",IF(D106="Sin estampar",VLOOKUP(A106,'Cotizador Compras'!$A$5:$J$21,8,FALSE),IF(D106="Pecho",VLOOKUP(A106,'Cotizador Compras'!$A$5:$J$21,10,FALSE),VLOOKUP(A106,'Cotizador Compras'!$A$5:$J$21,9,FALSE)))) -> 230000 | M106: =IF(OR(A106="",E106=""),"",L106*E106) -> 230000 | N106: =+G106+H106+I106+J106 -> 96200 | O106: =IF(L106>0,(L106-N106)/L106,0) -> 0.58173913 | P106: =CONCATENATE(A106," ",B106," ",C106) -> Chompa Capucha S Negro | R106: =SUMIF($P$26:$P$159,Q106,$E$26:$E$159) -> 0 | T106: =E106*G106 -> 90000 | X106: =ROUNDUP(L106*0.95,-3)*3 -> 657000 | Y106: =IF(X106>0,(X106-N106*3)/X106,0) -> 0.56073059 | AA106: =+ROUNDUP(L106*0.925,-3)*6 -> 1278000 | AB106: =IF(AA106>0,(AA106-N106*6)/AA106,0) -> 0.54835681 | AC106: =+E106*AD106/12 -> 207000 | AD106: =+ROUNDUP(L106*0.9,-3)*12 -> 2484000 | AE106: =IF(AD106>0,(AD106-N106*12)/AD106,0) -> 0.5352657
A107: Chompa Capucha | B107: M | C107: Negro | D107: Pecho | E107: 2 | F107: =IF(A107="","",VLOOKUP(A107,'Cotizador Compras'!$A$5:$J$21,2,FALSE)) -> YOUR BRAND | G107: =IF(A107="","",VLOOKUP(A107,'Cotizador Compras'!$A$5:$J$21,3,FALSE)) -> 90000 | H107: =IF(OR(A107="",D107=""),"",IF(D107="Sin estampar",0,IF(D107="Pecho",VLOOKUP(A107,'Cotizador Compras'!$A$5:$J$21,4,FALSE),IF(D107="Espalda",VLOOKUP(A107,'Cotizador Compras'!$A$5:$J$21,5,FALSE),VLOOKUP(A107,'Cotizador Compras'!$A$5:$J$21,4,FALSE)+VLOOKUP(A107,'Cotizador Compras'!$A$5:$J$21,5,FALSE))))) -> 3500 | I107: =IF(A107="","",VLOOKUP(A107,'Cotizador Compras'!$A$5:$J$21,6,FALSE)) -> 1700 | J107: =IF(A107="","",VLOOKUP(A107,'Cotizador Compras'!$A$5:$J$21,7,FALSE)) -> 1000 | K107: =IF(OR(A107="",E107=""),"",(G107+H107+I107+J107)*E107) -> 192400 | L107: =IF(A107="","",IF(D107="Sin estampar",VLOOKUP(A107,'Cotizador Compras'!$A$5:$J$21,8,FALSE),IF(D107="Pecho",VLOOKUP(A107,'Cotizador Compras'!$A$5:$J$21,10,FALSE),VLOOKUP(A107,'Cotizador Compras'!$A$5:$J$21,9,FALSE)))) -> 230000 | M107: =IF(OR(A107="",E107=""),"",L107*E107) -> 460000 | N107: =+G107+H107+I107+J107 -> 96200 | O107: =IF(L107>0,(L107-N107)/L107,0) -> 0.58173913 | P107: =CONCATENATE(A107," ",B107," ",C107) -> Chompa Capucha M Negro | R107: =SUMIF($P$26:$P$159,Q107,$E$26:$E$159) -> 0 | T107: =E107*G107 -> 180000 | X107: =ROUNDUP(L107*0.95,-3)*3 -> 657000 | Y107: =IF(X107>0,(X107-N107*3)/X107,0) -> 0.56073059 | AA107: =+ROUNDUP(L107*0.925,-3)*6 -> 1278000 | AB107: =IF(AA107>0,(AA107-N107*6)/AA107,0) -> 0.54835681 | AC107: =+E107*AD107/12 -> 414000 | AD107: =+ROUNDUP(L107*0.9,-3)*12 -> 2484000 | AE107: =IF(AD107>0,(AD107-N107*12)/AD107,0) -> 0.5352657
A108: Chompa Capucha | B108: L | C108: Negro | D108: Pecho | E108: 2 | F108: =IF(A108="","",VLOOKUP(A108,'Cotizador Compras'!$A$5:$J$21,2,FALSE)) -> YOUR BRAND | G108: =IF(A108="","",VLOOKUP(A108,'Cotizador Compras'!$A$5:$J$21,3,FALSE)) -> 90000 | H108: =IF(OR(A108="",D108=""),"",IF(D108="Sin estampar",0,IF(D108="Pecho",VLOOKUP(A108,'Cotizador Compras'!$A$5:$J$21,4,FALSE),IF(D108="Espalda",VLOOKUP(A108,'Cotizador Compras'!$A$5:$J$21,5,FALSE),VLOOKUP(A108,'Cotizador Compras'!$A$5:$J$21,4,FALSE)+VLOOKUP(A108,'Cotizador Compras'!$A$5:$J$21,5,FALSE))))) -> 3500 | I108: =IF(A108="","",VLOOKUP(A108,'Cotizador Compras'!$A$5:$J$21,6,FALSE)) -> 1700 | J108: =IF(A108="","",VLOOKUP(A108,'Cotizador Compras'!$A$5:$J$21,7,FALSE)) -> 1000 | K108: =IF(OR(A108="",E108=""),"",(G108+H108+I108+J108)*E108) -> 192400 | L108: =IF(A108="","",IF(D108="Sin estampar",VLOOKUP(A108,'Cotizador Compras'!$A$5:$J$21,8,FALSE),IF(D108="Pecho",VLOOKUP(A108,'Cotizador Compras'!$A$5:$J$21,10,FALSE),VLOOKUP(A108,'Cotizador Compras'!$A$5:$J$21,9,FALSE)))) -> 230000 | M108: =IF(OR(A108="",E108=""),"",L108*E108) -> 460000 | N108: =+G108+H108+I108+J108 -> 96200 | O108: =IF(L108>0,(L108-N108)/L108,0) -> 0.58173913 | P108: =CONCATENATE(A108," ",B108," ",C108) -> Chompa Capucha L Negro | R108: =SUMIF($P$26:$P$159,Q108,$E$26:$E$159) -> 0 | T108: =E108*G108 -> 180000 | X108: =ROUNDUP(L108*0.95,-3)*3 -> 657000 | Y108: =IF(X108>0,(X108-N108*3)/X108,0) -> 0.56073059 | AA108: =+ROUNDUP(L108*0.925,-3)*6 -> 1278000 | AB108: =IF(AA108>0,(AA108-N108*6)/AA108,0) -> 0.54835681 | AC108: =+E108*AD108/12 -> 414000 | AD108: =+ROUNDUP(L108*0.9,-3)*12 -> 2484000 | AE108: =IF(AD108>0,(AD108-N108*12)/AD108,0) -> 0.5352657
A109: Chompa Capucha | B109: S | C109: Perla | D109: Pecho | E109: 1 | F109: =IF(A109="","",VLOOKUP(A109,'Cotizador Compras'!$A$5:$J$21,2,FALSE)) -> YOUR BRAND | G109: =IF(A109="","",VLOOKUP(A109,'Cotizador Compras'!$A$5:$J$21,3,FALSE)) -> 90000 | H109: =IF(OR(A109="",D109=""),"",IF(D109="Sin estampar",0,IF(D109="Pecho",VLOOKUP(A109,'Cotizador Compras'!$A$5:$J$21,4,FALSE),IF(D109="Espalda",VLOOKUP(A109,'Cotizador Compras'!$A$5:$J$21,5,FALSE),VLOOKUP(A109,'Cotizador Compras'!$A$5:$J$21,4,FALSE)+VLOOKUP(A109,'Cotizador Compras'!$A$5:$J$21,5,FALSE))))) -> 3500 | I109: =IF(A109="","",VLOOKUP(A109,'Cotizador Compras'!$A$5:$J$21,6,FALSE)) -> 1700 | J109: =IF(A109="","",VLOOKUP(A109,'Cotizador Compras'!$A$5:$J$21,7,FALSE)) -> 1000 | K109: =IF(OR(A109="",E109=""),"",(G109+H109+I109+J109)*E109) -> 96200 | L109: =IF(A109="","",IF(D109="Sin estampar",VLOOKUP(A109,'Cotizador Compras'!$A$5:$J$21,8,FALSE),IF(D109="Pecho",VLOOKUP(A109,'Cotizador Compras'!$A$5:$J$21,10,FALSE),VLOOKUP(A109,'Cotizador Compras'!$A$5:$J$21,9,FALSE)))) -> 230000 | M109: =IF(OR(A109="",E109=""),"",L109*E109) -> 230000 | N109: =+G109+H109+I109+J109 -> 96200 | O109: =IF(L109>0,(L109-N109)/L109,0) -> 0.58173913 | P109: =CONCATENATE(A109," ",B109," ",C109) -> Chompa Capucha S Perla | R109: =SUMIF($P$26:$P$159,Q109,$E$26:$E$159) -> 0 | T109: =E109*G109 -> 90000 | X109: =ROUNDUP(L109*0.95,-3)*3 -> 657000 | Y109: =IF(X109>0,(X109-N109*3)/X109,0) -> 0.56073059 | AA109: =+ROUNDUP(L109*0.925,-3)*6 -> 1278000 | AB109: =IF(AA109>0,(AA109-N109*6)/AA109,0) -> 0.54835681 | AC109: =+E109*AD109/12 -> 207000 | AD109: =+ROUNDUP(L109*0.9,-3)*12 -> 2484000 | AE109: =IF(AD109>0,(AD109-N109*12)/AD109,0) -> 0.5352657
A110: Chompa Capucha | B110: M | C110: Perla | D110: Pecho | E110: 2 | F110: =IF(A110="","",VLOOKUP(A110,'Cotizador Compras'!$A$5:$J$21,2,FALSE)) -> YOUR BRAND | G110: =IF(A110="","",VLOOKUP(A110,'Cotizador Compras'!$A$5:$J$21,3,FALSE)) -> 90000 | H110: =IF(OR(A110="",D110=""),"",IF(D110="Sin estampar",0,IF(D110="Pecho",VLOOKUP(A110,'Cotizador Compras'!$A$5:$J$21,4,FALSE),IF(D110="Espalda",VLOOKUP(A110,'Cotizador Compras'!$A$5:$J$21,5,FALSE),VLOOKUP(A110,'Cotizador Compras'!$A$5:$J$21,4,FALSE)+VLOOKUP(A110,'Cotizador Compras'!$A$5:$J$21,5,FALSE))))) -> 3500 | I110: =IF(A110="","",VLOOKUP(A110,'Cotizador Compras'!$A$5:$J$21,6,FALSE)) -> 1700 | J110: =IF(A110="","",VLOOKUP(A110,'Cotizador Compras'!$A$5:$J$21,7,FALSE)) -> 1000 | K110: =IF(OR(A110="",E110=""),"",(G110+H110+I110+J110)*E110) -> 192400 | L110: =IF(A110="","",IF(D110="Sin estampar",VLOOKUP(A110,'Cotizador Compras'!$A$5:$J$21,8,FALSE),IF(D110="Pecho",VLOOKUP(A110,'Cotizador Compras'!$A$5:$J$21,10,FALSE),VLOOKUP(A110,'Cotizador Compras'!$A$5:$J$21,9,FALSE)))) -> 230000 | M110: =IF(OR(A110="",E110=""),"",L110*E110) -> 460000 | N110: =+G110+H110+I110+J110 -> 96200 | O110: =IF(L110>0,(L110-N110)/L110,0) -> 0.58173913 | P110: =CONCATENATE(A110," ",B110," ",C110) -> Chompa Capucha M Perla | R110: =SUMIF($P$26:$P$159,Q110,$E$26:$E$159) -> 0 | T110: =E110*G110 -> 180000 | X110: =ROUNDUP(L110*0.95,-3)*3 -> 657000 | Y110: =IF(X110>0,(X110-N110*3)/X110,0) -> 0.56073059 | AA110: =+ROUNDUP(L110*0.925,-3)*6 -> 1278000 | AB110: =IF(AA110>0,(AA110-N110*6)/AA110,0) -> 0.54835681 | AC110: =+E110*AD110/12 -> 414000 | AD110: =+ROUNDUP(L110*0.9,-3)*12 -> 2484000 | AE110: =IF(AD110>0,(AD110-N110*12)/AD110,0) -> 0.5352657
A111: Chompa Capucha | B111: L | C111: Perla | D111: Pecho | E111: 2 | F111: =IF(A111="","",VLOOKUP(A111,'Cotizador Compras'!$A$5:$J$21,2,FALSE)) -> YOUR BRAND | G111: =IF(A111="","",VLOOKUP(A111,'Cotizador Compras'!$A$5:$J$21,3,FALSE)) -> 90000 | H111: =IF(OR(A111="",D111=""),"",IF(D111="Sin estampar",0,IF(D111="Pecho",VLOOKUP(A111,'Cotizador Compras'!$A$5:$J$21,4,FALSE),IF(D111="Espalda",VLOOKUP(A111,'Cotizador Compras'!$A$5:$J$21,5,FALSE),VLOOKUP(A111,'Cotizador Compras'!$A$5:$J$21,4,FALSE)+VLOOKUP(A111,'Cotizador Compras'!$A$5:$J$21,5,FALSE))))) -> 3500 | I111: =IF(A111="","",VLOOKUP(A111,'Cotizador Compras'!$A$5:$J$21,6,FALSE)) -> 1700 | J111: =IF(A111="","",VLOOKUP(A111,'Cotizador Compras'!$A$5:$J$21,7,FALSE)) -> 1000 | K111: =IF(OR(A111="",E111=""),"",(G111+H111+I111+J111)*E111) -> 192400 | L111: =IF(A111="","",IF(D111="Sin estampar",VLOOKUP(A111,'Cotizador Compras'!$A$5:$J$21,8,FALSE),IF(D111="Pecho",VLOOKUP(A111,'Cotizador Compras'!$A$5:$J$21,10,FALSE),VLOOKUP(A111,'Cotizador Compras'!$A$5:$J$21,9,FALSE)))) -> 230000 | M111: =IF(OR(A111="",E111=""),"",L111*E111) -> 460000 | N111: =+G111+H111+I111+J111 -> 96200 | O111: =IF(L111>0,(L111-N111)/L111,0) -> 0.58173913 | P111: =CONCATENATE(A111," ",B111," ",C111) -> Chompa Capucha L Perla | R111: =SUMIF($P$26:$P$159,Q111,$E$26:$E$159) -> 0 | T111: =E111*G111 -> 180000 | X111: =ROUNDUP(L111*0.95,-3)*3 -> 657000 | Y111: =IF(X111>0,(X111-N111*3)/X111,0) -> 0.56073059 | AA111: =+ROUNDUP(L111*0.925,-3)*6 -> 1278000 | AB111: =IF(AA111>0,(AA111-N111*6)/AA111,0) -> 0.54835681 | AC111: =+E111*AD111/12 -> 414000 | AD111: =+ROUNDUP(L111*0.9,-3)*12 -> 2484000 | AE111: =IF(AD111>0,(AD111-N111*12)/AD111,0) -> 0.5352657
A112: Chompa Capucha | B112: S | C112: Verde Botella | D112: Pecho | E112: 1 | F112: =IF(A112="","",VLOOKUP(A112,'Cotizador Compras'!$A$5:$J$21,2,FALSE)) -> YOUR BRAND | G112: =IF(A112="","",VLOOKUP(A112,'Cotizador Compras'!$A$5:$J$21,3,FALSE)) -> 90000 | H112: =IF(OR(A112="",D112=""),"",IF(D112="Sin estampar",0,IF(D112="Pecho",VLOOKUP(A112,'Cotizador Compras'!$A$5:$J$21,4,FALSE),IF(D112="Espalda",VLOOKUP(A112,'Cotizador Compras'!$A$5:$J$21,5,FALSE),VLOOKUP(A112,'Cotizador Compras'!$A$5:$J$21,4,FALSE)+VLOOKUP(A112,'Cotizador Compras'!$A$5:$J$21,5,FALSE))))) -> 3500 | I112: =IF(A112="","",VLOOKUP(A112,'Cotizador Compras'!$A$5:$J$21,6,FALSE)) -> 1700 | J112: =IF(A112="","",VLOOKUP(A112,'Cotizador Compras'!$A$5:$J$21,7,FALSE)) -> 1000 | K112: =IF(OR(A112="",E112=""),"",(G112+H112+I112+J112)*E112) -> 96200 | L112: =IF(A112="","",IF(D112="Sin estampar",VLOOKUP(A112,'Cotizador Compras'!$A$5:$J$21,8,FALSE),IF(D112="Pecho",VLOOKUP(A112,'Cotizador Compras'!$A$5:$J$21,10,FALSE),VLOOKUP(A112,'Cotizador Compras'!$A$5:$J$21,9,FALSE)))) -> 230000 | M112: =IF(OR(A112="",E112=""),"",L112*E112) -> 230000 | N112: =+G112+H112+I112+J112 -> 96200 | O112: =IF(L112>0,(L112-N112)/L112,0) -> 0.58173913 | P112: =CONCATENATE(A112," ",B112," ",C112) -> Chompa Capucha S Verde Botella | R112: =SUMIF($P$26:$P$159,Q112,$E$26:$E$159) -> 0 | T112: =E112*G112 -> 90000 | X112: =ROUNDUP(L112*0.95,-3)*3 -> 657000 | Y112: =IF(X112>0,(X112-N112*3)/X112,0) -> 0.56073059 | AA112: =+ROUNDUP(L112*0.925,-3)*6 -> 1278000 | AB112: =IF(AA112>0,(AA112-N112*6)/AA112,0) -> 0.54835681 | AC112: =+E112*AD112/12 -> 207000 | AD112: =+ROUNDUP(L112*0.9,-3)*12 -> 2484000 | AE112: =IF(AD112>0,(AD112-N112*12)/AD112,0) -> 0.5352657
A113: Chompa Capucha | B113: M | C113: Verde Botella | D113: Pecho | E113: 2 | F113: =IF(A113="","",VLOOKUP(A113,'Cotizador Compras'!$A$5:$J$21,2,FALSE)) -> YOUR BRAND | G113: =IF(A113="","",VLOOKUP(A113,'Cotizador Compras'!$A$5:$J$21,3,FALSE)) -> 90000 | H113: =IF(OR(A113="",D113=""),"",IF(D113="Sin estampar",0,IF(D113="Pecho",VLOOKUP(A113,'Cotizador Compras'!$A$5:$J$21,4,FALSE),IF(D113="Espalda",VLOOKUP(A113,'Cotizador Compras'!$A$5:$J$21,5,FALSE),VLOOKUP(A113,'Cotizador Compras'!$A$5:$J$21,4,FALSE)+VLOOKUP(A113,'Cotizador Compras'!$A$5:$J$21,5,FALSE))))) -> 3500 | I113: =IF(A113="","",VLOOKUP(A113,'Cotizador Compras'!$A$5:$J$21,6,FALSE)) -> 1700 | J113: =IF(A113="","",VLOOKUP(A113,'Cotizador Compras'!$A$5:$J$21,7,FALSE)) -> 1000 | K113: =IF(OR(A113="",E113=""),"",(G113+H113+I113+J113)*E113) -> 192400 | L113: =IF(A113="","",IF(D113="Sin estampar",VLOOKUP(A113,'Cotizador Compras'!$A$5:$J$21,8,FALSE),IF(D113="Pecho",VLOOKUP(A113,'Cotizador Compras'!$A$5:$J$21,10,FALSE),VLOOKUP(A113,'Cotizador Compras'!$A$5:$J$21,9,FALSE)))) -> 230000 | M113: =IF(OR(A113="",E113=""),"",L113*E113) -> 460000 | N113: =+G113+H113+I113+J113 -> 96200 | O113: =IF(L113>0,(L113-N113)/L113,0) -> 0.58173913 | P113: =CONCATENATE(A113," ",B113," ",C113) -> Chompa Capucha M Verde Botella | R113: =SUMIF($P$26:$P$159,Q113,$E$26:$E$159) -> 0 | T113: =E113*G113 -> 180000 | X113: =ROUNDUP(L113*0.95,-3)*3 -> 657000 | Y113: =IF(X113>0,(X113-N113*3)/X113,0) -> 0.56073059 | AA113: =+ROUNDUP(L113*0.925,-3)*6 -> 1278000 | AB113: =IF(AA113>0,(AA113-N113*6)/AA113,0) -> 0.54835681 | AC113: =+E113*AD113/12 -> 414000 | AD113: =+ROUNDUP(L113*0.9,-3)*12 -> 2484000 | AE113: =IF(AD113>0,(AD113-N113*12)/AD113,0) -> 0.5352657
A114: Chompa Capucha | B114: L | C114: Verde Botella | D114: Pecho | E114: 2 | F114: =IF(A114="","",VLOOKUP(A114,'Cotizador Compras'!$A$5:$J$21,2,FALSE)) -> YOUR BRAND | G114: =IF(A114="","",VLOOKUP(A114,'Cotizador Compras'!$A$5:$J$21,3,FALSE)) -> 90000 | H114: =IF(OR(A114="",D114=""),"",IF(D114="Sin estampar",0,IF(D114="Pecho",VLOOKUP(A114,'Cotizador Compras'!$A$5:$J$21,4,FALSE),IF(D114="Espalda",VLOOKUP(A114,'Cotizador Compras'!$A$5:$J$21,5,FALSE),VLOOKUP(A114,'Cotizador Compras'!$A$5:$J$21,4,FALSE)+VLOOKUP(A114,'Cotizador Compras'!$A$5:$J$21,5,FALSE))))) -> 3500 | I114: =IF(A114="","",VLOOKUP(A114,'Cotizador Compras'!$A$5:$J$21,6,FALSE)) -> 1700 | J114: =IF(A114="","",VLOOKUP(A114,'Cotizador Compras'!$A$5:$J$21,7,FALSE)) -> 1000 | K114: =IF(OR(A114="",E114=""),"",(G114+H114+I114+J114)*E114) -> 192400 | L114: =IF(A114="","",IF(D114="Sin estampar",VLOOKUP(A114,'Cotizador Compras'!$A$5:$J$21,8,FALSE),IF(D114="Pecho",VLOOKUP(A114,'Cotizador Compras'!$A$5:$J$21,10,FALSE),VLOOKUP(A114,'Cotizador Compras'!$A$5:$J$21,9,FALSE)))) -> 230000 | M114: =IF(OR(A114="",E114=""),"",L114*E114) -> 460000 | N114: =+G114+H114+I114+J114 -> 96200 | O114: =IF(L114>0,(L114-N114)/L114,0) -> 0.58173913 | P114: =CONCATENATE(A114," ",B114," ",C114) -> Chompa Capucha L Verde Botella | R114: =SUMIF($P$26:$P$159,Q114,$E$26:$E$159) -> 0 | T114: =E114*G114 -> 180000 | X114: =ROUNDUP(L114*0.95,-3)*3 -> 657000 | Y114: =IF(X114>0,(X114-N114*3)/X114,0) -> 0.56073059 | AA114: =+ROUNDUP(L114*0.925,-3)*6 -> 1278000 | AB114: =IF(AA114>0,(AA114-N114*6)/AA114,0) -> 0.54835681 | AC114: =+E114*AD114/12 -> 414000 | AD114: =+ROUNDUP(L114*0.9,-3)*12 -> 2484000 | AE114: =IF(AD114>0,(AD114-N114*12)/AD114,0) -> 0.5352657
A115: Chompa Capucha | B115: S | C115: Plomo Plata | D115: Pecho | E115: 1 | F115: =IF(A115="","",VLOOKUP(A115,'Cotizador Compras'!$A$5:$J$21,2,FALSE)) -> YOUR BRAND | G115: =IF(A115="","",VLOOKUP(A115,'Cotizador Compras'!$A$5:$J$21,3,FALSE)) -> 90000 | H115: =IF(OR(A115="",D115=""),"",IF(D115="Sin estampar",0,IF(D115="Pecho",VLOOKUP(A115,'Cotizador Compras'!$A$5:$J$21,4,FALSE),IF(D115="Espalda",VLOOKUP(A115,'Cotizador Compras'!$A$5:$J$21,5,FALSE),VLOOKUP(A115,'Cotizador Compras'!$A$5:$J$21,4,FALSE)+VLOOKUP(A115,'Cotizador Compras'!$A$5:$J$21,5,FALSE))))) -> 3500 | I115: =IF(A115="","",VLOOKUP(A115,'Cotizador Compras'!$A$5:$J$21,6,FALSE)) -> 1700 | J115: =IF(A115="","",VLOOKUP(A115,'Cotizador Compras'!$A$5:$J$21,7,FALSE)) -> 1000 | K115: =IF(OR(A115="",E115=""),"",(G115+H115+I115+J115)*E115) -> 96200 | L115: =IF(A115="","",IF(D115="Sin estampar",VLOOKUP(A115,'Cotizador Compras'!$A$5:$J$21,8,FALSE),IF(D115="Pecho",VLOOKUP(A115,'Cotizador Compras'!$A$5:$J$21,10,FALSE),VLOOKUP(A115,'Cotizador Compras'!$A$5:$J$21,9,FALSE)))) -> 230000 | M115: =IF(OR(A115="",E115=""),"",L115*E115) -> 230000 | N115: =+G115+H115+I115+J115 -> 96200 | O115: =IF(L115>0,(L115-N115)/L115,0) -> 0.58173913 | P115: =CONCATENATE(A115," ",B115," ",C115) -> Chompa Capucha S Plomo Plata | R115: =SUMIF($P$26:$P$159,Q115,$E$26:$E$159) -> 0 | T115: =E115*G115 -> 90000 | X115: =ROUNDUP(L115*0.95,-3)*3 -> 657000 | Y115: =IF(X115>0,(X115-N115*3)/X115,0) -> 0.56073059 | AA115: =+ROUNDUP(L115*0.925,-3)*6 -> 1278000 | AB115: =IF(AA115>0,(AA115-N115*6)/AA115,0) -> 0.54835681 | AC115: =+E115*AD115/12 -> 207000 | AD115: =+ROUNDUP(L115*0.9,-3)*12 -> 2484000 | AE115: =IF(AD115>0,(AD115-N115*12)/AD115,0) -> 0.5352657
A116: Chompa Capucha | B116: M | C116: Plomo Plata | D116: Pecho | E116: 2 | F116: =IF(A116="","",VLOOKUP(A116,'Cotizador Compras'!$A$5:$J$21,2,FALSE)) -> YOUR BRAND | G116: =IF(A116="","",VLOOKUP(A116,'Cotizador Compras'!$A$5:$J$21,3,FALSE)) -> 90000 | H116: =IF(OR(A116="",D116=""),"",IF(D116="Sin estampar",0,IF(D116="Pecho",VLOOKUP(A116,'Cotizador Compras'!$A$5:$J$21,4,FALSE),IF(D116="Espalda",VLOOKUP(A116,'Cotizador Compras'!$A$5:$J$21,5,FALSE),VLOOKUP(A116,'Cotizador Compras'!$A$5:$J$21,4,FALSE)+VLOOKUP(A116,'Cotizador Compras'!$A$5:$J$21,5,FALSE))))) -> 3500 | I116: =IF(A116="","",VLOOKUP(A116,'Cotizador Compras'!$A$5:$J$21,6,FALSE)) -> 1700 | J116: =IF(A116="","",VLOOKUP(A116,'Cotizador Compras'!$A$5:$J$21,7,FALSE)) -> 1000 | K116: =IF(OR(A116="",E116=""),"",(G116+H116+I116+J116)*E116) -> 192400 | L116: =IF(A116="","",IF(D116="Sin estampar",VLOOKUP(A116,'Cotizador Compras'!$A$5:$J$21,8,FALSE),IF(D116="Pecho",VLOOKUP(A116,'Cotizador Compras'!$A$5:$J$21,10,FALSE),VLOOKUP(A116,'Cotizador Compras'!$A$5:$J$21,9,FALSE)))) -> 230000 | M116: =IF(OR(A116="",E116=""),"",L116*E116) -> 460000 | N116: =+G116+H116+I116+J116 -> 96200 | O116: =IF(L116>0,(L116-N116)/L116,0) -> 0.58173913 | P116: =CONCATENATE(A116," ",B116," ",C116) -> Chompa Capucha M Plomo Plata | R116: =SUMIF($P$26:$P$159,Q116,$E$26:$E$159) -> 0 | T116: =E116*G116 -> 180000 | X116: =ROUNDUP(L116*0.95,-3)*3 -> 657000 | Y116: =IF(X116>0,(X116-N116*3)/X116,0) -> 0.56073059 | AA116: =+ROUNDUP(L116*0.925,-3)*6 -> 1278000 | AB116: =IF(AA116>0,(AA116-N116*6)/AA116,0) -> 0.54835681 | AC116: =+E116*AD116/12 -> 414000 | AD116: =+ROUNDUP(L116*0.9,-3)*12 -> 2484000 | AE116: =IF(AD116>0,(AD116-N116*12)/AD116,0) -> 0.5352657
... A156: Pantaloneta | B156: XL | C156: Beige | D156: Sin estampar | E156: 4 | F156: =IF(A156="","",VLOOKUP(A156,'Cotizador Compras'!$A$5:$J$21,2,FALSE)) -> AUREN | G156: =IF(A156="","",VLOOKUP(A156,'Cotizador Compras'!$A$5:$J$21,3,FALSE)) -> 45000 | H156: =IF(OR(A156="",D156=""),"",IF(D156="Sin estampar",0,IF(D156="Pecho",VLOOKUP(A156,'Cotizador Compras'!$A$5:$J$21,4,FALSE),IF(D156="Espalda",VLOOKUP(A156,'Cotizador Compras'!$A$5:$J$21,5,FALSE),VLOOKUP(A156,'Cotizador Compras'!$A$5:$J$21,4,FALSE)+VLOOKUP(A156,'Cotizador Compras'!$A$5:$J$21,5,FALSE))))) -> 0 | I156: =IF(A156="","",VLOOKUP(A156,'Cotizador Compras'!$A$5:$J$21,6,FALSE)) -> 1700 | J156: =IF(A156="","",VLOOKUP(A156,'Cotizador Compras'!$A$5:$J$21,7,FALSE)) -> 1000 | K156: =IF(OR(A156="",E156=""),"",(G156+H156+I156+J156)*E156) -> 190800 | L156: =IF(A156="","",IF(D156="Sin estampar",VLOOKUP(A156,'Cotizador Compras'!$A$5:$J$21,8,FALSE),IF(D156="Pecho",VLOOKUP(A156,'Cotizador Compras'!$A$5:$J$21,10,FALSE),VLOOKUP(A156,'Cotizador Compras'!$A$5:$J$21,9,FALSE)))) -> 90000 | M156: =IF(OR(A156="",E156=""),"",L156*E156) -> 360000 | N156: =+G156+H156+I156+J156 -> 47700 | O156: =IF(L156>0,(L156-N156)/L156,0) -> 0.47 | P156: =CONCATENATE(A156," ",B156," ",C156) -> Pantaloneta XL Beige | R156: =SUMIF($P$26:$P$159,Q156,$E$26:$E$159) -> 0 | T156: =E156*G156 -> 180000 | X156: =ROUNDUP(L156*0.95,-3)*3 -> 258000 | Y156: =IF(X156>0,(X156-N156*3)/X156,0) -> 0.44534884 | AA156: =+ROUNDUP(L156*0.925,-3)*6 -> 504000 | AB156: =IF(AA156>0,(AA156-N156*6)/AA156,0) -> 0.43214286 | AC156: =+E156*AD156/12 -> 324000 | AD156: =+ROUNDUP(L156*0.9,-3)*12 -> 972000 | AE156: =IF(AD156>0,(AD156-N156*12)/AD156,0) -> 0.41111111
A157: Camisa Réplica Y/Out | B157: M | D157: Sin estampar | E157: 3 | F157: =IF(A157="","",VLOOKUP(A157,'Cotizador Compras'!$A$5:$J$21,2,FALSE)) -> BRACOR | G157: =IF(A157="","",VLOOKUP(A157,'Cotizador Compras'!$A$5:$J$21,3,FALSE)) -> 60000 | H157: =IF(OR(A157="",D157=""),"",IF(D157="Sin estampar",0,IF(D157="Pecho",VLOOKUP(A157,'Cotizador Compras'!$A$5:$J$21,4,FALSE),IF(D157="Espalda",VLOOKUP(A157,'Cotizador Compras'!$A$5:$J$21,5,FALSE),VLOOKUP(A157,'Cotizador Compras'!$A$5:$J$21,4,FALSE)+VLOOKUP(A157,'Cotizador Compras'!$A$5:$J$21,5,FALSE))))) -> 0 | I157: =IF(A157="","",VLOOKUP(A157,'Cotizador Compras'!$A$5:$J$21,6,FALSE)) | J157: =IF(A157="","",VLOOKUP(A157,'Cotizador Compras'!$A$5:$J$21,7,FALSE)) -> 1000 | K157: =IF(OR(A157="",E157=""),"",(G157+H157+I157+J157)*E157) -> 183000 | L157: =IF(A157="","",IF(D157="Sin estampar",VLOOKUP(A157,'Cotizador Compras'!$A$5:$J$21,8,FALSE),IF(D157="Pecho",VLOOKUP(A157,'Cotizador Compras'!$A$5:$J$21,10,FALSE),VLOOKUP(A157,'Cotizador Compras'!$A$5:$J$21,9,FALSE)))) -> 75000 | M157: =IF(OR(A157="",E157=""),"",L157*E157) -> 225000 | N157: =+G157+H157+I157+J157 -> 61000 | O157: =IF(L157>0,(L157-N157)/L157,0) -> 0.18666667 | P157: =CONCATENATE(A157," ",B157," ",C157) -> Camisa Réplica Y/Out M | R157: =SUMIF($P$26:$P$159,Q157,$E$26:$E$159) -> 0 | T157: =E157*G157 -> 180000 | X157: =ROUNDUP(L157*0.95,-3)*3 -> 216000 | Y157: =IF(X157>0,(X157-N157*3)/X157,0) -> 0.15277778 | AA157: =+ROUNDUP(L157*0.925,-3)*6 -> 420000 | AB157: =IF(AA157>0,(AA157-N157*6)/AA157,0) -> 0.12857143 | AC157: =+E157*AD157/12 -> 204000 | AD157: =+ROUNDUP(L157*0.9,-3)*12 -> 816000 | AE157: =IF(AD157>0,(AD157-N157*12)/AD157,0) -> 0.10294118
A158: Camisa Réplica Y/Out | B158: L | D158: Sin estampar | E158: 3 | F158: =IF(A158="","",VLOOKUP(A158,'Cotizador Compras'!$A$5:$J$21,2,FALSE)) -> BRACOR | G158: =IF(A158="","",VLOOKUP(A158,'Cotizador Compras'!$A$5:$J$21,3,FALSE)) -> 60000 | H158: =IF(OR(A158="",D158=""),"",IF(D158="Sin estampar",0,IF(D158="Pecho",VLOOKUP(A158,'Cotizador Compras'!$A$5:$J$21,4,FALSE),IF(D158="Espalda",VLOOKUP(A158,'Cotizador Compras'!$A$5:$J$21,5,FALSE),VLOOKUP(A158,'Cotizador Compras'!$A$5:$J$21,4,FALSE)+VLOOKUP(A158,'Cotizador Compras'!$A$5:$J$21,5,FALSE))))) -> 0 | I158: =IF(A158="","",VLOOKUP(A158,'Cotizador Compras'!$A$5:$J$21,6,FALSE)) | J158: =IF(A158="","",VLOOKUP(A158,'Cotizador Compras'!$A$5:$J$21,7,FALSE)) -> 1000 | K158: =IF(OR(A158="",E158=""),"",(G158+H158+I158+J158)*E158) -> 183000 | L158: =IF(A158="","",IF(D158="Sin estampar",VLOOKUP(A158,'Cotizador Compras'!$A$5:$J$21,8,FALSE),IF(D158="Pecho",VLOOKUP(A158,'Cotizador Compras'!$A$5:$J$21,10,FALSE),VLOOKUP(A158,'Cotizador Compras'!$A$5:$J$21,9,FALSE)))) -> 75000 | M158: =IF(OR(A158="",E158=""),"",L158*E158) -> 225000 | N158: =+G158+H158+I158+J158 -> 61000 | O158: =IF(L158>0,(L158-N158)/L158,0) -> 0.18666667 | P158: =CONCATENATE(A158," ",B158," ",C158) -> Camisa Réplica Y/Out L | R158: =SUMIF($P$26:$P$159,Q158,$E$26:$E$159) -> 0 | T158: =E158*G158 -> 180000 | X158: =ROUNDUP(L158*0.95,-3)*3 -> 216000 | Y158: =IF(X158>0,(X158-N158*3)/X158,0) -> 0.15277778 | AA158: =+ROUNDUP(L158*0.925,-3)*6 -> 420000 | AB158: =IF(AA158>0,(AA158-N158*6)/AA158,0) -> 0.12857143 | AC158: =+E158*AD158/12 -> 204000 | AD158: =+ROUNDUP(L158*0.9,-3)*12 -> 816000 | AE158: =IF(AD158>0,(AD158-N158*12)/AD158,0) -> 0.10294118
A159: Camisa Réplica Y/Out | B159: XL | D159: Sin estampar | E159: 2 | F159: =IF(A159="","",VLOOKUP(A159,'Cotizador Compras'!$A$5:$J$21,2,FALSE)) -> BRACOR | G159: =IF(A159="","",VLOOKUP(A159,'Cotizador Compras'!$A$5:$J$21,3,FALSE)) -> 60000 | H159: =IF(OR(A159="",D159=""),"",IF(D159="Sin estampar",0,IF(D159="Pecho",VLOOKUP(A159,'Cotizador Compras'!$A$5:$J$21,4,FALSE),IF(D159="Espalda",VLOOKUP(A159,'Cotizador Compras'!$A$5:$J$21,5,FALSE),VLOOKUP(A159,'Cotizador Compras'!$A$5:$J$21,4,FALSE)+VLOOKUP(A159,'Cotizador Compras'!$A$5:$J$21,5,FALSE))))) -> 0 | I159: =IF(A159="","",VLOOKUP(A159,'Cotizador Compras'!$A$5:$J$21,6,FALSE)) | J159: =IF(A159="","",VLOOKUP(A159,'Cotizador Compras'!$A$5:$J$21,7,FALSE)) -> 1000 | K159: =IF(OR(A159="",E159=""),"",(G159+H159+I159+J159)*E159) -> 122000 | L159: =IF(A159="","",IF(D159="Sin estampar",VLOOKUP(A159,'Cotizador Compras'!$A$5:$J$21,8,FALSE),IF(D159="Pecho",VLOOKUP(A159,'Cotizador Compras'!$A$5:$J$21,10,FALSE),VLOOKUP(A159,'Cotizador Compras'!$A$5:$J$21,9,FALSE)))) -> 75000 | M159: =IF(OR(A159="",E159=""),"",L159*E159) -> 150000 | N159: =+G159+H159+I159+J159 -> 61000 | O159: =IF(L159>0,(L159-N159)/L159,0) -> 0.18666667 | P159: =CONCATENATE(A159," ",B159," ",C159) -> Camisa Réplica Y/Out XL | R159: =SUMIF($P$26:$P$159,Q159,$E$26:$E$159) -> 0 | T159: =E159*G159 -> 120000 | X159: =ROUNDUP(L159*0.95,-3)*3 -> 216000 | Y159: =IF(X159>0,(X159-N159*3)/X159,0) -> 0.15277778 | AA159: =+ROUNDUP(L159*0.925,-3)*6 -> 420000 | AB159: =IF(AA159>0,(AA159-N159*6)/AA159,0) -> 0.12857143 | AC159: =+E159*AD159/12 -> 136000 | AD159: =+ROUNDUP(L159*0.9,-3)*12 -> 816000 | AE159: =IF(AD159>0,(AD159-N159*12)/AD159,0) -> 0.10294118
A160: Camisa Réplica 1.1 | B160: M | D160: Sin estampar | E160: 7 | F160: =IF(A160="","",VLOOKUP(A160,'Cotizador Compras'!$A$5:$J$21,2,FALSE)) -> BRACOR | G160: =IF(A160="","",VLOOKUP(A160,'Cotizador Compras'!$A$5:$J$21,3,FALSE)) -> 54000 | H160: =IF(OR(A160="",D160=""),"",IF(D160="Sin estampar",0,IF(D160="Pecho",VLOOKUP(A160,'Cotizador Compras'!$A$5:$J$21,4,FALSE),IF(D160="Espalda",VLOOKUP(A160,'Cotizador Compras'!$A$5:$J$21,5,FALSE),VLOOKUP(A160,'Cotizador Compras'!$A$5:$J$21,4,FALSE)+VLOOKUP(A160,'Cotizador Compras'!$A$5:$J$21,5,FALSE))))) -> 0 | I160: =IF(A160="","",VLOOKUP(A160,'Cotizador Compras'!$A$5:$J$21,6,FALSE)) | J160: =IF(A160="","",VLOOKUP(A160,'Cotizador Compras'!$A$5:$J$21,7,FALSE)) -> 1000 | K160: =IF(OR(A160="",E160=""),"",(G160+H160+I160+J160)*E160) -> 385000 | L160: =IF(A160="","",IF(D160="Sin estampar",VLOOKUP(A160,'Cotizador Compras'!$A$5:$J$21,8,FALSE),IF(D160="Pecho",VLOOKUP(A160,'Cotizador Compras'!$A$5:$J$21,10,FALSE),VLOOKUP(A160,'Cotizador Compras'!$A$5:$J$21,9,FALSE)))) -> 75000 | M160: =IF(OR(A160="",E160=""),"",L160*E160) -> 525000 | N160: =+G160+H160+I160+J160 -> 55000 | O160: =IF(L160>0,(L160-N160)/L160,0) -> 0.26666667 | P160: =CONCATENATE(A160," ",B160," ",C160) -> Camisa Réplica 1.1 M | R160: =SUMIF($P$26:$P$159,Q160,$E$26:$E$159) -> 0 | T160: =E160*G160 -> 378000 | X160: =ROUNDUP(L160*0.95,-3)*3 -> 216000 | Y160: =IF(X160>0,(X160-N160*3)/X160,0) -> 0.23611111 | AA160: =+ROUNDUP(L160*0.925,-3)*6 -> 420000 | AB160: =IF(AA160>0,(AA160-N160*6)/AA160,0) -> 0.21428571 | AC160: =+E160*AD160/12 -> 476000 | AD160: =+ROUNDUP(L160*0.9,-3)*12 -> 816000 | AE160: =IF(AD160>0,(AD160-N160*12)/AD160,0) -> 0.19117647
A161: Camisa Réplica 1.1 | B161: L | D161: Sin estampar | E161: 7 | F161: =IF(A161="","",VLOOKUP(A161,'Cotizador Compras'!$A$5:$J$21,2,FALSE)) -> BRACOR | G161: =IF(A161="","",VLOOKUP(A161,'Cotizador Compras'!$A$5:$J$21,3,FALSE)) -> 54000 | H161: =IF(OR(A161="",D161=""),"",IF(D161="Sin estampar",0,IF(D161="Pecho",VLOOKUP(A161,'Cotizador Compras'!$A$5:$J$21,4,FALSE),IF(D161="Espalda",VLOOKUP(A161,'Cotizador Compras'!$A$5:$J$21,5,FALSE),VLOOKUP(A161,'Cotizador Compras'!$A$5:$J$21,4,FALSE)+VLOOKUP(A161,'Cotizador Compras'!$A$5:$J$21,5,FALSE))))) -> 0 | I161: =IF(A161="","",VLOOKUP(A161,'Cotizador Compras'!$A$5:$J$21,6,FALSE)) | J161: =IF(A161="","",VLOOKUP(A161,'Cotizador Compras'!$A$5:$J$21,7,FALSE)) -> 1000 | K161: =IF(OR(A161="",E161=""),"",(G161+H161+I161+J161)*E161) -> 385000 | L161: =IF(A161="","",IF(D161="Sin estampar",VLOOKUP(A161,'Cotizador Compras'!$A$5:$J$21,8,FALSE),IF(D161="Pecho",VLOOKUP(A161,'Cotizador Compras'!$A$5:$J$21,10,FALSE),VLOOKUP(A161,'Cotizador Compras'!$A$5:$J$21,9,FALSE)))) -> 75000 | M161: =IF(OR(A161="",E161=""),"",L161*E161) -> 525000 | N161: =+G161+H161+I161+J161 -> 55000 | O161: =IF(L161>0,(L161-N161)/L161,0) -> 0.26666667 | P161: =CONCATENATE(A161," ",B161," ",C161) -> Camisa Réplica 1.1 L | R161: =SUMIF($P$26:$P$159,Q161,$E$26:$E$159) -> 0 | T161: =E161*G161 -> 378000 | X161: =ROUNDUP(L161*0.95,-3)*3 -> 216000 | Y161: =IF(X161>0,(X161-N161*3)/X161,0) -> 0.23611111 | AA161: =+ROUNDUP(L161*0.925,-3)*6 -> 420000 | AB161: =IF(AA161>0,(AA161-N161*6)/AA161,0) -> 0.21428571 | AC161: =+E161*AD161/12 -> 476000 | AD161: =+ROUNDUP(L161*0.9,-3)*12 -> 816000 | AE161: =IF(AD161>0,(AD161-N161*12)/AD161,0) -> 0.19117647
A162: Camisa Réplica 1.1 | B162: XL | D162: Sin estampar | E162: 8 | F162: =IF(A162="","",VLOOKUP(A162,'Cotizador Compras'!$A$5:$J$21,2,FALSE)) -> BRACOR | G162: =IF(A162="","",VLOOKUP(A162,'Cotizador Compras'!$A$5:$J$21,3,FALSE)) -> 54000 | H162: =IF(OR(A162="",D162=""),"",IF(D162="Sin estampar",0,IF(D162="Pecho",VLOOKUP(A162,'Cotizador Compras'!$A$5:$J$21,4,FALSE),IF(D162="Espalda",VLOOKUP(A162,'Cotizador Compras'!$A$5:$J$21,5,FALSE),VLOOKUP(A162,'Cotizador Compras'!$A$5:$J$21,4,FALSE)+VLOOKUP(A162,'Cotizador Compras'!$A$5:$J$21,5,FALSE))))) -> 0 | I162: =IF(A162="","",VLOOKUP(A162,'Cotizador Compras'!$A$5:$J$21,6,FALSE)) | J162: =IF(A162="","",VLOOKUP(A162,'Cotizador Compras'!$A$5:$J$21,7,FALSE)) -> 1000 | K162: =IF(OR(A162="",E162=""),"",(G162+H162+I162+J162)*E162) -> 440000 | L162: =IF(A162="","",IF(D162="Sin estampar",VLOOKUP(A162,'Cotizador Compras'!$A$5:$J$21,8,FALSE),IF(D162="Pecho",VLOOKUP(A162,'Cotizador Compras'!$A$5:$J$21,10,FALSE),VLOOKUP(A162,'Cotizador Compras'!$A$5:$J$21,9,FALSE)))) -> 75000 | M162: =IF(OR(A162="",E162=""),"",L162*E162) -> 600000 | N162: =+G162+H162+I162+J162 -> 55000 | O162: =IF(L162>0,(L162-N162)/L162,0) -> 0.26666667 | P162: =CONCATENATE(A162," ",B162," ",C162) -> Camisa Réplica 1.1 XL | R162: =SUMIF($P$26:$P$159,Q162,$E$26:$E$159) -> 0 | T162: =E162*G162 -> 432000 | X162: =ROUNDUP(L162*0.95,-3)*3 -> 216000 | Y162: =IF(X162>0,(X162-N162*3)/X162,0) -> 0.23611111 | AA162: =+ROUNDUP(L162*0.925,-3)*6 -> 420000 | AB162: =IF(AA162>0,(AA162-N162*6)/AA162,0) -> 0.21428571 | AC162: =+E162*AD162/12 -> 544000 | AD162: =+ROUNDUP(L162*0.9,-3)*12 -> 816000 | AE162: =IF(AD162>0,(AD162-N162*12)/AD162,0) -> 0.19117647
F163: =IF(A163="","",VLOOKUP(A163,'Cotizador Compras'!$A$5:$J$21,2,FALSE)) | G163: =IF(A163="","",VLOOKUP(A163,'Cotizador Compras'!$A$5:$J$21,3,FALSE)) | H163: =IF(OR(A163="",D163=""),"",IF(D163="Sin estampar",0,IF(D163="Pecho",VLOOKUP(A163,'Cotizador Compras'!$A$5:$J$21,4,FALSE),IF(D163="Espalda",VLOOKUP(A163,'Cotizador Compras'!$A$5:$J$21,5,FALSE),VLOOKUP(A163,'Cotizador Compras'!$A$5:$J$21,4,FALSE)+VLOOKUP(A163,'Cotizador Compras'!$A$5:$J$21,5,FALSE))))) | I163: =IF(A163="","",VLOOKUP(A163,'Cotizador Compras'!$A$5:$J$21,6,FALSE)) | J163: =IF(A163="","",VLOOKUP(A163,'Cotizador Compras'!$A$5:$J$21,7,FALSE)) | K163: =IF(OR(A163="",E163=""),"",(G163+H163+I163+J163)*E163) | L163: =IF(A163="","",IF(D163="Sin estampar",VLOOKUP(A163,'Cotizador Compras'!$A$5:$J$21,8,FALSE),IF(D163="Pecho",VLOOKUP(A163,'Cotizador Compras'!$A$5:$J$21,10,FALSE),VLOOKUP(A163,'Cotizador Compras'!$A$5:$J$21,9,FALSE)))) | M163: =IF(OR(A163="",E163=""),"",L163*E163) | P163: =CONCATENATE(A163," ",B163," ",C163) | R163: =SUMIF($P$26:$P$159,Q163,$E$26:$E$159) -> 0
A165: TOTALES | E165: =SUM(E26:E163) -> 342 | G165: =SUMPRODUCT(G26:G163,E26:E163) -> 18132000 | H165: =SUMPRODUCT(H26:H163,E26:E163) -> 486500 | I165: =SUMPRODUCT(I26:I163,E26:E163) -> 530400 | J165: =SUMPRODUCT(J26:J163,E26:E163) -> 342000 | K165: =+SUM(K26:K162) -> 19490900 | M165: =+SUM(M26:M162) -> 39855000
M167: =+M165-K165 -> 20364100
A168: RESUMEN
A170: Total Unidades: | B170: =E165 -> 342 | D170: DESGLOSE DE COSTOS: | H170: PROVEEDOR | I170: TOTAL | J170: PAGO | K170: Cada uno
A171: Inversión Total (Costo): | B171: =+E175 -> 19490900 | D171: • Prendas: | E171: =G165 -> 18132000 | F171: =+E171/$E$175 -> 0.93028028 | H171: AUREN | I171: =+SUMIF($F$26:$F$162,H171,$T$26:$T$162) -> 5820000 | J171: CREDITO | K171: =I171/3 -> 1940000
A172: Venta Esperada: | B172: =+M165 -> 39855000 | D172: • Estampado: | E172: =H165 -> 486500 | F172: =+E172/$E$175 -> 0.024960366 | H172: YOUR BRAND | I172: =+SUMIF($F$26:$F$162,H172,$T$26:$T$162) -> 10644000 | J172: TC | K172: =I172/3 -> 3548000
A173: Ganancia Bruta Estimada: | B173: =+B172-B171 -> 20364100 | D173: • Etiquetas: | E173: =I165 -> 530400 | F173: =+E173/$E$175 -> 0.027212699 | H173: BRACOR | I173: =+SUMIF($F$26:$F$162,H173,$T$26:$T$162) -> 1668000 | J173: CREDITO | K173: =I173/3 -> 556000
A174: Margen Bruto %: | B174: =IF(B172>0,(B172-B171)/B172,0) -> 0.51095471 | D174: • Empaque: | E174: =J165 -> 342000 | F174: =+E174/$E$175 -> 0.01754665 | I174: =SUM(I171:I173) -> 18132000 | K174: =I174/3 -> 6044000
D175: TOTAL: | E175: =+SUM(E171:E174) -> 19490900
D176: TOTAL SIN PRENDAS: | E176: =+E175-E171 -> 1358900
D177: Cada Uno | E177: =E175/3 -> 6496966.7

Sheet Punto Equilibrio - Proyeccion
A1: PUNTO DE EQUILIBRIO
A2: Cuanto hay que vender para no perder
A3: SUPUESTOS
A5: Costos fijos mensuales | B5: ='Costos Fijos'!B12 -> 1914900
A6: Precio promedio de venta por prenda
A7: Costo promedio por prenda
A8: Margen bruto promedio por prenda
A10: CÁLCULO PUNTO DE EQUILIBRIO
A12: Prendas a vender por mes para cubrir costos
A13: Prendas a vender por día (26 días/mes)
A14: Ventas mensuales mínimas
A17: PROYECCIÓN FLUJO DE CAJA - 6 MESES
A19: Escenario de ventas (prendas/día) | B19: =+'Punto Equilibrio'!B29+2 -> #REF! | C19: Cambiar
B21: 46067 | C21: 46082 | D21: 46113 | E21: 46143 | F21: 46174 | G21: 46204 | H21: TOTAL
A22: Días operativos | B22: 12 | C22: 26 | D22: 26 | E22: 26 | F22: 26 | G22: 26 | H22: =SUM(B22:G22) -> 142
A23: Prendas vendidas | B23: =$B$19*B22 -> #REF! | C23: =$B$19*C22 -> #REF! | D23: =$B$19*D22 -> #REF! | E23: =$B$19*E22 -> #REF! | F23: =$B$19*F22 -> #REF! | G23: =$B$19*G22 -> #REF! | H23: =SUM(B23:G23) -> #REF!
A25: INGRESOS
A26: Ventas brutas | B26: =B23*'Margen Producto'!$C$27 -> #REF! | C26: =C23*'Margen Producto'!$C$27 -> #REF! | D26: =D23*'Margen Producto'!$C$27 -> #REF! | E26: =E23*'Margen Producto'!$C$27 -> #REF! | F26: =F23*'Margen Producto'!$C$27 -> #REF! | G26: =G23*'Margen Producto'!$C$27 -> #REF! | H26: =SUM(B26:G26) -> #REF!
A28: EGRESOS
A29: Costo mercancía | B29: =B23*'Margen Producto'!$B$27 -> #REF! | C29: =C23*'Margen Producto'!$B$27 -> #REF! | D29: =D23*'Margen Producto'!$B$27 -> #REF! | E29: =E23*'Margen Producto'!$B$27 -> #REF! | F29: =F23*'Margen Producto'!$B$27 -> #REF! | G29: =G23*'Margen Producto'!$B$27 -> #REF! | H29: =SUM(B29:G29) -> #REF!
A30: Costo Estampaciones y empaques (8% merch) | B30: =B29*8% -> #REF! | C30: =C29*8% -> #REF! | D30: =D29*8% -> #REF! | E30: =E29*8% -> #REF! | F30: =F29*8% -> #REF! | G30: =G29*8% -> #REF! | H30: =SUM(B30:G30) -> #REF!
A31: Costos fijos | B31: ='Costos Fijos'!$B$13*B22/30 -> 0 | C31: ='Costos Fijos'!$B$13 | D31: ='Costos Fijos'!$B$13 | E31: ='Costos Fijos'!$B$13 | F31: ='Costos Fijos'!$B$13 | G31: ='Costos Fijos'!$B$13 | H31: =SUM(B31:G31) -> 0
A32: Inversión inicial | B32: =+'Inversión Inicial'!B27-'Inversión Inicial'!B21 -> #REF! | H32: =SUM(B32:G32) -> #REF!
A33: Total egresos | B33: =B29+B31+B32+B30 -> #REF! | C33: =C29+C31+C32+C30 -> #REF! | D33: =D29+D31+D32+D30 -> #REF! | E33: =E29+E31+E32+E30 -> #REF! | F33: =F29+F31+F32+F30 -> #REF! | G33: =G29+G31+G32+G30 -> #REF! | H33: =SUM(B33:G33) -> #REF!
A35: RESULTADO
A36: Utilidad mensual | B36: =B26-B33 -> #REF! | C36: =C26-C33 -> #REF! | D36: =D26-D33 -> #REF! | E36: =E26-E33 -> #REF! | F36: =F26-F33 -> #REF! | G36: =G26-G33 -> #REF! | H36: =SUM(B36:G36) -> #REF!
A37: Utilidad por socio (3) | B37: =B36/3 -> #REF! | C37: =C36/3 -> #REF! | D37: =D36/3 -> #REF! | E37: =E36/3 -> #REF! | F37: =F36/3 -> #REF! | G37: =G36/3 -> #REF! | H37: =H36/3 -> #REF!
